{
  "query": "双性人 小说",
  "language": "zh-cn",
  "geo_location": "cn",
  "totalPages": 3,
  "endpoint": "/search",
  "date": "2024-11-04T00:15:57.852576",
  "results": [
    {
      "searchParameters": {
        "q": "双性人 小说",
        "gl": "cn",
        "hl": "zh-cn",
        "type": "search",
        "num": 100,
        "page": 1,
        "engine": "google"
      },
      "organic": [
        {
          "title": "bl双性人小说 - 起点中文",
          "link": "https://www.qidian.com/ask/tzfrhfowz",
          "snippet": "以下是一些涉及双性人题材的小说： - 《双性》：科幻类型小说，在起点文学网首发，讲述主人公秦枫卷入萨尔星身世漩涡，借助外星双性文明技术，能在男女之间转化成为双性人的故事 ...",
          "position": 1
        },
        {
          "title": "双性_好看的双性小说 - 肉肉屋",
          "link": "https://m.rourouwu.de/tag/sx/",
          "snippet": "双性. 【耽美】痴汉让人厌恶(双性) - 远上白云间; 【耽美】突然站年下(双性) - 陆任逸; 【耽美】为妓(双性) - 司马青衫湿; 【耽美】闻啼鸟音痴(双性ntr) - 天痕壹月 ...",
          "position": 2
        },
        {
          "title": "双性生子高H_BL小说|耽美小说_腐小书",
          "link": "https://fuxs2.cc/plus/hsearch.php?keyword=%E5%8F%8C%E6%80%A7++%E7%94%9F%E5%AD%90++%E9%AB%98H",
          "snippet": "原创男男古代高H 正剧美人受高H 骄傲自负的杨家小公子被一街边破烂算卦的说成雌雄同体，天生眉骨，淫浪至极。傲娇小公子恼羞成怒的让下人将算卦的暴打一顿，却不料竟 ...",
          "position": 3
        },
        {
          "title": "双性人的恋爱小说 - 起点中文",
          "link": "https://m.qidian.com/ask/tqbpeiqzfxabp",
          "snippet": "以下是几本双性人甜宠小说的推荐： 1. 《快穿攻略：宿主今天又恋爱了》讲述了一个十八线小明星沈妄川因为意外变成了植物人，被迫与主角恋爱。这本小说被称为甜宠无虐，文笔好人 ...",
          "position": 4
        },
        {
          "title": "双性小说_热门双性排行榜- 蓝海搜书",
          "link": "https://www.letsboox.com/s/%E5%8F%8C%E6%80%A7",
          "snippet": "这篇文看名字都戳我萌点，君臣，双性生子，文案看起来也不错，霸道痴情攻X风流美人受但是这篇文的情节和虐点，简直是看的我要吐血，不能再让人糟心好吗！ 真的我以前看文觉得我 ...",
          "position": 5
        },
        {
          "title": "双性_BL小说|耽美小说_腐小书",
          "link": "http://www.fxshu.top/tags.php?/%E5%8F%8C%E6%80%A7/5/",
          "snippet": "腐小书提供双性系列全本完结耽美小说，双性系列耽美小说列表。",
          "position": 6
        },
        {
          "title": "双性 - 耽美XYZ",
          "link": "https://www.danmei.xyz/tag/bisexual",
          "snippet": "简介：双性心机受X温柔攻，养兄弟年上，年差11岁微博：小甜饼量产师w肉文短篇双性温柔哥哥攻X弟弟诱受许峰檐… 阅读更多. 分类BL肉文、 耽美小说 标签双性、 现代、 肉文 发表 ...",
          "position": 7
        },
        {
          "title": "双性_BL小说|耽美小说_腐小书",
          "link": "http://www.fxshu.top/tags.php?/%E5%8F%8C%E6%80%A7/3/",
          "snippet": "作为双性人，陆橙自幼父母双亡，寄居在表哥陆博唯家。从来没有人在乎他，没有人重视他。陆橙高中的时候经常帮表哥跑腿，在这个过程中爱上了... 2022-04-18 10:10:23 ...",
          "position": 8
        },
        {
          "title": "搜索结果_求双性人bl文 - 百度知道",
          "link": "https://zhidao.baidu.com/index/?word=%E6%B1%82%E5%8F%8C%E6%80%A7%E4%BA%BAbl%E6%96%87&from=qb&samplow_val=917",
          "snippet": "一部古代bl小说:小攻是双性人,曾任武林盟主,小受是大夫,小攻生了好几... 绝对的《花容天下》《十里红莲艳酒》（花容天下的第二部）《月上 ...",
          "position": 9
        },
        {
          "title": "《双性人巴尔班》读后感 - 豆瓣",
          "link": "https://m.douban.com/book/review/14632890/",
          "snippet": "本书包含了双性人巴尔班的遗书《我的回忆》，以及围绕双性人而展开的相关讨论。我是在图书馆无意中看到这本书的，双性人这个名词在黄色小说里是经久不衰 ...",
          "date": "2022年9月6日",
          "position": 10
        },
        {
          "title": "双性人小说1_郁郁 - 新浪网站导航",
          "link": "https://blog.sina.com.cn/s/blog_4cd4aaec010008pt.html",
          "snippet": "双性人 小说1. (2007-04-20 23:41:02). 标签：. 爱情小说. 双性人. 我是好玩才写的 那个名词是很久以前看到. 第一章 遗弃. 在我的17岁那年以前,我从来不认为自己和其他 ...",
          "position": 11
        },
        {
          "title": "双性人 - 番茄小说",
          "link": "https://fanqienovel.com/page/7283858835108793396",
          "snippet": "番茄小说提供双性人完整版在线免费阅读，精彩小说尽在番茄小说网。讲述了清未时代发生了一件奇怪的双性人格分裂，李可和李东的故事李东去世后他家发生了奇怪的事情李可 ...",
          "position": 12
        },
        {
          "title": "现代双性耽美小说 - QQ阅读",
          "link": "https://ubook.reader.qq.com/ask/keyword/skdymikgyc",
          "snippet": "经典重生现代耽美小说推荐包括《重生之豁然》和《东山再起[娱乐圈]》。《重生之豁然》是由缘何故所著，故...",
          "position": 13
        },
        {
          "title": "双性_BL小说|耽美小说_腐小书",
          "link": "http://www.fxshu.cc/tags.php?/%E5%8F%8C%E6%80%A7/",
          "snippet": "老婆别怕，我不是什么好人。 裴黎意外获得了一项特异功能读心术。他很痛苦，因为他一点也不想知道陌生人的秘密。 直到在一次 ...",
          "position": 14
        },
        {
          "title": "双性人小生子小说- 喜马拉雅手机版",
          "link": "https://m.ximalaya.com/ask/t1779372",
          "snippet": "下文中千叶为双重的女主角，栗为男主角。高晓媛和许安还是他们。 千叶被人催眠过好几次，然后被带到高晓媛（依旧还是看不见）那里。后来他们4个人根据一个乐谱分析，在千叶和栗 ...",
          "position": 15
        },
        {
          "title": "多面人夫（肉合集，双性，**，乱X等） - 笔趣阁",
          "link": "https://m.bqgl.cc/look/137476/",
          "snippet": "内容简介: 双性粗口黄暴短篇合集（攻全部大jj猛男，受各种类型风骚双性，有人兽，古风，年下，父子乱伦等等，请随意品尝）第一个故事：直男警察和退伍兵哥的纯爱。",
          "position": 16
        },
        {
          "title": "双性_BL小说|耽美小说_腐小书",
          "link": "https://www.jiqinw.com/tags.php?/%E5%8F%8C%E6%80%A7/8/",
          "snippet": "陆詹庭的母亲亡故后，只有舅舅对他好，舅舅帮他做饭，哄他睡觉将军府的下人嫌他是庶子而虐待他的时候，也是舅舅帮他据理力争。 所以陆詹庭的目标就是等考取了功名，做了大官， ...",
          "position": 17
        },
        {
          "title": "妹妹是双性人我带她去治疗, 却因此失去男友怨恨全都归咎于我| #小说 ...",
          "link": "https://www.youtube.com/watch?v=iCfTt3ZM7gs",
          "snippet": "每天更新精彩的短篇小说喜歡的話不要忘記幫我按贊訂閱分享 記得打開小 哦#小说#短篇 ...\n时长： 19:00\n发布时间： 2024年8月16日",
          "date": "2024年8月16日",
          "position": 18
        },
        {
          "title": "双性_百度百科",
          "link": "https://baike.baidu.com/item/%E5%8F%8C%E6%80%A7",
          "snippet": "... 小说，由起点文学网首发，讲述的是主人公秦枫被卷入了萨尔星的身世漩涡中，通过这个外星双性文明的技术， ... 双性人的故事。",
          "position": 19
        },
        {
          "title": "既有子宫卵巢，又有睾丸阴茎？双性人的生殖构造到底是怎样的？",
          "link": "https://i.ifeng.com/c/8CfmMRaGGbu",
          "snippet": "性别在大多数人的常识中，不过就是非男即女。 但其实在现实社会中，还有我们想象不到的第三性——间性（即雌雄同体性），也就是民间流传的“双性人”。",
          "date": "2022年1月10日",
          "position": 20
        },
        {
          "title": "【文字科普】大家对双性人的常见问题 - bilibili",
          "link": "https://www.bilibili.com/read/cv11902988/",
          "snippet": "... 双性人上厕所是站着还是蹲着？答：这个要看生理构造，不是所有双性人 ... 小说法国米歇尔·福柯《双性人巴尔班》、加拿大凯特琳·温特《安娜贝尔》 ...",
          "date": "2021年6月27日",
          "position": 21
        },
        {
          "title": "双性人巴尔班- 图书- 豆瓣",
          "link": "https://m.douban.com/book/subject/30422637/",
          "snippet": "双性人巴尔班豆瓣评分：7.9 简介：1868年，位于巴黎贫民区的医学院街，一间简陋、肮脏的阁楼，一名男性自杀身亡，旁边放着一本自传的手稿。1 897年，这本自传以《阿莱克西纳·B ...",
          "currency": "$",
          "price": 28.54,
          "position": 22
        },
        {
          "title": "模范性伴侣（双jj/双性人/生子产乳）-v文 - 爱阅小说网",
          "link": "https://m.aiyue9.com/index/119789/",
          "snippet": "... 快更新在线阅读。模范性伴侣（双jj/双性人/生子产乳）-v文全文免费阅读是一本情节与文笔两者兼备的女生小说,看小说不会产生广告,在浏览阅读的过程中,加载流畅！",
          "position": 23
        },
        {
          "title": "双性人杨愠之小说- 喜马拉雅手机版",
          "link": "https://m.ximalaya.com/ask/t1652771",
          "snippet": "双性人杨愠之小说 ... “人不知而不愠，不亦君子乎。” 所谓“愠”，就文字解释，是放在心中的怨恨，没有发出来，在内心中有烦厌、厌恶、讨厌、怨恨之感。 意思：别人不了解我，而我并 ...",
          "position": 24
        },
        {
          "title": "好看的双性小说 - PO18 脸红心跳",
          "link": "https://m.po18.xyz/tag/sx/",
          "snippet": "双性 · 【言情】偷妻（双性） - 冉尔 · 【耽美】【双性】军医难为 - 空凉的城 · 【耽美】【双性】折辱高傲 - 空凉的城 · 【耽美】【双性】情难自禁 - 空凉的城 · 【耽美】双性·都 ...",
          "position": 25
        },
        {
          "title": "间性人的自白：“我是一个会来月经的男孩” - BBC News 中文",
          "link": "https://www.bbc.com/zhongwen/simp/science-54970542",
          "snippet": "... 性别，世上其实有很多这些人。 间性人（Intersex，又称双性人、阴阳人）是一个概括性的词语，包含了超过40种不同的男女性别特征。有一些是荷尔蒙的 ...",
          "date": "2020年11月23日",
          "position": 26
        },
        {
          "title": "言情小说- 《双性人传说》泠泠碎玉 - 晋江文学城",
          "link": "http://www.jjwxc.net/onebook.php?novelid=1644285",
          "snippet": "《双性人传说》,泠泠碎玉,悲剧,主角：X ┃ 配角：H，花铃┃ 其它：双性人，爱情，幻想|最新更新:2012-10-11 11:06:43|作品积分：550983.",
          "date": "8天前",
          "position": 27
        },
        {
          "title": "双性恋- 维基百科，自由的百科全书",
          "link": "https://zh.wikipedia.org/zh-cn/%E5%8F%8C%E6%80%A7%E6%81%8B",
          "snippet": "它是三大主要性倾向分类之一，与异性恋、同性恋并列于性取向连续体之内。自认为双性恋者的人不一定会认为两性皆拥有一样的性吸引力；不少自认为双性恋者的 ...",
          "position": 28
        },
        {
          "title": "世界上真有“双性人”吗?｜豆瓣一周热门图书 - 搜狐",
          "link": "https://www.sohu.com/a/313062489_641855",
          "snippet": "本周，《双性人巴尔班》揭秘双性人不为人知的内心与生活；《女人无名》描写一位遭受性侵的女性20年来追寻真相与正义之路；夏初春末，让一本《汪老师的植物 ...",
          "date": "2019年5月10日",
          "position": 29
        },
        {
          "title": "羞*辱住在隔壁丈夫经常出差的双性人*妻 - 秒书屋",
          "link": "http://m.fzr6.com/book/104746/",
          "snippet": "... 双性人 ... 作者：鹿瞳之影分类：耽美小说: 状态：连载字数：319931: 更新：2023-07-08 19:34 ...",
          "position": 30
        },
        {
          "title": "热门双性壮汉排行榜- 蓝海搜书",
          "link": "https://www.letsboox.com/s/%E5%8F%8C%E6%80%A7%E5%A3%AE%E6%B1%89",
          "snippet": "乡下壮汉被名义上的豪门小叔子吃抹干净的故事十六不六原创小说- BL - 长篇- 完结古代- HE - 双性- 美强荤素均衡乡下来的壮汉老实人被迫嫁进豪门为病弱大少爷冲喜，却被二 ...",
          "position": 31
        },
        {
          "title": "模范性伴侣（双jj/双性人/生子产乳）-v文全文免费阅读 - 笔趣阁",
          "link": "https://m.tokew.com/bqg/105927/",
          "snippet": "笔趣阁为您提供《模范性伴侣（双jj/双性人/生子产乳）-v文》全文阅读，麦芽糖的小说《模范性伴侣（双jj/双性人/生子产乳）-v文》全文免费阅读精彩无极限，不来读是你的损失 ...",
          "position": 32
        },
        {
          "title": "双性小说",
          "link": "https://www.dmxs.org/tags-124-0.html",
          "snippet": "双性小说. 倾尽缠绵. 作者： 无欢也笑 2019-03-31. 温馨穿越、多人宠爱、有小 ... 性情人，黎向皖。 克制稳重攻x人qi双性you受短篇，ntr，放飞自我内容标签： 生子 ...",
          "position": 33
        },
        {
          "title": "双性人巴尔班- 福柯(法) - Google Books",
          "link": "https://books.google.com/books/about/%E5%8F%8C%E6%80%A7%E4%BA%BA%E5%B7%B4%E5%B0%94%E7%8F%AD.html?id=bMBOzQEACAAJ",
          "snippet": "... 小说女修道院丑闻,这是该故事在十九,二十世纪之交演绎化的版本.最后,埃里克·法桑的后记说明了重读巴尔班为自己赋予\"真实社会性别\"的这份重要叙述对于社会性别研究的 ...",
          "position": 34
        },
        {
          "title": "《我的双性人男友》稻草上的火鸡 - 晋江文学城",
          "link": "http://www.jjwxc.net/onebook.php?novelid=3334742",
          "snippet": "本站作品（专栏、小说、评论、贴子等）版权均为原创者所有，本站仅提供上传、存储及展示功能。本站所收录、展示内容及广告仅代表创作者观点，与本站立场无关。",
          "date": "2天前",
          "position": 35
        },
        {
          "title": "双性人纪事最新章节 - 懒人小说",
          "link": "http://m.lrxs.org/6_6654/",
          "snippet": "双性人纪事最新章节由网友提供，《双性人纪事》情节跌宕起伏、扣人心弦，是一本情节与文笔俱佳的精品小说，懒人小说免费提供双性人纪事最新清爽干净的 ...",
          "date": "2020年9月13日",
          "position": 36
        },
        {
          "title": "沦为奴（双性、猎奇） - 文海小说",
          "link": "http://m.zgzl.net/info_ndx7/",
          "snippet": "沦为奴（双性、猎奇）. 作者：风格风人. 点击：28980. 更新：2024/8/28 21:41:12. 最新 ...",
          "position": 37
        },
        {
          "title": "單身雙性人醫生被慢慢攻略的故事-カノンチヒロ｜Renta！亂搭",
          "link": "https://tw.myrenta.com/item/30362?srsltid=AfmBOoqRqyHGpJks3KHZ1SL8RCoaI6AfVd20UT5TeEMtoS2UzJoqJ3ky",
          "snippet": "時宗凪是一位雙性人婦產科醫生，他跟同樣是醫生的真田遼已經交往十幾年了。初次見面的時候，時宗跟真田的關係只有「研習醫生與認識的人的兒子」，但少年真田非常喜歡比他 ...",
          "position": 38
        },
        {
          "title": "竹馬發現我是雙性人的秘密，我立刻摀住他的嘴！不讓他說出去！",
          "link": "https://www.youtube.com/watch?v=Zzl3_rP9Xk0",
          "snippet": "竹馬發現我是雙性人的秘密，我立刻摀住他的嘴！不讓他說出去！ ，你給我看一下我就不說出去 ...\n时长： 22:22\n发布时间： 2024年8月16日",
          "date": "2024年8月16日",
          "position": 39
        },
        {
          "title": "被迫禁锢（双性/np） - 耽美小说",
          "link": "https://m.dm22.cc/info/176341/",
          "snippet": "内容简介: 叶蕴穿越到了一个可怕的世界，这个世界没有女人，只有男人和双儿。双儿外形相较男人普遍会娇小和清秀些，跟叶蕴原来世界的双性人一样，而叶蕴就是一个双性人，他 ...",
          "position": 40
        },
        {
          "title": "美味的双性室友最新章节",
          "link": "http://m.hfschunhua.com/xiaoshuo/118136/",
          "snippet": "美味的双性室友最新章节由网友提供，《美味的双性室友》目前更新258712字，剧情情节跌宕起伏、扣人心弦，是一本情节与文笔俱佳的耽美小说，第二书包免费提供美味的双性室友 ...",
          "position": 41
        },
        {
          "title": "（科普文章3） 什么是双性人？ - Bilibili",
          "link": "https://www.bilibili.com/read/cv22616963/",
          "snippet": "1、目前，双性人能否生孩子，还没有确定的回答，每个患者的具体情况不一样，需要到医生进行确诊。 2、如果是女性患者，可以进行生殖器移植治疗，手术顺利的话， ...",
          "date": "2023年3月24日",
          "position": 42
        },
        {
          "title": "双性-BL小说|耽美小说-腐小说",
          "link": "http://www.fuxsb.com/tags-209-1.html",
          "snippet": "我老婆就是世界上坠吊的！ 班上来转班生的那天，班长给程秋池说：看到中间那个人吗？祝淮，我们学校的高岭之 ...",
          "position": 43
        },
        {
          "title": "搜尋雙性 - 小說狂人",
          "link": "https://czbooks.net/hashtag/%E9%9B%99%E6%80%A7",
          "snippet": "鈣片男優的淫蕩生活[雙性]. 作者: 顧萌萌. 最新: 第49章. 2019-08-18. 2873; 561071. 已完結. 逼婚良緣. 作者: 甜心小喵喵. 最新: 第50章. 2020-04-09. 3166; 482569.",
          "position": 44
        },
        {
          "title": "多面人夫（肉合集，双性，**，乱X等）最新章节 - CP小说网",
          "link": "https://m.cpafarm.com/book/142174/",
          "snippet": "多面人夫（肉合集，双性，**，乱X等）最新章节由网友提供，《多面人夫（肉合集，双性，**，乱X等）》是一本由著名作家大樱桃创作的玄幻魔法，此书情节跌宕、故事令人回味。",
          "position": 45
        },
        {
          "title": "小野种（双性/np/火葬场）最新章节 - 秒书屋",
          "link": "http://m.fzr6.com/book/132833/",
          "snippet": "作者：叁水叁分类：耽美小说: 状态：连载字数：57866: 更新：2023-07-11 03:34 ... 最可笑的是，曾经一起轮jian他的人竟然会因为他多看谁一眼而大打出手。 （含骨科 ...",
          "position": 46
        },
        {
          "title": "双性生子产乳_BL小说|耽美小说_腐小书",
          "link": "http://www.fxshu.cc/plus/hsearch.php?keyword=%E5%8F%8C%E6%80%A7+%E7%94%9F%E5%AD%90+%E4%BA%A7%E4%B9%B3&searchtype=titlekeyword",
          "snippet": "纨绔混账皇子x冷清禁欲将军Original Novel - BL - 长篇- 完结古代- 双性- 生子- 年下产乳元徵x岑夜阑年下第1章岑夜阑议事时，底下人来报，元徵又私自出府了。 周遭皆一静，部 ...",
          "position": 47
        },
        {
          "title": "总榜_‌​‎‌耽‍​美‎‍​‌小说排行 - 宝文书库",
          "link": "https://www.mybaowen.com/rank/all/9/30.html",
          "snippet": "就是两个同宿舍的宿友一路啪啪啪，从身体到心的故事。 床上鬼畜床下温柔攻X对外冰山对老公​人‌​‌妻‌‌​宠溺温顺受互宠双性短篇​‍ ...",
          "position": 48
        },
        {
          "title": "双性人巴尔班 - QQ阅读",
          "link": "https://ubook.reader.qq.com/book-detail/32282738?g_f=4000001",
          "snippet": "双性人巴尔班是米歇尔·福柯创作的哲学类小说,QQ阅读提供双性人巴尔班部分章节免费在线阅读,此外还提供双性人巴尔班全本在线阅读.",
          "date": "2020年7月29日",
          "position": 49
        },
        {
          "title": "父子双性小说_热门父子双性排行榜 - 蓝海搜书",
          "link": "https://www.jumpsea.cc/s/%E7%88%B6%E5%AD%90%E5%8F%8C%E6%80%A7",
          "snippet": "蓝海搜书 ... ...十足继父攻VS对内柔美乖巧对外高冷帅气双性继子受【伪父子，年上，双性，高H，剧情肉，肉汁四溢绝不弃文放心食用。】 ... 双性人渣受被父子囚禁轮奸了。 排雷：有两 ...",
          "position": 50
        },
        {
          "title": "双性_BL小说|耽美小说_腐小书",
          "link": "http://www.fuxiaoshu.com/tags.php?/%E5%8F%8C%E6%80%A7/7/",
          "snippet": "双性人将军受X帝王攻强制爱强虐身有生子HE 永昌十四年冬月十七封泰新任单於淳维，集众部於玉门。 魏三军再征塞北。 熙帝封若妃之兄、乔云飞为从四品宣威将军；五月後，擢正 ...",
          "position": 51
        },
        {
          "title": "[双性]人尽可夫- 全文在线阅读_炖肉兔子小说作品- 海外书包",
          "link": "https://www.haiwaishubao.com/book/13412/",
          "snippet": "[双性]人尽可夫最新完整章节由网友提供。《[双性]人尽可夫》是由炖肉兔子创作的海棠耽美小说书籍，海外书包提供[双性]人尽可夫小说全文章节目录的免费 ...",
          "date": "2022年9月22日",
          "position": 52
        },
        {
          "title": "双性-BL小说|耽美小说-腐小说",
          "link": "https://fuxsb.com/tags-209-0.html",
          "snippet": "老婆别怕，我不是什么好人。 裴黎意外获得了一项特异功能——读心术。他很痛苦，因为他一点也不想知道陌生人的秘密。 直到 ...",
          "position": 53
        },
        {
          "title": "双性异香人小说",
          "link": "https://v.qqzuankuo.com/book/52_3005394_58092471.shtml",
          "snippet": "相关标签： 都市 现言 慢热型 慢热 1v1 HE 双性 母亲 小说 双性人. 最后更新：2024/4/10 21:19:42. 最新章节：《[双性]异香人》最新章节57防盗番外2024-04-10. 小说简介：[ ...",
          "position": 54
        },
        {
          "title": "中国前卫文艺空间受限：从《三体》编辑被查到金星演出被拒 - 美国之音",
          "link": "https://www.voachinese.com/a/tabooed-science-fiction-transgenderism-and-halloween-stifle-chinese-literary-and-artistic-innovation/7843781.html",
          "snippet": "近期，中国前卫文艺受到愈发严厉的限制。从《三体》出版人姚海军落马，到知名跨性别主持人金星的舞台剧《日出》在广州被拒演出，再到西洋万圣节被当局严 ...",
          "date": "1天前",
          "position": 55
        },
        {
          "title": "男子每月痛苦不堪，46年才发现自己是双性人，想通过手术变女人",
          "link": "https://k.sina.cn/article_6477603854_18218640e00100kej0.html",
          "snippet": "双性人似乎是小说中的人物，但却有不少真真实实的双性人就生活在我们的身边。他们并没有小说中说的那样的奇妙生活，却比我们正常人，多了很多不该有的 ...",
          "date": "2019年11月19日",
          "position": 56
        },
        {
          "title": "【双性】人到中年爱上清纯男高 - 文海小说",
          "link": "http://m.zgzl.net/info_ox2n/",
          "snippet": "【双性】人到中年爱上清纯男高》提供西瓜咔咔好吃的最新章节，【双性】人到中年爱上清纯男高全文免费阅读，【双性】人到中年爱上清纯男高情节算得上跌宕 ...",
          "date": "2024年5月10日",
          "position": 57
        },
        {
          "title": "高h 双性_BL小说|耽美小说_腐小书",
          "link": "http://www.jiqinw.com/plus/hsearch.php?keyword=%E9%AB%98h++%E5%8F%8C%E6%80%A7&searchtype=titlekeyword&channeltype=0&orderby=&kwtype=0&pagesize=20&typeid=0&TotalResult=76&PageNo=4",
          "snippet": "姬怜是出身贵族的双性人，天赋美貌， 乃皇族内定的太子妃，然而他却有着轻微的露阴癖。 他一直苦苦压抑的病... 2018-03-01 作者：君黛. [玄幻灵异] ...",
          "position": 58
        },
        {
          "title": "男子路上遇到一场车祸，没想到事故车上走下来一位“小说女主” - 网易",
          "link": "https://www.163.com/v/video/VYF5ADQ8C.html",
          "snippet": "那些拒绝礼让消防车的奇葩人类，上一秒趾高气昂 · 湖南罕见双性人，上半身女性下半身男性，被 ...\n时长： 0:13\n发布时间： 15小时前",
          "date": "15小时前",
          "position": 59
        },
        {
          "title": "AI写的小说，有没有版权？ - 新闻频道- 央视网",
          "link": "https://news.cctv.com/2024/11/04/ARTI2X1ygitCsZsURz8ErrnD241104.shtml",
          "snippet": "张洪波表示，传统的侵权认定标准在AI创作场景下也面临适用难的问题——由于AI生成过程的复杂性和多样性，权利人难以顺利取证，维护自己的权益。 ... 双11“大战” ...",
          "date": "2小时前",
          "position": 60
        },
        {
          "title": "长沙年轻人为何钟情逛中医馆？答案来了 - 网易",
          "link": "https://www.163.com/v/video/VLF6N2H9B.html",
          "snippet": "湖南罕见双性人，上半身女性下半身男性，被男人求婚该如何抉择？ 历史博 ... 晓小说 201跟贴. 我国船员被菲律宾扣押，真敢跟中国比划 · 讲真，是球 ...",
          "date": "3小时前",
          "position": 61
        },
        {
          "title": "十年前女生站在学校讲台上，好心人捐赠了女生10万奖学金 - 网易",
          "link": "https://m.163.com/v/video/VPF4O9KO5.html",
          "snippet": "湖南罕见双性人，上半身女性下半身男性，被男人求婚该如何抉择？ 历史博 ... 晓小说 201跟贴. 我国船员被菲律宾扣押，真敢跟中国比划 · 老人吃完饭 ...",
          "date": "12小时前",
          "position": 62
        },
        {
          "title": "钓鱼佬7天连钓4条“中华鲟”，当事人：很头疼都及时放生了，网友 - 网易",
          "link": "https://m.163.com/v/video/VEF5HT84J.html?clickfrom=subscribe",
          "snippet": "湖南罕见双性人，上半身女性下半身男性，被男人求婚该如何抉择？ 历史博 ... 晓小说 201跟贴 ...\n时长： 0:15\n发布时间： 14小时前",
          "date": "14小时前",
          "position": 63
        },
        {
          "title": "中共严防死守中国“文化不自信” - 万维读者网",
          "link": "https://m.creaders.net/news/page/1290284",
          "snippet": "近期，中国前卫文艺受到愈发严厉的限制。从《三体》出版人姚海军落马，到知名跨性别主持人金星的舞台剧《日出》在广州被拒演出，再到西洋万圣节被当局严 ...",
          "date": "1天前",
          "position": 64
        },
        {
          "title": "双性男妻的礼仪 - 海外书包",
          "link": "https://www.haiwaishubao.com/book/10646/",
          "snippet": "当朝盛行娶双性人为妻，双性人生性淫荡需要受家主管制束缚，管制越严厉则表明越受宠爱。且一旦成亲生命、欲望、精神都要归夫主所有，双性人不可入朝为官，但 ...",
          "date": "2022年9月11日",
          "position": 65
        },
        {
          "title": "双性小说",
          "link": "https://dmxsw.org/tags-124-0.html",
          "snippet": "性情人，黎向皖。 克制稳重攻x人qi双性you受短篇，ntr，放飞自我内容标签： 生子豪门世家边缘恋歌未来架空搜索关键字 ...",
          "position": 66
        },
        {
          "title": "被阴暗疯批玩烂的双性美人 - 第九源言情小说网",
          "link": "https://czbokai.com/info/103440/",
          "snippet": "双性自卑弱受VS巨屌肌肉病娇阴暗攻徐迎是个双性人，他厌恶自己的身体，但是与日俱增的欲望让他深陷快感无法自拔。 直到楼下快递站新来了一个快递员，徐迎 ...",
          "date": "2024年6月4日",
          "position": 67
        },
        {
          "title": "湖南一女子大学毕业后不久，被同县男子拘禁近5年遭多次强奸产女",
          "link": "https://www.163.com/v/video/VYF6196RT.html",
          "snippet": "湖南罕见双性人，上半身女性下半身男性，被男人求婚该如何抉择？ 历史博 ... 晓小说 201跟贴. 我国船员被菲律宾扣押，真敢跟中国比划 · 他开到 ...",
          "date": "9小时前",
          "position": 68
        },
        {
          "title": "空中灭火、无人机送货……多款广州智造新型飞行器亮相这场博览会",
          "link": "https://news.dayoo.com/guangzhou/202411/02/139995_54740876.htm",
          "snippet": "广州研发的双座载人机可供低空观光旅游. “我们这次带来四架亿航EH216 ... 他透露：“我们目前在广州海心沙到天德广场开通一条示范性观光旅游航线，正在测试阶段 ...",
          "date": "2天前",
          "position": 69
        },
        {
          "title": "不可思议的交通事故瞬间大合集：2024年最震撼画面 - 网易",
          "link": "https://www.163.com/v/video/VNF67UQ1D.html",
          "snippet": "湖南罕见双性人，上半身女性下半身男性，被男人求婚该如何抉择？ 历史博 ... 晓小说 201跟贴 ...\n时长： 4:47\n发布时间： 7小时前",
          "date": "7小时前",
          "position": 70
        },
        {
          "title": "双性身份被发现后【黄/暴】最新章节",
          "link": "http://m.hfschunhua.com/xiaoshuo/132634/",
          "snippet": "双性身份被发现后【黄/暴】最新章节由网友提供，《双性身份被发现后【黄/暴】》目前更新144479字，剧情情节跌宕起伏、扣人心弦，是一本情节与文笔俱佳的耽美小说， ...",
          "position": 71
        },
        {
          "title": "前迪士尼高管：好莱坞因黑岩集团强推DEI 陷入了危机 - 3DM游戏网",
          "link": "https://www.3dmgame.com/news/202411/3907643.html",
          "snippet": "你必须有一定数量的黑人或双性人、变性人、非二元性别者。 相关内容. 标签 ... 小说漫画. 全新沉浸式互动阅读APP. 下载 · 斗罗大陆. 动漫动作. 《斗罗 ...",
          "date": "3天前",
          "position": 72
        },
        {
          "title": "重庆一农行逼迫签字恐吓，24岁女员工“遭恐吓”后轻生？银行回应 - 网易",
          "link": "https://m.163.com/v/video/VOF5O6BG3.html",
          "snippet": "湖南罕见双性人，上半身女性下半身男性，被男人求婚该如何抉择？ 历史博 ... 晓小说 201跟贴 ...\n时长： 2:20\n发布时间： 6小时前",
          "date": "6小时前",
          "position": 73
        },
        {
          "title": "“正面保质期4天， 背面1年”！山姆超市卤水现“阴阳标签”，监管部门",
          "link": "https://m.163.com/v/video/VEF23PK1A.html",
          "snippet": "湖南罕见双性人，上半身女性下半身男性，被男人求婚该如何 · 三清山抬狗 ... 晓小说 201跟贴. 我国船员被菲律宾扣押，真敢跟中国比划 · 疯狂路怒症 ...",
          "date": "2天前",
          "position": 74
        },
        {
          "title": "高校纷纷开设微专业，“香”在哪 - 新华网",
          "link": "http://www.news.cn/politics/20241104/41805ea7e6cd44aab6748f1805397bba/c.html",
          "snippet": "... 人仓储要用到的机器视觉、人工智能、5G导航等，这是传统的自动化专业无法 ... 性新兴产业紧密连接以及面向就业市场的新兴学科等。 记者还查询到 ...",
          "date": "39分钟前",
          "position": 75
        },
        {
          "title": "山区隐蔽处惊现“军中茅台”！一瓶成本仅3元 - 网易",
          "link": "https://www.163.com/v/video/VCF6750GF.html",
          "snippet": "天下霸唱小说《火神》改编，凡人得罪神明，全城 ... 湖南罕见双性人，上半身女性下半身男性，被男人 ...\n时长： 0:07\n发布时间： 7小时前",
          "date": "7小时前",
          "position": 76
        },
        {
          "title": "BOOKUU小说怎么样人到中年，就要读余华。 - 什么值得买",
          "link": "https://post.smzdm.com/talk/p/ag5ok277/",
          "snippet": "今年双十一让我最欣喜的是收到了很多自己想看的新书，都是名家大作，这一次是“潦草小狗”余华的小说套装， ... 黑暗的左手 ...",
          "date": "1天前",
          "position": 77
        },
        {
          "title": "泉涌(双性)(H)-攻党肉控-耽美小说-动漫阁文学手机阅读",
          "link": "https://omexs.com/book/11694.html",
          "snippet": "皇上有个小秘密，他是个阴阳人，知道这个秘密的除了他的母后，当今的太后娘娘，其余的人全都死翘翘了。 皇上还知道个小秘密，悄悄告诉你们，他的小太监，不知道怎么回事长出了 ...",
          "position": 78
        },
        {
          "title": "混血女孩美国长大，国内英语考试垫底，爸爸日常三国语言交流 - 网易",
          "link": "https://m.163.com/v/video/VZF4NTAOT.html",
          "snippet": "湖南罕见双性人，上半身女性下半身男性，被男人求婚该如何抉择？ 历史博 ... 晓小说 201跟贴 ...\n时长： 0:13\n发布时间： 14小时前",
          "date": "14小时前",
          "position": 79
        },
        {
          "title": "当代文学的王炸来了！余华、莫言都推荐 - 三联生活周刊",
          "link": "https://www.lifeweek.com.cn/h5/article/detail.do?artId=237984",
          "snippet": "关于他讲述“如何走上文学道路”的金句不断被提起，其中让人印象深刻的还有一段拒稿往事。 余华曾语带幽默地说：“我野心很大。一上来不管自己小说写得 ...",
          "date": "10小时前",
          "position": 80
        },
        {
          "title": "间性人- 维基百科，自由的百科全书",
          "link": "https://zh.wikipedia.org/zh-cn/%E9%9B%99%E6%80%A7%E4%BA%BA",
          "snippet": "间性人（英语：Intersex），又称双性人，俗称阴阳人，根据联合国人权事务高级专员办事处的报告，性别特征包括染色体、性腺、性激素或生殖器的变异导致“不符合男性或女性身体的典型 ...",
          "position": 81
        },
        {
          "title": "别怪年轻人没有passion，他们当了太久的NPC-36氪",
          "link": "https://m.36kr.com/p/3017083670783497",
          "snippet": "《恋与制作人》上线前后，网易游戏的《阴阳师》、米哈游的《崩坏3》等作品培养出一个至今仍被争论的品类：二次元游戏。 二次元或ACGN，原指日式动漫、游戏和轻 ...",
          "date": "4天前",
          "position": 82
        },
        {
          "title": "【SC】低俗小说- Cirrus811 - Compilation of Final Fantasy VII ...",
          "link": "https://archiveofourown.org/works/60285283",
          "snippet": "克劳德不希望重蹈覆辙，所以当萨菲罗斯沉默着拒绝告知基本信息的时候，他本想立刻关门的，眼前人 ... 过于激烈的双倍性快感让他瘫软在床上，久久回不过神来，萨菲 ...",
          "date": "11小时前",
          "position": 83
        },
        {
          "title": "双性人小说特辑- 装饰集",
          "link": "https://m.zhuangshiji.com/article/8p7q0m/",
          "snippet": "双性人小说专题为您带来最精彩的双性人小说小说推荐。这里汇聚了各类双性人小说的故事，让您尽享双性人小说文学的魅力。从经典到新作，每一部小说都充满了创意与惊喜， ...",
          "position": 84
        },
        {
          "title": "双性人纪事（重写版） - 西瓜书屋",
          "link": "https://www.xiguashuwu2.com/book/75215/",
          "snippet": "双性人纪事（重写版）最新完整版在线阅读由网友提供。《双性人纪事（重写版）》是由deepinsertion创作的其他小说书籍，西瓜书屋提供双性人纪事（重写版）小说 ...",
          "date": "2023年6月14日",
          "position": 85
        },
        {
          "title": "双性受小说_热门双性受排行榜 - 蓝海搜书",
          "link": "https://www.gosealib.com/s/%E5%8F%8C%E6%80%A7%E5%8F%97",
          "snippet": "原创/ 男男/ 现代/ 高H / 正剧/ 虐心/ 青梅竹马在最开始的那一秒，有些事注定要到老。 有些事有些人没什么值不值得的，爱上了就不想改了一段关于青梅竹马的爱情被人生生扭曲 ...",
          "position": 86
        },
        {
          "title": "11月3日（报道时间）江西吉安，男孩和女孩在幼儿园发生矛盾 - 网易",
          "link": "https://www.163.com/v/video/VEF640T18.html",
          "snippet": "湖南罕见双性人，上半身女性下半身男性，被男人求婚该如何抉择？ 历史博 ... 晓小说 201跟贴 ...\n时长： 0:12\n发布时间： 9小时前",
          "date": "9小时前",
          "position": 87
        },
        {
          "title": "奶奶私自拿走外婆给宝宝的金吊坠，拿去熔了换了条大的自己戴 - 网易",
          "link": "https://m.163.com/v/video/VJF4SD1CI.html",
          "snippet": "湖南罕见双性人，上半身女性下半身男性，被男人求婚该如何抉择？ 历史博 ... 晓小说 201跟贴 ...\n时长： 0:23\n发布时间： 14小时前",
          "date": "14小时前",
          "position": 88
        },
        {
          "title": "【双性/催眠/雌堕】人夫全部都雌堕 - ‌小‍‎红‍‍书‌‌",
          "link": "https://www.shongshu.com/book/349293848371271/",
          "snippet": "【双性/催眠/雌堕】人夫全部都雌堕最新完整章节由网友提供。《【双性/催眠/雌堕】人夫全部都雌堕》是由云中月下鸢创作的‍‌‎耽‌‎美‎‌‍‌‍小说书籍， ...",
          "date": "2024年2月13日",
          "position": 89
        },
        {
          "title": "穿进‌‍‎‍‎淫‍‌‍荡‍‎‎皇宫中双性np - 飞‌‎‍书‍‍小‍‍说‍‌‍网‎‍",
          "link": "https://www.feishubook.com/book/376042301882437/",
          "snippet": "... 双性np小说 ... 无子宫双性人。 详细过程见文章内容，其他待补充:2024/3/25留❤️ 目前出场攻有: 人形‎‎‍‍‌鸡‎‌‎巴‎‌‍‌ ...",
          "date": "2024年4月28日",
          "position": 90
        },
        {
          "title": "【总受】双性‍‎‎‌‍美‌‎‎‌人‍‍‎就算在童话也要被艹 - ‌‍新‌龙‍‎小‍‌‎说",
          "link": "https://www.xinlongbook.com/book/410207854051397/",
          "snippet": "... 是由鸳黛黛创作的‎‌‎‍耽‎‌‍‎‌美‌‍‎‍小说书籍，新龙小说网提供【总受】双性‍‎‎‌‍美‌‎‎‌人‍‍‎就算在童话也要被艹小说全文章节目录的免费在线阅读。",
          "date": "2024年8月3日",
          "position": 91
        },
        {
          "title": "长沙媳妇台上唱歌谢84岁婆婆：情真意切 - 网易",
          "link": "https://www.163.com/v/video/VKF6N2QCS.html",
          "snippet": "湖南罕见双性人，上半身女性下半身男性，被男人求婚该如何抉择？ 历史博 ... 晓小说 201跟贴 ...\n时长： 0:38\n发布时间： 3小时前",
          "date": "3小时前",
          "position": 92
        },
        {
          "title": "沈阳这个楼盘提前完成交付，栋察楼市实地探访看品质如何？ - 网易",
          "link": "https://m.163.com/v/video/VSF2O14RA.html?clickfrom=subscribe",
          "snippet": "《低俗小说》筹备史：让一线大咖排队等信，把 · 俄罗斯的武器弹药 ... 湖南罕见双性人，上半身女 ...\n时长： 1:10\n发布时间： 2天前",
          "date": "2天前",
          "position": 93
        },
        {
          "title": "11月3日（发布）河南郑州。65岁大爷退休后在郑州拍短剧。当过兵",
          "link": "https://www.163.com/v/video/VJF5NMCOO.html",
          "snippet": "湖南罕见双性人，上半身女性下半身男性，被男人求婚该如何抉择？ 历史博 ... 晓小说 201跟贴 ...\n时长： 0:17\n发布时间： 12小时前",
          "date": "12小时前",
          "position": 94
        },
        {
          "title": "哈尔滨保安5分钟寻娃，家长痛哭跪谢，保安：孩子在东北一定丢不了",
          "link": "https://m.163.com/v/video/VKF57278T.html?spss=news-hotlist-wap-index",
          "snippet": "湖南罕见双性人，上半身女性下半身男性，被男人求婚该如何抉择？ 历史博鉴览 254 ... 晓小说 ...\n时长： 0:08\n发布时间： 4小时前",
          "date": "4小时前",
          "position": 95
        },
        {
          "title": "蹂躏双性小‌‍‍‌‎美‎‌‌人‌‎‍‎‌（共妻NPH ） - ‌‌新‌龙‌小‌‎说‌网‌‍",
          "link": "https://www.longmebook.com/book/375599932149829/",
          "snippet": "蹂躏双性小‌‍‍‌‎美‎‌‌人‌‎‍‎‌（共妻NPH ）最新完整章节由网友提供。《蹂躏双性小‌‍‍‌‎美‎‌‌人‌‎‍‎‌（共妻NPH ）》是由华云创作的‎‌‍‍言‌‎‍‎情‎‌‎小说书籍， ...",
          "date": "2024年4月27日",
          "position": 96
        },
        {
          "title": "11月3日，河南，郑州大学生夜骑自行车去开封，开封城管心疼娃们太 ...",
          "link": "https://www.163.com/v/video/VJF5NM62A.html",
          "snippet": "湖南罕见双性人，上半身女性下半身男性，被男人求婚该如何抉择？ 历史博 ... 晓小说 201跟贴 ...\n时长： 0:09\n发布时间： 12小时前",
          "date": "12小时前",
          "position": 97
        },
        {
          "title": "今天也被‎‎‍‌轮‎‎‍‌‍奸‌‍了吗（双性合集） - ‌‍新‌龙‍‎小‍‌‎说",
          "link": "https://www.xinlongbook.com/book/302623958388805/",
          "snippet": "... （双性合集）》是由没有名字创作的‌‎‍‌‎耽‌‎美‍‎‌‎‍小说书籍，新龙小说网提供今天也被‎‎‍‌轮‎‎‍‌‍奸‌‍了吗（双性合集）小说全文章节目录的免费在线阅读。",
          "date": "2023年10月4日",
          "position": 98
        },
        {
          "title": "双性大奶‌‎‍美‎‍‌‍人‍‎‌每天都被大屌草醒（大奶‎‍美‌‌人‎‍‌‎‍受‌‍肉合集） - ‌‌‎小‎红‎‍‎书‎‍",
          "link": "https://www.shongshu.com/book/264300304805957/",
          "snippet": "... 的‍‌耽‌‎美‍‍‎‌‎小说书籍，小红书提供双性大奶‌‎‍美‎‍‌‍人‍‎‌每天都被大屌草醒（大奶‎‍美‌‌人‎‍‌‎‍受‌‍肉合集）小说全文章节目录的免费在线阅读。",
          "date": "2023年6月17日",
          "position": 99
        },
        {
          "title": "激烈喷水的双性‎‌‍人‌‎妻‍‌‍（‌‎高‍‍‎H‌‎‎‍） - ‌‎飞‎‌书‎‍小‍说‌网‌",
          "link": "https://www.feishubook.com/book/347863457640518/",
          "snippet": "... 双性‎‌‍人‌‎妻‍‌‍（‌‎高‍‍‎H‌‎‎‍）》是由被摸那里会受不了的创作的‎‎‌‍耽‍‎‍‌美‍‌小说书籍，飞书小说网提供激烈喷水的双性‎‌‍人‌‎妻‍‌‍（‌‎高‍‍‎H‌‎‎‍） ...",
          "date": "2024年2月9日",
          "position": 100
        }
      ],
      "relatedSearches": [
        {
          "query": "海棠小说"
        },
        {
          "query": "小说狂人"
        },
        {
          "query": "帐中香"
        }
      ],
      "credits": 2
    },
    {
      "searchParameters": {
        "q": "双性人 小说",
        "gl": "cn",
        "hl": "zh-cn",
        "type": "search",
        "num": 100,
        "page": 2,
        "engine": "google"
      },
      "organic": [
        {
          "title": "夜很贫瘠小说作品全集 - 废‍纸‎‍‌文‎学‍",
          "link": "https://www.sosadhappy.com/writer/32705865863237/",
          "snippet": "中篇设定：双性人存在已知，每个婴儿出生后都要经过严格检查确认性别，记录在案。 在河下村，被检查出双性的人，最终都会沦为村中所有男人的玩物。 村里唯一的医生陈常勇 ...",
          "position": 1
        },
        {
          "title": "双性人英语 - 科幻小说网",
          "link": "https://www.tangkitchen.net/lxs/784850/784851116/",
          "snippet": "双性人英语. 获 0.07万人读过 0万字 连载. 小说简介：“一群怂包看清楚了，这才叫做教训，这样的教训才能让他们服气。” 最新章节：双性秘密被发现被学生强奸开苞(1个月 ...",
          "position": 2
        },
        {
          "title": "双性人电视剧-アンドロジナス-苇原旭-最新章节第6话",
          "link": "https://www.costcoshop.net/costcocw/8332717.html",
          "snippet": "猜你喜欢. 恋爱甜心. 对恋爱毫无经验的法式甜点师衿绪,与拥有不为人知过往的小说 ...",
          "date": "2024年8月22日",
          "position": 3
        },
        {
          "title": "双性人有月经吗 - 科幻小说网",
          "link": "https://www.tangkitchen.net/lxs/784850/784851115/",
          "snippet": "双性人有月经吗. 获 0.07万人读过 0万字 连载. 小说简介：那么现在就让你们一个报仇的机会，去狠狠的教训一下他们，一些胡人杂种也敢奴役我汉家儿郎。” 最新章节：双性 ...",
          "position": 4
        },
        {
          "title": "双性人-アンドロジナス-苇原旭-最新章节第6话",
          "link": "https://www.costcoshop.net/costcocw/748881.html",
          "snippet": "双性人和正常人有什么区别 · 双性人怎么选厕所 · 双性什么意思 · 双性别能来月经吗 · 双重人格的表现症状是什么 · 双性阴阳人是什么 ... 双性海棠小说 · 双 ...",
          "date": "2024年8月22日",
          "position": 5
        },
        {
          "title": "母妃- 一个老炮儿小说作品- 废纸文学",
          "link": "https://www.sosadhappy.com/book/442869447524421/",
          "snippet": "内容简介. 新帝登基第一件事，是去找被藏在深宫中的母妃一个老炮儿 ‍‌‌原‌‎‎创‍‌小说- BL - 中篇- 完结 ‌‍‍‎‌古‌‌‍‎‎代‎‎ - 双性- 强制爱太子失势一朝 ...",
          "date": "22小时前",
          "position": 6
        },
        {
          "title": "双性人特征-アンドロジナス-苇原旭-最新章节第6话",
          "link": "https://www.ozimax.com/ozimaxcw/14592843.html",
          "snippet": "双性人和正常人有什么区别 · 双性将军在敌 ... 双性阴阳人是什么 · 双性人手术 · 双性美人 · 双性 ... 双性海棠小说 · 双性人最新新闻 · 双性生殖科普知识 ...",
          "date": "2024年8月22日",
          "position": 7
        }
      ],
      "credits": 2
    }
  ]
}