{
  "query": "变装艺术",
  "language": "zh-cn",
  "geo_location": "cn",
  "totalPages": 3,
  "endpoint": "/search",
  "date": "2024-11-04T00:33:01.475083",
  "results": [
    {
      "searchParameters": {
        "q": "变装艺术",
        "gl": "cn",
        "hl": "zh-cn",
        "type": "search",
        "num": 100,
        "page": 1,
        "engine": "google"
      },
      "organic": [
        {
          "title": "变装- 维基百科，自由的百科全书",
          "link": "https://zh.wikipedia.org/zh-cn/%E8%AE%8A%E8%A3%9D",
          "snippet": "变换、更换服装。 · 化装，修饰容貌、妆扮外表，是戏剧、电影等表演场合的造型手段之一。 · 易装，改变装扮外观与装束服饰的行为。 · 乔装，为了掩饰自己的真实身份，而改变容貌和 ...",
          "position": 1
        },
        {
          "title": "为你选书｜《变装的艺术》：颠覆想像！变装就是一门戏耍性别的艺术",
          "link": "https://cn.womany.net/read/article/27964",
          "snippet": "变装，是一门戏耍性别的艺术，颠覆主流对于美、对于性别的想像。想了解更多变装的历史与趋势，《变装的艺术》是一本了解变装简史必备的图文书。",
          "date": "2021年11月9日",
          "position": 2
        },
        {
          "title": "变装技术的演变与应用 - 万维易源",
          "link": "https://www.showapi.com/news/article/6699bf164ddd79f11a01412e",
          "snippet": "变装技术，这一融合了科技与艺术的领域，其历史可追溯至古代。早在古希腊和罗马时期，戏剧演员便利用简单的化妆和服饰变换来扮演不同的角色，这是变装技术 ...",
          "date": "2024年7月19日",
          "position": 3
        },
        {
          "title": "TikTok中国变装：展现多样魅力的艺术表达 - 连连国际",
          "link": "https://global.lianlianpay.com/article_wiki/32-79644.html",
          "snippet": "变装艺术是指通过化妆、服装和表演等手段，将自己转变为不同性别、角色或风格的人物。在TikTok上，许多创作者利用变装艺术展示自己的才华和创意，通过化妆和 ...",
          "date": "2023年7月9日",
          "position": 4
        },
        {
          "title": "艺术家克里斯托遗作：“变装”巴黎凯旋门",
          "link": "https://www.archdaily.cn/cn/968536/yi-gu-yi-zhu-jia-ke-li-si-tuo-yi-zuo-bei-bao-guo-de-ba-li-kai-xuan-men-zui-xin-zhao-pian",
          "snippet": "建筑摄影师Jad Sylla用镜头记录了这一大型公共艺术，他的第一张照片展示了克里斯托对凯旋门所作的改变：凯旋门外包裹着约25000平方米的银蓝色可回收聚丙烯 ...",
          "date": "2021年9月21日",
          "position": 5
        },
        {
          "title": "你不知道的变装文化变装皇后：这不可耻（组图） - 新华网",
          "link": "http://news.xinhuanet.com/world/2016-05/19/c_128995781.htm",
          "snippet": "据英国《每日邮报》5月17日报道，在过去的7年里，变装皇后越来越多的在大众面前出现，例如著名的美国电视节目鲁保罗变装皇后秀，让原本小众的艺术形式变得 ...",
          "date": "2016年5月19日",
          "position": 6
        },
        {
          "title": "变装皇后：你我生来如此，其余皆是变装 - 搜狐",
          "link": "https://www.sohu.com/a/315152287_118065",
          "snippet": "变装文化兴起于19世纪后期的欧洲，当时被欧洲人称为迷幻贵妇人（Pantomime Dames)。生活在冰冷工业时代的人们厌倦了严肃的莎翁剧与高大上的意大利歌剧，于是 ...",
          "date": "2019年5月21日",
          "position": 7
        },
        {
          "title": "变装艺术 - 微博",
          "link": "https://m.weibo.cn/search?containerid=231522type%3D1%26t%3D10%26q%3D%23%E5%8F%98%E8%A3%85%E8%89%BA%E6%9C%AF%23&luicode=10000011&lfid=106003type%3D25%26t%3D3%26disable_hot%3D1%26filter_type%3Drealtimehot",
          "snippet": "今天变好看了吗. 7-12 16:10 来自微博视频号. 外在形式真的那么关键吗？内心的感受才是决定性的力量！ #变装艺术# 形象转变前后# 神奇妆容术# #艺术# · 今天变好看了吗的微 ...",
          "position": 8
        },
        {
          "title": "變裝的藝術 - 博客來",
          "link": "https://www.books.com.tw/products/0010904047?srsltid=AfmBOorWlUKRoCaHmmlervL0Pm8T71xWcSMZofdXxsBlOXCjYRevNAjI",
          "snippet": "在迷人的假髮、亮片和睫毛膏之外，本書揭開了「變裝」和戲劇、電影、性別、政治與時尚的交匯，繽紛奪目的插畫分別由三位酷兒藝術家操刀，顏色對撞，表情浮誇，意圖奔放，每一頁都 ...",
          "position": 9
        },
        {
          "title": "近观：中国的变装皇后——二元身份之外的流行 - The China Temper",
          "link": "https://chinatemper.com/zh/%E7%89%B9%E5%86%99/chinadragzh",
          "snippet": "蹑手蹑脚进入20世纪，变装皇后在艺术和文化中的份额日益凸显。尤其在西方，变装文化的规模扩大到前所未有，电视真人秀等平台都播出了《鲁保罗变装皇后秀》 ...",
          "date": "2018年6月27日",
          "position": 10
        },
        {
          "title": "傻瓜相机记录下的变装皇后历史 - 纽约时报",
          "link": "https://cn.nytimes.com/culture/20150813/t13lindasimpson/",
          "snippet": "从上世纪八九十年代开始，变装喜剧演员琳达·辛普森拍摄了约5000张变装表演者欢乐的合影和迷人的肖像照。它们记录了变装从一种地下艺术形式演变成流行 ...",
          "date": "2015年8月13日",
          "position": 11
        },
        {
          "title": "[PDF] 诗意空间与变装肖像 - 北京大学人文学部",
          "link": "https://fh.pku.edu.cn/docs/2021-04/20210412085355333406.pdf",
          "snippet": "艺术史学者乔迅（Jonathan Hay）则指出，17世纪以来对于西方平. 面玻璃的引进对于中国人的审美情趣有着一定的影响，一些新的装饰艺术品的诞生是由于大. 玻璃镜所带来的新奇感与 ...",
          "position": 12
        },
        {
          "title": "他满世界拍摄变装皇后，惊艳极了 - 界面新闻",
          "link": "https://m.jiemian.com/article/682957.html",
          "snippet": "观看这段表演唤醒了Hastings心里的那个热爱变装的自己，虽然在孩提时期他就已经迫于社会压力放弃了这项艺术，但仍旧保留着深入了解这个圈子的渴望。在Vanity ...",
          "date": "2016年6月11日",
          "position": 13
        },
        {
          "title": "【我们的故事】变装国王周奕升：发出属于自己的光 - SBS",
          "link": "https://www.sbs.com.au/language/chinese/zh-hans/podcast-episode/our-storyshine-your-own-light-taiwanese-drag-performer-jass-chou/ni343qyn1",
          "snippet": "现今，变装表演已经演变成一种全球现象，涵盖多种形式的表演艺术，变装国王（Drag King）表演就是其中一种。 传统上，Drag King指的是女性或非二元 ...",
          "date": "2024年8月23日",
          "position": 14
        },
        {
          "title": "火爆全球的变装选秀，带来最强的时尚脑洞！ - 搜狐",
          "link": "https://www.sohu.com/a/465116963_99983225",
          "snippet": "如今，鲁保罗秀已经在英国、泰国、加拿大、荷兰、澳大利亚、西班牙等地都举办了分赛，并即将聚集各国比赛的优秀选手参加鲁保罗国际变装大赛，可见变装艺术的 ...",
          "date": "2021年5月7日",
          "position": 15
        },
        {
          "title": "妮妃雅如何重新定义源于西方的变装文化｜端闻Podcast",
          "link": "https://theinitium.com/zh-hans/audio/20240529-initium-audio-taiwan-nymphia-wind-wins-rupauls-drag-race",
          "snippet": "妮妃雅让我们看到，亚洲变装皇后不必复制西方的“diva” ，可以成为一种风格。 2024年5月25日，台北，妮妃雅在第二届台北国际变装艺术节上表演。",
          "date": "2024年5月28日",
          "position": 16
        },
        {
          "title": "变装皇后的自我增幅变妆术｜PAR 表演艺术杂志",
          "link": "https://par.npac-ntch.org/cn/article/doc/GGSCW559IO",
          "snippet": "美国指标性变装皇后露波（RuPaul）说过：「We born naked, and rest is drag.（我们生而赤身裸体，而剩下的都是变装。）」言简意赅地带出「性别」除了生物身体性， ...",
          "position": 17
        },
        {
          "title": "苏州经典艺术摄影工作室——JD|经典|摄影|经典影业——Powered By ...",
          "link": "http://www.jdcdsy.com/",
          "snippet": "·昆曲艺术妆容. ·优雅休闲服饰. ·美丽的旗袍. ·时尚的礼服. 苏州经典艺术摄影工作室为您提供更完美的拍摄方案. 小枚变装和闺蜜在周. 外景跟随 工作室位于景色优美的苏州 ...",
          "position": 18
        },
        {
          "title": "变装皇后- 维基百科，自由的百科全书",
          "link": "https://zh.wikipedia.org/zh-cn/%E8%AE%8A%E8%A3%9D%E7%9A%87%E5%90%8E",
          "snippet": "变装皇后（英语：drag queen），或扮装皇后、易装皇后、异装者，指透过穿女性服装来扮演女性的男性。异装有很多种表现形式，有些是想效法展示女性之美，近代则多为行为艺术家的 ...",
          "position": 19
        },
        {
          "title": "台湾反串艺人与变装皇后以表演“活出自己的样子” - BBC News 中文",
          "link": "https://www.bbc.com/zhongwen/simp/chinese-news-69166017",
          "snippet": "... （Nymphia Wind）4月于美国《鲁保罗变装皇后秀》夺冠后在台湾引起一阵风潮，让变装 ... 是艺术，也是对父权的抗议：台湾反串艺人与变装皇后以表演“活出自己的 ...",
          "date": "2024年7月8日",
          "position": 20
        },
        {
          "title": "巴黎变装秀：顶级地址和令人惊叹的表演- Sortiraparis.com",
          "link": "https://www.sortiraparis.com/zh/zai-bali-kan-shenme/jiemu/guides/263374-ba-li-bian-zhuang-xiu-ding-ji-de-zhi-he-ling-ren-jing-tan-de-biao-yan",
          "snippet": "近年来，变装表演大受欢迎，这主要归功于Netflix 上的美剧《鲁保罗变装大赛》（RuPaul's Drag Race）。这一现象将变装艺术推向了国际舞台的最前沿，其法语版第 ...",
          "date": "2023年12月11日",
          "position": 21
        },
        {
          "title": "北京变装会所燕子摄影师告诉你如何变装好看 - 新浪网站导航",
          "link": "https://blog.sina.com.cn/s/blog_13dbedfea0102yayq.html",
          "snippet": "1、性质不同，TS会所以娱乐或者SM为主服务，我们会所专业化妆摄影为主服务，即使做绳艺，也是以绳艺艺术为出发点的，你在享受被束缚的同时，留下绳艺精美照片的 ...",
          "date": "2018年12月21日",
          "position": 22
        },
        {
          "title": "变装-视觉探索:视觉艺术视频-新片场",
          "link": "https://www.xinpianchang.com/a11841610",
          "snippet": "变装来自创作人刘云达的视频作品, 新片场汇聚全球优质创作人及原创视频下载, 视觉探索作品拍摄制作公司提供视觉探索和视觉艺术相关的样片案例、TVC、文案策划、配音 ...",
          "position": 23
        },
        {
          "title": "一个崇拜泰迪熊的变装癖，怎么用艺术改变世界？ - 公益- 凤凰网",
          "link": "https://gongyi.ifeng.com/c/7hD9UdlruFr",
          "snippet": "陶匠、先锋艺术家、电视明星、作家、泰迪熊崇拜者、异装癖者，伦敦艺术大学名誉校长……很难想象这一大串标签会属于同一个人，但这件事发生了。",
          "date": "2017年9月28日",
          "position": 24
        },
        {
          "title": "巴黎奥运会开幕式遭痛批，变装艺术惹怒宗教群体，奥组委紧急道歉",
          "link": "https://news.qq.com/rain/a/20240730A083AL00",
          "snippet": "全球瞩目的巴黎奥运会开幕式，被骂上了全球热搜，巴黎奥组委还不得不出来紧急道歉。 直接原因是，在开幕式上有一个极其辣眼睛的节目。奥组委通过艺术形式 ...",
          "date": "2024年7月30日",
          "position": 25
        },
        {
          "title": "变装皇后：挤进大码高跟鞋，他们让心里的女孩站上舞台 - 澎湃新闻",
          "link": "https://m.thepaper.cn/newsDetail_forward_1478999",
          "snippet": "“我觉得国人很难去理解变装皇后这个职业。”Maria是“鲁保罗变装皇后秀”的粉丝，每集都观看，“我觉得变装艺术在于用自己的方式糅进时尚的元素来表达作品理念， ...",
          "date": "2016年6月28日",
          "position": 26
        },
        {
          "title": "揭开对异装（drag）的误解 - 时尚- 搜狐",
          "link": "https://fashion.sohu.com/20161025/n471296884.shtml",
          "snippet": "依靠独特真实、令人心碎的真实故事，犀利风趣的智慧，和令人惊叹的艺术性，这一节目将不可能变为可能：令drag 这一通过表演和美学重塑性别、极具颠覆性的艺术 ...",
          "date": "2016年10月25日",
          "position": 27
        },
        {
          "title": "9位顛覆你想像的變裝表演家 - Harper's BAZAAR",
          "link": "https://www.harpersbazaar.com/tw/celebrity/celebritynews/g22005968/8-must-know-drag-artists/",
          "snippet": "Drag(變裝)源自1870年代男扮女裝的舞台表演方式，後來因為許多同志人士的參與，才有Drag Queen(變裝皇后)的誕生。其實Drag不只是一門表演藝術， ...",
          "date": "2018年11月9日",
          "position": 28
        },
        {
          "title": "为什么变装皇后要对口型表演- 日记- 豆瓣",
          "link": "https://m.douban.com/note/853861825/",
          "snippet": "19世纪，人们开始用「变装」drag来指代这种艺术形式，涵盖舞蹈表演、现场演唱、喜剧或某种动作。不过，在当时，变装通常是杂耍剧vaudeville theater的一部分， ...",
          "date": "2023年9月12日",
          "position": 29
        },
        {
          "title": "“中式变装”如何硬控“Z世代”青年 - 新华网",
          "link": "http://www.news.cn/local/20240710/f0f1abb9a0fe4db69cd57ebafcd7112f/c.html",
          "snippet": "陈晓寒认为，艺术就应该要有创新和突破。她希望通过自己的镜头，让更多人看到林黛玉可能存在的另一面，看到一个勇敢、自由的独立女性形象 ...",
          "date": "2024年7月10日",
          "position": 30
        },
        {
          "title": "蔡英文祝贺台湾变装皇后美国夺冠 - DW",
          "link": "https://www.dw.com/zh/%E8%94%A1%E8%8B%B1%E6%96%87%E7%A5%9D%E8%B4%BA%E5%8F%B0%E6%B9%BE%E5%8F%98%E8%A3%85%E7%9A%87%E5%90%8E%E7%BE%8E%E5%9B%BD%E5%A4%BA%E5%86%A0/a-68878494",
          "snippet": "蔡英文在X平台上用英文写道：“恭喜你，Nymphia Wind，在变装这一高难度的艺术形式上取得了如此大的成就，成为第一个登上鲁保罗变装大赛舞台并获得冠军的台湾人 ...",
          "date": "2024年4月20日",
          "position": 31
        },
        {
          "title": "不到30岁，他就成了“天花板”",
          "link": "https://news.qq.com/rain/a/20240407A078CK00",
          "snippet": "2014年，朱铁雄考上了山东大学，尽管念的是环境艺术设计专业，但表演的热情愈发高涨。 ... “传统文化的变装变成了现代特警的变装，只是造型上的区别而已，但内里 ...",
          "date": "2024年4月7日",
          "position": 32
        },
        {
          "title": "妮妃雅的风与疯：亚洲第一皇后诞生，鲁保罗变装秀的夺冠幕后 - 端傳媒",
          "link": "https://theinitium.com/zh-hans/article/20240425-taiwan-nymphia-wind-wins-rupauls-drag-race",
          "snippet": "Leo 对于传统表演艺术的启蒙，要追溯至2017年他从英国创作艺术大学毕业返台后，开始与剧场服装设计师李育升共事。李育升擅长以高级订制服的工艺手法制作剧场 ...",
          "date": "2024年4月24日",
          "position": 33
        },
        {
          "title": "春晚舞台上的11秒国风变装太燃了！原来是他→",
          "link": "http://m.cnhubei.com/content/2024-02/11/content_17409251.html",
          "snippet": "2014年，朱铁雄考上山东大学，攻读环境艺术设计专业。大学期间，他加入武术社团，爱上了电影和舞台剧，还自学了摄影和后期特效制作，自编自导自演 ...",
          "date": "2024年2月11日",
          "position": 34
        },
        {
          "title": "博物志|人人生来赤裸，其余皆是变装 - 劳动关系学院",
          "link": "https://news.culr.edu.cn/whcbxy/xsgz/xsmj/xzxjxsbz/8dbb5d037e544a17a49bfb48fc95817c.htm",
          "snippet": "变装皇后表演涉及的领域就更多了：T台走秀，服装设计，唇舞，喜剧演出…任何你能想到的艺术表演形式都可以“变装化”。换句话说，变装，这一变化多样的艺术载体 ...",
          "date": "2021年4月26日",
          "position": 35
        },
        {
          "title": "复古照片带你走进19和20世纪的“变装皇后” - 英国那些事儿",
          "link": "http://www.hereinuk.com/45843.html",
          "snippet": "... 变装”在21世纪已经成为一种常见的艺术表演形式。 然而在此之前，那些生活在传统保守年代里的男性，早就做出了“变装”这样大胆的举动。 一大批复古照片 ...",
          "date": "2015年10月1日",
          "position": 36
        },
        {
          "title": "双鹿小子IP形象变装设计》获国家级银级类奖项 - 吉林动画学院官网",
          "link": "https://www.jlai.edu.cn/info/1102/4962.htm",
          "snippet": "《世界之“鹿”—双鹿小子IP形象变装设计》设计图. 赛事名称：2023年中国大学生广告艺术节秋季征集大赛. 作者：李昂. 指导教师：梅婷婷. 奖项：国家级银级类.",
          "date": "2024年1月5日",
          "position": 37
        },
        {
          "title": "艺术秀巴黎- 巴黎变装歌舞表演• 价格、时间表和演出预订",
          "link": "https://www.cometoparis.com/chi/catalog/artishow-paris-8031",
          "snippet": "欢迎来到巴黎的Cabaret l'Artishow！自2002年以来，这个独特的地方融合了喜剧、戏剧、舞蹈和变装表演。在第11区的一条小巷里，艺术家们巧妙地扮成Mylène Farmer、Sheila ...",
          "position": 38
        },
        {
          "title": "变装皇后|表演艺术- 娱乐与流行文化| 十一月2024 - gov-civ-guarda.pt",
          "link": "https://zh.gov-civ-guarda.pt/drag-queen",
          "snippet": "变装皇后，一个穿着女装在观众面前表演的男人。变装秀（通常在夜总会和同性恋骄傲节上演）在很大程度上是一种亚文化现象。尽管变装从未享有主流吸引力，但变装皇后在流行 ...",
          "position": 39
        },
        {
          "title": "鲁保罗— Google 艺术与文化",
          "link": "https://artsandculture.google.com/entity/m01lqf49?hl=zh",
          "snippet": "鲁保罗‧安德尔‧查尔斯，艺名鲁保罗，是一位美国男演员、歌手及变装皇后。",
          "position": 40
        },
        {
          "title": "走上春晚舞台的校友朱铁雄：用变装“魔法”点亮国风梦想",
          "link": "https://www.view.sdu.edu.cn/info/1440/188735.htm",
          "snippet": "2013年，朱铁雄考上山东大学，从东海边的家乡来到黄海边的校园，在山东大学威海校区的艺术学院学习环境艺术设计专业。 “山大丰富的校园活动和平台，让 ...",
          "date": "2024年3月21日",
          "position": 41
        },
        {
          "title": "变装皇后- activities - Sortiraparis.com",
          "link": "https://www.sortiraparis.com/zh/articles/tag/bian-zhuang-huang-hou",
          "snippet": "这个全新的节目将由才华横溢的变装皇后和变装国王进行科学表演，这个夜晚有望模糊变装艺术和科学普及之间的界限！",
          "position": 42
        },
        {
          "title": "我对NYU讲的故事：变装皇后与癌症男孩的救赎 - ACG-艺术留学",
          "link": "https://www.acgorg.com/yishuzixunInfo-1558.html",
          "snippet": "电影，是梦与黎明的距离。虚实影音交错，生活的百般滋味日夜上演。特异的电影美学，一段亦真亦假的人生。尽管我们身处不同世界，却仍能感悟另一个世界的喜 ...",
          "date": "2020年12月23日",
          "position": 43
        },
        {
          "title": "语言是一门艺术#憋笑挑战#印度变装搞笑#翻唱- 抖音",
          "link": "https://www.douyin.com/video/7405299558219091254",
          "snippet": "语言是一门艺术#憋笑挑战#印度变装搞笑#翻唱- JF江峰于20240820发布在抖音，已经收获了347706个喜欢，来抖音，记录美好生活！",
          "position": 44
        },
        {
          "title": "关于变装的电影 - 豆瓣",
          "link": "https://m.douban.com/tag/%E5%8F%98%E8%A3%85/movie",
          "snippet": "... 艺术/ 美国/ 2009 · 鲁保罗变装皇后秀第六季RuPaul's Drag Race Season 6. 9.2. 鲁保罗/ 舞台艺术/ 美国/ 2014 · 变装求职记Work It. 7.5. 贝丝·麦卡锡-米勒/ 阿莫里· ...",
          "position": 45
        },
        {
          "title": "偶像派对变装秀，粉丝惊喜不已；电视剧演员现场换错剧本 - YouTube",
          "link": "https://www.youtube.com/watch?v=leMuutPKoNg",
          "snippet": "偶像派对变装秀，粉丝惊喜不已；电视剧演员现场换错剧本，即兴演出引爆笑；名演员偷偷参与街头 ...\n时长： 8:39\n发布时间： 2024年1月20日",
          "date": "2024年1月20日",
          "position": 46
        },
        {
          "title": "变装秀 - 微博",
          "link": "https://m.weibo.cn/search?containerid=231522type%3D1%26t%3D10%26q%3D%23%E5%8F%98%E8%A3%85%E7%A7%80%23&isnewpage=1&luicode=10000011&lfid=231522type%3D1%26t%3D10%26q%3D%23%E8%89%BA%E6%9C%AF%23&featurecode=newtitle%0A%E3%80%90%E8%A7%A6%E7%9B%AE%E6%83%8A%E5%BF%83%EF%BC%81%E9%BB%91%E9%BE%99%E6%B1%9F%E4%B8%80&launchid=10000360-QQ_liulanqi_resou",
          "snippet": "大触的绘板姬 · 中国广核集团 · 东风快递 · 八一青春方阵 · 荆晓萌_Adorable · 高原战士 · 贝贝Tina呀 · 西昌发布V ...",
          "position": 47
        },
        {
          "title": "神奇的变脸变装变伞艺术 - 文学城| 博客",
          "link": "https://blog.wenxuecity.com/myblog/57346/201205/3717.html",
          "snippet": "神奇的变脸变装变伞艺术. (2012-05-06 01:39:00) 下一个. 神奇的变脸变装变伞艺术 http://www.youtube.com/watch?v=qVKrKA_HLYY&feature=fvsre3. [ 打印 ].",
          "position": 48
        },
        {
          "title": "如何联系变装团队人员| PingCode智库",
          "link": "https://docs.pingcode.com/baike/1642387",
          "snippet": "社交媒体平台如Instagram和Facebook是联系变装团队的绝佳途径。大多数变装艺术家和团队会在这些平台上展示他们的作品。通过搜索相关标签（如#变装艺术、# ...",
          "date": "2024年9月5日",
          "position": 49
        },
        {
          "title": "单慧乾",
          "link": "http://madeinmuseum.art/index.php/%E5%8D%95%E6%85%A7%E4%B9%BE/",
          "snippet": "单慧乾（1991 年生于多伦多）以思辨小说的方式介入行为、写作与动态影像中，以扰乱对于慾望、身份认同与物化的规训过程。单慧乾以「变装」作为具目的性的艺术体现，质疑归因于 ...",
          "position": 50
        },
        {
          "title": "曼谷阿瓦尼Lost & Found & 河畔酒店（鸡尾酒& 现场音乐） - Klook",
          "link": "https://www.klook.com/zh-CN/activity/94670-lost-and-found-avani-riverside-bangkok/",
          "snippet": "前往Lost & Found 享用我们的“Diva Night Brunch”，这里的鸡尾酒很烈，但“女士们”的酒劲更大！ · 奢华娱乐：失物招领之夜热闹非凡，有充满活力的LGBTQ 快闪表演，艺术、戏剧和变装 ...",
          "rating": 4.9,
          "ratingCount": 20,
          "position": 51
        },
        {
          "title": "美术与书法讲坛｜赵琰哲：游园、计时、变装 - 北京大学图书馆",
          "link": "https://www.lib.pku.edu.cn/hdrl/43d4611b1e4c444083c09c6769563ebf.htm",
          "snippet": "讲座主题：游园、计时、变装——清代宫廷艺术与多元文化碰撞. 主讲人：赵琰哲（北京画院理论部研究员）. 主持人：刘晨（北京大学艺术学院研究员，博士生导师）.",
          "date": "7天前",
          "position": 52
        },
        {
          "title": "'You Better Werq!' 第二屆台北國際變裝藝術節Taipei International ...",
          "link": "https://cumpartytw.kktix.cc/events/werq",
          "snippet": "魯保羅變裝秀台灣之光~Nymphia Wind，第16季人氣天后Mirage、Plane Jane以及菲律賓天后M1ss JadeSo同台演出/ 台灣最大變裝盛事/網羅台灣最受歡迎變裝 ...",
          "date": "2024年5月25日",
          "position": 53
        },
        {
          "title": "2024 的300 个變裝皇后点子 - Pinterest",
          "link": "https://www.pinterest.com/gelin5138/%E8%AE%8A%E8%A3%9D%E7%9A%87%E5%90%8E/",
          "snippet": "2024年4月29日- 在Pinterest 上探索禹珊傅的图板“變裝皇后”。。查看更多关于變裝皇后, 化妆艺术, 变装皇后主题的点子。",
          "position": 54
        },
        {
          "title": "首尔变装游行将酷儿文化从夜总会带到日光下 - 海房网",
          "link": "http://m.91kutui.com/news/show/303641/",
          "snippet": "“有些场所甚至根据性别或性取向限制入场，所以我们想创造一个空间，让任何人都可以尝试变装，或者至少可以看到它。户外活动也是庆祝变装艺术和酷儿表演者的一 ...",
          "date": "7天前",
          "position": 55
        },
        {
          "title": "玩出艺术新高度——辰美体艺节系列活动之变装晚会精彩纷呈",
          "link": "https://m.ieduchina.com/school/education/202311/103210.html",
          "snippet": "灯光、糖果、音乐、舞蹈、走秀......轮番精彩上演11月1日晚由辰美学生会与学生处联合举办的体艺节变装晚会在充满艺术装置氛围的报告厅圆满举办辰美 ...",
          "date": "2023年11月6日",
          "position": 56
        },
        {
          "title": "喜报：艺传学生在第二届国际大学生艺术年度奖上斩获佳绩",
          "link": "https://www.xit.edu.cn/yishuxueyuan/ShowArticle.asp?ArticleID=14421",
          "snippet": "... 变装记》荣获第二届国际大学生艺术年度奖银奖。 庄毅插画作品《白衣战士变装记》. 学生获奖证书. 此次赛事由台北市政府教育局发起主办，联合台北艺术 ...",
          "date": "2020年9月7日",
          "position": 57
        },
        {
          "title": "鲁保罗变装皇后秀英国版_百度百科",
          "link": "https://baike.baidu.com/item/%E9%B2%81%E4%BF%9D%E7%BD%97%E5%8F%98%E8%A3%85%E7%9A%87%E5%90%8E%E7%A7%80%E8%8B%B1%E5%9B%BD%E7%89%88/53584693",
          "snippet": "... 变装皇后秀英国版》是由Tony Grech-Smith执导，鲁保罗、Michelle ... 编剧, 艺术指导. Fenton Bailey、Randy Barbato, Tony Grech-Smith, Christian Manley ...",
          "position": 58
        },
        {
          "title": "中华龙IP全国首展玩“变装”，上海复地活力城四周年庆超多福利",
          "link": "https://www.shxwcb.com/1124608.html",
          "snippet": "... 艺术共融的新纪元。 在商场内外，中华龙的不同造型演绎着全新的场景，让来往的顾客感到耳目一新。在外场点位，山水祥云植入龙的底座，金属朋克元素和 ...",
          "date": "2023年12月18日",
          "position": 59
        },
        {
          "title": "Prime Video: 《变装皇后杰米》",
          "link": "https://www.primevideo.com/-/zh/detail/%E3%80%8A%E5%8F%98%E8%A3%85%E7%9A%87%E5%90%8E%E6%9D%B0%E7%B1%B3%E3%80%8B/0PLOV52PKHQ9AIOR5CR9U215JA",
          "snippet": "这是一部根据真实故事改编的励志音乐剧，讲述的是16岁的杰米排除重重困难、勇敢追寻他那非传统的梦想的故事。 IMDb 6.51 小时56 分钟2021X-RayHDRUHDPG-13. 艺术、娱乐 ...",
          "position": 60
        },
        {
          "title": "喜迎春来——北京apm、NTP新城广场灯光艺术装置华丽变装",
          "link": "http://www.beijingapm.cn/index.php/Index/Index/news/id/339.shtml",
          "snippet": "2020年1月17日，临近春节，五大灯光艺术装置华丽变装，被春节元素装扮一新，暖色灯光交替变幻、炫彩夺目，洋溢出浓郁的中国年喜庆氛围。 五大灯光艺术装置华丽变装喜迎新年.",
          "position": 61
        },
        {
          "title": "舞台魔术-梦想家魔术",
          "link": "http://www.gzvmagic.com/wtms",
          "snippet": "以快速变装作为主导的魔术节目。当你眨眼间，魔术师也许就变换了一套新服饰 ... 中国传统艺术的结合表演。在这里，你能感受到属于中国文化的魔术魅力。 Drama ...",
          "position": 62
        },
        {
          "title": "蔡英文祝贺台湾变装皇后美国夺冠 - 博讯",
          "link": "https://boxun.com/archives/368456",
          "snippet": "蔡英文在X平台上用英文写道：“恭喜你，Nymphia Wind，在变装这一高难度的艺术形式上取得了如此大的成就，成为第一个登上鲁保罗变装大赛舞台并获得冠军的台湾人 ...",
          "date": "2024年4月20日",
          "position": 63
        },
        {
          "title": "让非遗文化“活”起来、“火”起来！安溪19岁高甲戏小生惊艳变装 - 新福建",
          "link": "https://www.fjdaily.com/app/content/2024-06/14/content_2594987.html",
          "snippet": "“视频能引起这么多关注，挺意外的。”安溪县文化体育和旅游局艺术股负责人谢玙璁介绍，在时下变装潮流带动下，他们想以一种新颖时尚的方式推介传统非遗安溪高甲戏，整个视频 ...",
          "position": 64
        },
        {
          "title": "这次你们觉得像谁？ #变装#妆前妆后#反差#爆改#艺术在抖音",
          "link": "https://www.douyin.com/video/7391036057568988450",
          "snippet": "这次你们觉得像谁？ #变装#妆前妆后#反差#爆改#艺术在抖音- 韩承羽于20240713发布 ...\n时长： 0:19\n发布时间： 2024年7月14日",
          "date": "2024年7月14日",
          "position": 65
        },
        {
          "title": "“日有所思，夜有所梦” 戏剧人Felicia Jiang专访 - ELLE中文网",
          "link": "https://www.ellechina.com/fashion/news/a44416364/16883858962/",
          "snippet": "在此之前她在欧洲的7年生活学习经历使得她将身份认同，东亚文化与欧洲中心主义的碰撞作为她戏剧艺术创作的重要议题。她的戏剧作品将当代艺术，酷儿变装文化和社群戏剧 ...",
          "position": 66
        },
        {
          "title": "变装皇后Mo Heart 关注庄重的风格和出色的营销| 亚马逊广告",
          "link": "https://advertising.amazon.com/zh-cn/library/expert-advice/mo-heart-style-and-brilliant-marketing",
          "snippet": "随着变装和酷儿艺术得到前所未有的主流关注，Heart 正在寻求一种平衡，即最大限度地利用她面前的机会，打造一个在Drag Race（变装皇后秀）之外引起共鸣的 ...",
          "date": "2023年6月27日",
          "position": 67
        },
        {
          "title": "变装文化，嘲弄性别的陈规陋习 - 三联生活周刊",
          "link": "https://www.lifeweek.com.cn/article/57796",
          "snippet": "虽然鞋厂还是在2000年倒闭了，但被收录在北安普顿艺术博物馆中的高跟男靴见证了那一时期兴盛的变装文化。 出现于19世纪的“变装皇后”一词指代装扮成女性进行娱乐表演的 ...",
          "position": 68
        },
        {
          "title": "梦想时间| UCCA尤伦斯当代艺术中心",
          "link": "https://ucca.org.cn/exhibition/dream-time/",
          "snippet": "单慧乾以“变装”作为具目的性的艺术体现，质疑归因于科技和观看系统中生成的理想形像的化身。他们的作品透过观看和渴望的个人经验，呈现建基于社会体系中个体不安经验的 ...",
          "position": 69
        },
        {
          "title": "老胡玩艺术的主页- 抖音",
          "link": "https://www.douyin.com/user/MS4wLjABAAAAI5HmpK2aP-owXFnBzKb4syyjs2xe825MxgNCh1p_wgJmO_mrFJBPzH43pRdtpM9n",
          "snippet": "#有桃花还有钱花#初五迎财神 · #名画模仿#名画#名画今天让我们来看看结婚一年后的情侣 · #变装100位艺术家——谁说相亲不能遇到真爱？！ · 做广播操时摔倒了！ · 变装100位艺术家VOL ...",
          "position": 70
        },
        {
          "title": "三丽鸥蛋仔魔幻艺术画贴贴画贴纸粘贴画diy创意刮画手工变装贴画评价",
          "link": "https://pingjia.taobao.com/7211f5f36da24110849c940511b9876d.html",
          "snippet": "用户购买三丽鸥蛋仔魔幻艺术画贴贴画贴纸粘贴画diy创意刮画手工变装贴画后使用体验报告，包含了图片、使用视频和使用后的口碑评价，帮你更好的了解这款商品.",
          "position": 71
        },
        {
          "title": "伦敦：格雷森·佩里陈列展 - 每日环球展览- iCity",
          "link": "https://art.icity.ly/entries/e5z5fcn",
          "snippet": "... 艺术展厅举行。 附展览信息： Grayson Perry：你是谁？ 2014年10月25日- 2015年3月15日英国国家肖像馆. St Martin's Pl，London WC2H 0HE Grayson Perry 从13岁起开始变装 ...",
          "position": 72
        },
        {
          "title": "25790 变装皇后图片、库存照片、3D 物体和矢量图 - Shutterstock",
          "link": "https://www.shutterstock.com/zh/search/%E5%8F%98%E8%A3%85%E7%9A%87%E5%90%8E",
          "snippet": "... 图和插图，可免版税下载。 查看变装皇后库存视频影片. 筛选条件. 图片类型. 服装和配饰 · 女性 · 科技 · 异装艺术 · 彩虹 · 连衣裙 · 女人 · 假髮 · 连体衣 · 異性裝扮 · 下 ...",
          "position": 73
        },
        {
          "title": "ROPPONGI ART NIGHT 2024 - 六本木アートナイト",
          "link": "https://www.roppongiartnight.com/2024/cn/",
          "snippet": "参展艺术家从过去以主要艺术家为中心的形式，变为“六本木艺术之夜”关注的 ... 他们从60年代的京剧电影和蔡明亮的电影作品中汲取灵感，通过性别转换变装 ...",
          "date": "2024年9月27日",
          "position": 74
        },
        {
          "title": "南大：公开表演不应涉及敏感主题将检讨内部程序 - 联合早报",
          "link": "https://www.zaobao.com.sg/realtime/singapore/story20231007-1440373",
          "snippet": "南大当代艺术中心的十周年活动，包括一场名为“酷儿歌台”（Queer-tai）的演出。这场表演中，一名表演者以变装皇后的造型亮相演出。（取自南大当代艺术中心脸 ...",
          "date": "2023年10月7日",
          "position": 75
        },
        {
          "title": "呼吸酱Una个人主页-哔哩哔哩视频 - BiliBili",
          "link": "https://space.bilibili.com/286824961/",
          "snippet": "... 玩游戏，分享伪娘变装艺术 展开. 动态 视频. 呼吸酱Una. 2021-10-07 · 投稿了视频. 01:05. 0弹幕. 上海明仪变装外出中～这姐们绝对有点社交牛叉症在身上，居然趁我跑 ...",
          "position": 76
        },
        {
          "title": "「变装皇后」妮妃雅为民主发声路透：台湾在国际的非官方大使",
          "link": "https://www.worldjournal.com/wj/story/121617/7988971?zh-cn",
          "snippet": "... 变装艺术节」举行回台后首次演出。(路透). 台湾变装皇后妮妃雅（Nymphia Wind）拿下美国实境节目《鲁保罗变装秀》（RuPaul's Drag Race）冠军一举成名 ...",
          "date": "2024年5月25日",
          "position": 77
        },
        {
          "title": "然后他提到历史上诸多变装的艺术表现形式，比如在古代，东西方的 ...",
          "link": "https://www.threads.net/@iohntownzhang/post/C_4gYZJN5iR",
          "snippet": "IohntownẐang (@iohntownzhang). 2 Replies. 抖音一位博主@DamianLA 借由RuPaul's Drag Race 介绍Drag Queen，然后他提到历史上诸多变装的艺术表现形式 ...",
          "date": "2024年9月13日",
          "position": 78
        },
        {
          "title": "变装小鬼设计元素下载-PNG素材网",
          "link": "https://www.pngsucai.com/free-png/1900159.html",
          "snippet": "卡通扇艺术变装 · 海盗小鬼 · 超人变装 · 小鬼南瓜头 · 卡通黑色幽灵小鬼 · 马匹卡通女佣变装马.",
          "position": 79
        },
        {
          "title": "為你選書｜《變裝的藝術》：顛覆想像！變裝就是一門戲耍性別的藝術",
          "link": "https://today.line.me/tw/v2/article/aGVGvo3",
          "snippet": "下列的變裝皇后，包含單慧乾（Victoria Sin）、加拉瑪（Glamrou）、惡童皇后（Imp Queen）和薄荷糖（Peppermint）──她於二〇一七年成了首位在《魯保羅變裝皇后秀》 ...",
          "date": "2021年11月9日",
          "position": 80
        },
        {
          "title": "菲律宾：宠物变装秀",
          "link": "https://luxury.huanqiu.com/article/4AQX1Del8dN",
          "snippet": "... ，在菲律宾奎松城，主人带着宠物犬参加万圣节变装 ... 艺术·文博 · 时尚 · 女性 · 体育 · 丝路 · 教育 · 房产 · 公益 · 城市 · 商业 · 听书 · 农业 · 文化 · 质量 ...",
          "position": 81
        },
        {
          "title": "瑞安•特雷卡丁的艺术",
          "link": "https://www.artforum.com.cn/print/200906/1929",
          "snippet": "... 艺术界。（艺术界：特雷卡丁需要它吗？）2006年，他又创作了七分钟长的录像 ... 在这个到处是变装皇后的母系社会里，改头换面随处可见，有的人甚至经历过好几轮变 ...",
          "position": 82
        },
        {
          "title": "姐弟变装图片素材下载 - 潮国创意",
          "link": "https://chaopx.com/img/121725.html",
          "snippet": "姐弟变装图片素材下载. 结果. 3D立体酸性变电子设备话筒 · 夏日瘦身变美计划夏天健身运动活动小红书分享长图H5 · 时光在变爱你不变艺术字 · 百变女神女装促销彩色卡通 ...",
          "position": 83
        },
        {
          "title": "最有气候意识意识的变装皇后 - Sustainability for Students",
          "link": "https://www.sustainabilityforstudents.com/post/%E6%9C%80%E6%9C%89%E6%B0%94%E5%80%99%E6%84%8F%E8%AF%86%E6%84%8F%E8%AF%86%E7%9A%84%E5%8F%98%E8%A3%85%E7%9A%87%E5%90%8E",
          "snippet": "在2021年，Bimini与Depop合作与出了新系列“让我们对话”来庆祝地球日。通过简单的交谈艺术，Depop的目标是将循环经济推广为一种充满希望和适用于所有人的时尚 ...",
          "date": "2024年2月28日",
          "position": 84
        },
        {
          "title": "变装动态图片_变装gif动图 - 千库网",
          "link": "https://588ku.com/gif/bianzhuang.html",
          "snippet": "全部 素材库 图片库 3D库 免抠元素 免抠艺术字 GIF动图 背景图 插画 摄影图 广告 ... 万圣节变身变装聚会跳舞舞会可爱动 ...",
          "position": 85
        },
        {
          "title": "酷哥野猪变装,CG插画,绘画艺术,摩尔网(CGMOL)",
          "link": "https://m.cgmol.com/cgshare/3806.html",
          "snippet": "... 变装,摩尔网-分享改变 ... 酷哥野猪变装. nilian-animation-studio-grimboar-web nilian-animation-studio-rapboar-2-web nilian-animation-studio ...",
          "position": 86
        },
        {
          "title": "《变装皇后的诞生》 | Netflix 官方网站",
          "link": "https://www.netflix.com/sg-zh/title/81140803",
          "snippet": "在这档变装改造节目中，格洛丽亚·律动和亚莉克希亚·旋风帮助六名艺人找到在舞台上的自信，让变装梦想成真。播放预告片及了解详情。",
          "position": 87
        },
        {
          "title": "文化：新闻、播客、视频和分析 - RFI",
          "link": "https://www.rfi.fr/cn/%E5%85%B3%E9%94%AE%E8%AF%8D/%E6%96%87%E5%8C%96/",
          "snippet": "... 艺术界同行眼里的林辉华 · 罗峥与她的团队. 文化艺术. 03/10/2024. 罗峥的丝绸 ... 变装皇后妮妃雅（右二））和疯家其他成员. 中华世界. 22/08/2024. 文化奥运：台湾馆 ...",
          "position": 88
        },
        {
          "title": "长源：一座被艺术“唤醒”的村庄 - 黄山市人民政府",
          "link": "https://www.huangshan.gov.cn/zxzx/qxdt/8406860.html",
          "snippet": "长源国际艺术村，依托文化艺术 ... 装”后成了艺术品；一台空调外机，创意改造后变身复古相机……村民们一看：呀，原来这就是设计？这就是艺术？高大上的艺术，一下子变 ...",
          "date": "4天前",
          "position": 89
        },
        {
          "title": "乌鲁木齐：南瓜艺术展十万南瓜共绘金秋画卷 - 中青在线",
          "link": "http://m.cyol.com/gb/articles/2024-09/19/content_4wodP8fWl7.html",
          "snippet": "2024年9月15日，乌鲁木齐，游客在南瓜艺术展上参观。 2024年9月15日 ... 上海展览中心华丽变装灯光视觉盛宴璀璨亮相 · 在额尔古纳遇见最美的秋天 ...",
          "date": "2024年9月19日",
          "position": 90
        },
        {
          "title": "变装国王和变装女王/变装皇后一样，都是有着悠久历史的表演艺术的 ...",
          "link": "https://www.reddit.com/r/cn_talk/comments/11u1hr8/%E5%8F%98%E8%A3%85%E5%9B%BD%E7%8E%8B%E5%92%8C%E5%8F%98%E8%A3%85%E5%A5%B3%E7%8E%8B%E5%8F%98%E8%A3%85%E7%9A%87%E5%90%8E%E4%B8%80%E6%A0%B7%E9%83%BD%E6%98%AF%E6%9C%89%E7%9D%80%E6%82%A0%E4%B9%85%E5%8E%86%E5%8F%B2%E7%9A%84%E8%A1%A8%E6%BC%94%E8%89%BA%E6%9C%AF%E7%9A%84%E4%B8%80%E9%83%A8%E5%88%86%E6%88%91%E4%BB%AC%E7%9A%84%E7%A4%BE%E4%BC%9A%E6%9C%89%E6%84%8F%E6%97%A0%E8%A7%86%E7%94%B7%E6%80%A7%E5%8C%96%E7%9A%84%E5%8F%98%E8%A3%85%E7%A7%80%E7%9A%84%E5%AD%98/",
          "snippet": "【网评】我很难过地发现居然有太多人不知道变装国王的存在了。如果更多人了解变装国王，也就会有更多人愿意投身到变装表演这种艺术中去。同时，变装表演 ...",
          "date": "2023年3月17日",
          "position": 91
        },
        {
          "title": "变装男友柠檬派_百度百科",
          "link": "https://baike.baidu.com/item/%E5%8F%98%E8%A3%85%E7%94%B7%E5%8F%8B%E6%9F%A0%E6%AA%AC%E6%B4%BE/16624041",
          "snippet": "... 《变装男友柠檬派》是2013年湖南少年儿童出版社出版的图书， ... 为了近距离接触偶像延正雨，夏柠檬拼尽全力考入科林艺术学院，不料却与一个个性 ...",
          "position": 92
        },
        {
          "title": "巴黎奥运会开幕式遭痛批，变装艺术惹怒宗教群体，奥组委紧急道歉",
          "link": "https://www.163.com/dy/article/J8C8L9PL0552R9P2.html",
          "snippet": "奥组委通过艺术形式重现了达·芬奇的名画《最后的晚餐》，原画呈现的是基督教历史上极为神圣的一个场景。然而，在开幕式上，耶稣和十二门徒皆由变装皇后、跨 ...",
          "date": "2024年7月30日",
          "position": 93
        },
        {
          "title": "秋叶艺术节来袭，跟着'落叶兔'畅游九寨沟！ - 搜狐",
          "link": "https://roll.sohu.com/a/822996905_121956422",
          "snippet": "艺术装置展览：在九寨的山中，将会有13件由艺术家创作的装置呈现，探访这些作品如同参与一场神秘的寻宝之旅。 · 变装秀与当地文化：展览当天，众多艺术爱好者身 ...",
          "date": "2天前",
          "position": 94
        },
        {
          "title": "表演藝術新潮流不為人知的變裝藝術家 - PeoPo 公民新聞",
          "link": "https://www.peopo.org/news/688358",
          "snippet": "變裝皇后(Drag Queen)源自於1870年代，是一種男性透過浮誇的妝髮和服裝，以「女裝」呈現的表演方式，後續更加入了許多同志人士，協力推動這門藝術，顛覆了先前 ...",
          "date": "2024年6月7日",
          "position": 95
        },
        {
          "title": "加拿大：“变装”长跑 - 新华网",
          "link": "http://www.news.cn/photo/2021-10/25/c_1127991587.htm",
          "snippet": "... ：“变装”长跑---10月24日，穿着动漫服装的人们在加拿大多伦多参加“变装 ... 埃及首届金字塔国际艺术展开幕.",
          "date": "2021年10月25日",
          "position": 96
        },
        {
          "title": "艺术- BBC News 中文",
          "link": "https://www.bbc.com/zhongwen/simp/topics/czp1qex2jy8t",
          "snippet": "艺术 · 台湾反串艺人与变装皇后 · 该片在中国戏院累计观影人次已经突破千万，从今年 · 张晓昂解释说，从构思到下笔，她花了约莫六年的 · 2016年6月1日，五月天乐队主唱阿信香港举行 ...",
          "position": 97
        },
        {
          "title": "美节目「鲁保罗变装皇后秀」首位台湾人妮妃雅掀黄色旋「疯」",
          "link": "https://www.iask.ca/news/648482",
          "snippet": "第16季竞赛将于1月5日登场，来自台湾的妮妃雅（Nymphia Wind）与其他13名参赛者在全球最知名的变装艺术舞台争奇斗艳，争夺「下一位变装巨星」的头衔。 「非常 ...",
          "date": "2023年12月19日",
          "position": 98
        },
        {
          "title": "悉尼歌剧院变装秀？！ - Apple 101°",
          "link": "https://apple101.com.my/2013/05/%E6%82%89%E5%B0%BC%E6%AD%8C%E5%89%A7%E9%99%A2%E5%8F%98%E8%A3%85%E7%A7%80%EF%BC%9F%EF%BC%81/",
          "snippet": "澳洲Vivid Sydney创意艺术节，今年将正式迈入第六年，在过去五年里它為悉尼带来了大量的人潮，来自世界各地的游客无一不赞叹那被五光十色的灯光点缀得绚烂 ...",
          "date": "2013年5月27日",
          "position": 99
        },
        {
          "title": "变装派对造型专题模板 - 我图网",
          "link": "https://m.ooopic.com/sousuo/32246008/",
          "snippet": "原创万圣节PPT模板节日活动策划鬼节变装狂欢派对 · 万圣节儿童变装派对紫色卡通海报 · 万圣节搞怪手机海报朋友圈微信海报变装派对 · 变装派对万圣节艺术字免费下载.",
          "position": 100
        }
      ],
      "credits": 2
    },
    {
      "searchParameters": {
        "q": "变装艺术",
        "gl": "cn",
        "hl": "zh-cn",
        "type": "search",
        "num": 100,
        "page": 2,
        "engine": "google"
      },
      "organic": [
        {
          "title": "变装皇后绘画时尚女孩绘画肖像女人原创艺术- Pinkoi | 相似推薦",
          "link": "https://messenger.pinkoi.com/recommend/product/ftFspRf9",
          "snippet": "Pinkoi 販售設計商品、數位創作、體驗活動，堅持用好品味、客製化的獨特設計，實現每個人對生活詮釋的想像，也讓每個送禮時刻更加獨一無二。",
          "position": 1
        },
        {
          "title": "表演藝術新潮流不為人知的變裝藝術家 - PeoPo 公民新聞",
          "link": "https://www.peopo.org/news/688358",
          "snippet": "變裝皇后(Drag Queen)源自於1870年代，是一種男性透過浮誇的妝髮和服裝，以「女裝」呈現的表演方式，後續更加入了許多同志人士，協力推動這門藝術，顛覆了先前 ...",
          "date": "2024年6月7日",
          "position": 2
        },
        {
          "title": "小雀斑变性记，《丹麦女孩》完美变装的秘密 - 影视工业网",
          "link": "https://cinehello.com/stream/124794",
          "snippet": "只是随着沉睡女性人格的被唤醒，艾纳开始厌恶自己作为男性的身体，他渐渐发现莉莉不但是艺术存在，更是真正的自己。格尔达也没有想到只是临时起意的 ...",
          "date": "2020年4月16日",
          "position": 3
        },
        {
          "title": "双人变装秀：开灯关灯的魔幻时刻 - 搜狐",
          "link": "https://m.sohu.com/a/812713358_121924583",
          "snippet": "所谓的“开灯关灯变装”，其实是一种通过灯光变化来快速切换服装和角色的艺术表演。演出中，演员在灯光一闪而灭的瞬间，利用舞台的技巧瞬间换装，给人一种时空 ...",
          "date": "2024年9月29日",
          "position": 4
        },
        {
          "title": "苏富比官宣艺术家恩利领军Theirsverse将拍卖",
          "link": "http://www.zgshuhuajia.com/show.asp?id=783",
          "snippet": "不同于传统原生艺术家终身单独创作，年轻世代的Web3 艺术家，将宇宙观、反抗、自我态度，通过技术、共创，打造出新的艺术语言。 ... 此红色皇后为变装皇后系列，是少数数字藏品中 ...",
          "position": 5
        },
        {
          "title": "逗万变装笔|从引力哲学到超跑时尚，文具世界的无限可能",
          "link": "http://www.damiwonka.com/index.php?m=home&c=View&a=index&aid=171",
          "snippet": "引力系列以太极东方哲学为灵感，打造出阴阳结合的东方美学艺术，引发哲学思考；山海经系列，将《山海经》中的神秘神兽融入笔身设计，每一笔一划间都流淌着千年 ...",
          "date": "2024年7月31日",
          "position": 6
        },
        {
          "title": "执著自拍四十年她进入了艺术史",
          "link": "https://www.visitbeijing.com.cn/article/47QnrupnZsK",
          "snippet": "... 变化让人觉得神奇。很多孩子小时候都喜欢玩变装游戏，舍曼也不例外，但是她长大后还在继续！ 舍曼出生于新泽西州格伦里奇，属于长岛郊区，他们一家虽然离纽约很近，但 ...",
          "position": 7
        },
        {
          "title": "特效天才！超酷的变装过度-视觉探索 - 新片场",
          "link": "https://www.xinpianchang.com/a12056566?kw=Nathan+Kaso&from=search_post",
          "snippet": "超酷的变装过度来自创作人会玩创意站的视频作品, 新片场汇聚全球优质创作人及原创视频下载, 辽宁视觉探索作品拍摄制作公司提供视觉探索和视觉艺术相关的",
          "date": "2022年8月8日",
          "position": 8
        },
        {
          "title": "有机扎染师 - 宜家",
          "link": "https://www.ikea.cn/cn/zh/ideas/storage-story/the-organic-tie-dyer-pubf6c4a35f",
          "snippet": "在艺术创作过程中，Audrey需要合适的艺术工作室储物方案，来制作、晾干和 ... 变装皇后. 变装皇后 · 一位戴墨镜的女士站在草地边，肩上扛着摄像机. 充满诗情的摄影 ...",
          "position": 9
        },
        {
          "title": "若非50年前的这场“石墙”暴动，今日的艺术光景是否大不相同？",
          "link": "https://www.artnetnews.cn/art-world/ruofei50nianqiandezhechangshiqiangbaodongjinrideyishuguangjingshifoudabuxiangtong-114841",
          "snippet": "6月28号的凌晨，8个警察突袭石墙酒吧，逮捕了13个酒吧工作人员和异装人士（在当时的纽约，“变装\"异性是违法的）。也许是因为对纽约警察长久骚扰还有各 ...",
          "date": "2019年6月27日",
          "position": 10
        },
        {
          "title": "人生奇旅妙想无界梅赛德斯-奔驰V级MPV上演“变装”大秀 - 读特",
          "link": "https://m.dutenews.com/p/6824374.html",
          "snippet": "作为“好奇无界”米奇艺术展中国巡展的首席赞助伙伴，梅赛德斯-奔驰V级MPV突破固有边界，携手青年艺术家陈粉丸女士，以现代艺术的创新表达探索想象力的无穷 ...",
          "date": "2022年6月11日",
          "position": 11
        },
        {
          "title": "成都反串拍照反串写真摄影变装写真摄影Lisa小姐姐/乔伊摄影作品_人像",
          "link": "https://www.poco.cn/works/detail_id20025252",
          "snippet": "... 变装会所我们是专业的变装私房摄影机构！ ... 反串艺术照. 1 条评论. 秋意浓. 新年快乐，欢迎回访指教！ 18年02月17日.",
          "date": "2018年2月18日",
          "position": 12
        },
        {
          "title": "学院动态| 艺传学子在第二届国际大学生艺术年度奖上斩获大奖",
          "link": "https://www.xit.edu.cn/Article/ShowArticle.asp?ArticleID=14453",
          "snippet": "近日，第二届国际大学生艺术年度奖评选结果新鲜出炉。艺术与传媒学院周杨东方老师指导的2018级动画专业学生庄毅插画作品《白衣战士变装记》荣获第二届国际大学生艺术 ...",
          "position": 13
        },
        {
          "title": "汉服变装、夜巡古城...丽江益田汉服文化节带给游客别样体验 - 文旅头条",
          "link": "http://m.wenlvnews.com/p/384412.html",
          "snippet": "五子棋比赛：冠军将获得NEX 3S项圈磁吸蓝牙耳机一副；亚军将获得RECCL无线蓝牙耳机一副；前10名将获得嘿猴代金券2张；参与奖将获得梵高星空艺术馆门票1张。",
          "date": "2020年10月1日",
          "position": 14
        },
        {
          "title": "被疏离的行为艺术，如何再度拽入中国当代艺术的视野 - 360Doc",
          "link": "http://www.360doc.com/content/23/0516/17/37024376_1080937194.shtml",
          "snippet": "参考当代生活中另类时尚、明星效应和变装文化如何灵活的篡改身体的外貌 ... “活成行为艺术家——2023行为艺术文献展”目前正在上海没顶美术馆展出 ...",
          "date": "2023年5月16日",
          "position": 15
        },
        {
          "title": "艺术还在：一场闭馆期间的展览2020. 2. 13 - 持续进行展厅【0326BY】",
          "link": "https://mwoods.org/0402ZZ",
          "snippet": "该作品属于一个持续进行中的单刷版画作品系列（也可称之为绘画），它如死亡面具一般记录并纪念着艺术家演出的每一个变装化身、人物角色及其情感。 ... 更多参展艺术家和艺术 ...",
          "position": 16
        },
        {
          "title": "公司介绍_上海莫丽斯实业有限公司",
          "link": "http://molisshanghai.dsdz318.com/introduce/",
          "snippet": "... 艺术”，颠覆传统美学观念，完成CD时尚届BIBLE的历史使命。 Moli's 如何区别于普通的反串摄影工作室？ 不仅仅是提供世界一流的变装产品，而是完全从每一位顾客的细腻心思出发。",
          "position": 17
        },
        {
          "title": "静安案例展| 本周日，时“毛”艺术家共创活动 - 澎湃新闻",
          "link": "https://m.thepaper.cn/newsDetail_forward_25468333",
          "snippet": "原创SUSAS 上海城市空间艺术季. 万象共创活动. 时“毛”艺术家. DATE：2023.12.03. TIME：14：30--16：00. 【萌宠变装秀】——宠物变装大赛. 共创艺术家. 杨柳.",
          "date": "2023年11月29日",
          "position": 18
        },
        {
          "title": "台湾首位摘美变装秀后冠总统感谢妮妃雅勇敢做自己| 世界新闻网",
          "link": "https://www.worldjournal.com/wj/story/121478/7914275?from=wj_maintab_cate&zh-cn",
          "snippet": "总统表示，「变装皇后是一门非常不容易的表演艺术，恭喜妮妃雅成为台湾第一位站上RuPaul's Drag Race，并夺得总冠军的皇后。」 总统说：「夺冠时，妳说：Taiwan, ...",
          "date": "2024年4月21日",
          "position": 19
        },
        {
          "title": "上海警方严防万圣节街头变装活动据报有人在警局卸妆 - 联合早报",
          "link": "https://www.zaobao.com.sg/news/china/story20241027-5254654",
          "snippet": "特写 美食 旅行 文化艺术 人文史地 专栏 @世代 生态与环保 时尚与美容 ... （上海综合讯）万圣节将至，上海警方在去年的变装狂欢中心区域加强管控，严防街头变装 ...",
          "date": "8天前",
          "position": 20
        },
        {
          "title": "东伦敦俱乐部十年纪 - Art-Ba-Ba 中国当代艺术社区",
          "link": "http://www.art-ba-ba.com/main/view.art?threadId=190117&forumId=8",
          "snippet": "东区三大青年向俱乐部各司其职，Dalston Superstore 专意与变装皇后、野生超模和涂鸦艺术家合作；Café OTO 是日本向实验音乐圣地；Vogue Fabrics 则带着知识 ...",
          "date": "2018年6月29日",
          "position": 21
        },
        {
          "title": "“不安的绘画”系列影像分享：摇身一变| UCCA尤伦斯当代艺术中心",
          "link": "https://ucca.org.cn/program/painting-unsettled-series-screening-persona-swap/",
          "snippet": "... 艺术家在现代主义艺术史中缺席”的问题。此次放映的影像作品《另一个“他 ... 就像影片中那些重新摆拍的“配角儿”，无论以何种姿态倒下，都不过是一种变装 ...",
          "date": "2023年4月1日",
          "position": 22
        },
        {
          "title": "第九届柏林双年展：变装的当下- 燃点Ran Dian",
          "link": "http://www.randian.art/zh-hans/%E7%AC%AC%E4%B9%9D%E5%B1%8A%E6%9F%8F%E6%9E%97%E5%8F%8C%E5%B9%B4%E5%B1%95%EF%BC%9A%E5%8F%98%E8%A3%85%E7%9A%84%E5%BD%93%E4%B8%8B/",
          "snippet": "纽约时装品牌Telfar就在柏林艺术学院（Akademie der Künste）的入口处拥有一个展位，贩售90欧元一件的T恤衫。紧邻的“LIT”试图用从中国的曹斐到美国的马丁·希 ...",
          "date": "2016年6月9日",
          "position": 23
        },
        {
          "title": "美过刘亦菲？看粤剧花木兰“双面”变装秀｜艺术咖 - 南方+",
          "link": "https://static.nfapp.southcn.com/content/202009/23/c4077362.html",
          "snippet": "本期艺术咖，小南带你来到粤剧《花木兰》的后台，看这两位青春靓丽的粤剧演员，如何在化妆师的巧手下，变身气宇轩昂的巾帼英豪。 戳视频，看粤剧演员的变装秀↓.",
          "date": "2020年9月24日",
          "position": 24
        },
        {
          "title": "千万别眨眼！ - 光明网",
          "link": "https://m.gmw.cn/toutiao/2024-11/01/content_1303886203.htm",
          "snippet": "点蓝色字关注“央视新闻”近日，婺剧《三打白骨精》在浙江绍兴上演，演员在变脸的同时还能瞬间变装，让无数网友惊叹“太惊艳了，第一次看到'变脸+变装'的”。",
          "date": "3天前",
          "position": 25
        },
        {
          "title": "Top 100件变装舞会面具- 2024年10月更新- Taobao",
          "link": "https://www.taobao.com/list/product/%E5%8F%98%E8%A3%85%E8%88%9E%E4%BC%9A%E9%9D%A2%E5%85%B7.htm",
          "snippet": "... 变装舞会面具相关的商品在售，其中按品牌划分，有DIY3件、爱新奇12件、舞耀13件。 在这些变装舞会面具的面具类型有恶棍搞笑和恐怖等多种，在变装 ... 变装道具舞会艺术白假面.",
          "position": 26
        },
        {
          "title": "音乐舞蹈学院- 【党史学习教育】用艺术讲好红色文化 - 华侨大学新闻网",
          "link": "https://news.hqu.edu.cn/info/1019/234071.htm",
          "snippet": "化身一朵朵三角梅，奋力盛开在新时代；变装一个个俏花旦，舞出京剧国粹经典；穿越到1937年，演绎女学生们与侵略者斗争的果敢与勇毅；置身黄河岸边， ...",
          "date": "2021年6月17日",
          "position": 27
        },
        {
          "title": "冷门艺术进课堂如何“爆改”年轻人？ - 海报新闻",
          "link": "https://hb.dzwww.com/p/p2aDGfTO8Gf.html",
          "snippet": "在这门大学通识课上，身着戏服的老师舞着水袖、耍着刀枪，学生不仅看得津津有味，还争相“变装”上台表演。在一层一层上油彩、一句一句念唱词中，学生们近距离 ...",
          "date": "2024年3月28日",
          "position": 28
        },
        {
          "title": "Netflix《鲁保罗变装皇后秀》美丽的背后意味着什么 ... - 女人迷Womany",
          "link": "https://cn.womany.net/read/article/32880",
          "snippet": "变装皇后是如何从地下文化崛起为艺术？从《鲁保罗变装皇后秀》一窥变装皇后的历史、影响力及争议！",
          "date": "2024年3月27日",
          "position": 29
        },
        {
          "title": "TANK Artist Takeover | 变装皇后Victoria Sin_上海油罐艺术中心",
          "link": "https://m-news.artron.net/20200612/n1079703.html",
          "snippet": "TANK Artist Takeover | 变装皇后Victoria Sin. 2020-06-12 17:52:16 上海油罐艺术中心. 作为即将开幕的展览《More, More, More》“艺术家接管计划”的一部分，本周我们 ...",
          "position": 30
        },
        {
          "title": "中国男性穿裙参加变装大赛：别叫我们变态娘娘腔 - 新闻频道",
          "link": "http://news.cctv.com/2016/05/02/ARTINmz5ZYihLNM9WjYmT9iF160502.shtml",
          "snippet": "“我希望他们能站出来，我想让他们见见天日，告诉社会中国有变装皇后，且他们的艺术是美丽的。” 于小洋最后得了季军，他用派对气球填补了胸前的空缺 ...",
          "date": "2016年5月2日",
          "position": 31
        },
        {
          "title": "绳艺体验 - 广州玲距离变装摄影工作室官方网站",
          "link": "http://www.ljlcd.com/price",
          "snippet": "自助变装特价1288元 当天22:00前可自助变装更换指定服装不限次数. 温馨说明 ... 3.2 人体艺术写真 6800元. 使用化妆技术和技术手段，把身体上身(包括上身和下身) ...",
          "position": 32
        },
        {
          "title": "龙年变装图片 - 千库网",
          "link": "https://m.588ku.com/image/116211110.html",
          "snippet": "全部 素材库 图片库 3D库 免抠元素 免抠艺术字 GIF动图 背景图 插画 摄影图 广告设计 UI设计 视频素材 音频音效 ppt模板 word文档 手抄报 Excel模板 · 全部 素材库 图片 ...",
          "position": 33
        },
        {
          "title": "花瓣网-Rupaul's Drag Race / 鲁保罗变装皇后秀》正式在Logo电视台 ...",
          "link": "https://huaban.com/pins/3744231395/",
          "snippet": "——我把四季用来... 147. 花间禅院 采集到. 乙-艺术禅之书画禅.",
          "date": "2021年2月3日",
          "position": 34
        },
        {
          "title": "美国男化妆师变装经典女性卡通角色成网红 - 中国在线",
          "link": "https://cnews.chinadaily.com.cn/a/201902/08/WS5c5ccb67a31010568bdc8b41.html",
          "snippet": "【环球网综合报道】据英国《每日邮报》2月1日报道，近日，美国加州25岁的化妆师理查德·谢弗(Richard Schaefer)因完美变身迪斯尼卡通人物和艺术作品而 ...",
          "date": "2019年2月8日",
          "position": 35
        },
        {
          "title": "变身古画中人在博物馆跨年是什么感受？看展览原来可以这么好玩",
          "link": "https://www.jfdaily.com/staticsg/res/html/web/newsDetail.html?id=699832&sid=11",
          "snippet": "隔着一道几乎看不见的低反玻璃，历史与现实、艺术与生活、东方与 ... 在鼓励观众们沉浸式观展之时，上海博物馆带头“变装”。去年“今夜无眠·上博 ...",
          "date": "2023年12月31日",
          "position": 36
        },
        {
          "title": "美国国家级亚洲艺术博物馆“变装”重启 - 新浪四川",
          "link": "http://sc.sina.cn/art/yxdg/2017-10-16/ys-ifymviyp1519116.d.html",
          "snippet": "弗里尔美术馆完成“变装”重启，于11日举办媒体预展。",
          "date": "2017年10月16日",
          "position": 37
        },
        {
          "title": "中国艺术与女权主义– artforum.com.cn",
          "link": "https://www.artforum.com.cn/slant/11496",
          "snippet": "... 艺术，没有想到女艺术家的问题。”五年后，在他策划的另一次群展“墙 ... 这部影像是一场形式上的变装秀，Ta的画外音明显是一个女人的声音，却以 ...",
          "date": "2018年7月7日",
          "position": 38
        },
        {
          "title": "【異色變裝】所以⋯⋯男扮女裝超浮誇對嘴有什麼好看？ - 劇說戲言",
          "link": "https://theatretalk.com.tw/topic/classic-elements-and-charisma-of-drag-shows/",
          "snippet": "——淺談變裝秀之經典元素及其魅力點. Drag作為一門表演藝術，即使「假」也不讓人感覺空虛造作，就是因為這些看似虛華 ...",
          "date": "2024年4月9日",
          "position": 39
        },
        {
          "title": "“You Better Werq!”最大規模變裝盛事「台北國際變裝藝術節」魯保羅 ...",
          "link": "https://www.vogue.com.tw/entertainment/article/entertainmen-you-better-werq",
          "snippet": "“You Better Werq”最大規模變裝盛事「台北國際變裝藝術.",
          "date": "2023年1月6日",
          "position": 40
        },
        {
          "title": "巴黎奥运变装皇后 - 西瓜视频",
          "link": "https://m.ixigua.com/zhuanti/7398250083353118756",
          "snippet": "巴黎奥运会开幕式遭痛批，变装艺术惹怒宗教群体，奥组委紧急道歉. 3次播放 2024-08-01. 巴黎奥运会开幕式，变装皇后与《最后的晚餐》引争议.",
          "date": "2024年8月1日",
          "position": 41
        },
        {
          "title": "东海国际艺术节10/6登场花博变装走秀吸睛 - 臺中觀光旅遊網",
          "link": "https://www.taichung.travel/zh-cn/event/newsdetail/3641",
          "snippet": "迈入第五届的东海国际艺术节将於10月6日在东海艺术街柯比意广场盛大举办，今年以「花漾艺术˙东海好优雅」为主题，活动包括变装走秀、花漾市集、街头艺人 ...",
          "date": "2018年9月27日",
          "position": 42
        },
        {
          "title": "Michou酒店 - Come to Paris",
          "link": "https://www.cometoparis.com/chi/catalog/michou-125",
          "snippet": "... 变成一场令人眼花缭乱的表演。 歌舞伎变装艺术在巴黎之心. 在Chez Michou歌舞伎餐厅的中心，灯光渐暗，幕布升起，魔法开始。台上，化妆打扮得惊人的变装艺术家们 ...",
          "rating": 4.9,
          "ratingCount": 11,
          "position": 43
        },
        {
          "title": "变装皇后接触儿童利还是弊？ - 加拿大七天资讯网",
          "link": "https://septdays.com/?p=21280",
          "snippet": "到了上个世纪20年代，变装的男性表演开始和LGBT社区结合起来，而随着男同性恋以及性工作者参与“变装”表演后，变装表演开始从主流的艺术表演形式慢慢的 ...",
          "date": "2023年4月14日",
          "position": 44
        },
        {
          "title": "刘宇宁秀演技？好六街上演“惊喜变装夜” - 新快报",
          "link": "https://www.xkb.com.cn/articleDetail/354309",
          "snippet": "新快报讯本周好六街开启“惊喜变装夜”，《锦绣安宁》主演张晚意、任敏与苏醒、刘宇宁、付航、张颜齐、石凯、李雪琴、丁程鑫、杨迪以两人一组的形式开启 ...",
          "date": "2天前",
          "position": 45
        },
        {
          "title": "欣意·新春报道（8）：点燃全场！山大校友在春晚舞台表演国风变装节目",
          "link": "https://www.view.sdu.edu.cn/info/1003/187848.htm",
          "snippet": "朱铁雄是山东大学2013级环境艺术设计专业校友。从孙悟空到哪吒，从二郎神到“常山赵子龙”，在朱铁雄的视频里，用特效变装的形式，展现国风 ...",
          "date": "2024年2月11日",
          "position": 46
        },
        {
          "title": "好莱坞女星其实是男人？Drag Queen到底是什么来头？！｜ Yoho!Boys",
          "link": "https://www.yohoboys.com/yohonow/html/content/detail?id=70127&app=1&t=1502159075",
          "snippet": "把变装当成是一门艺术和职业. 说起变装皇后Drag Queen，相信很多人并不了解他们的存在吧。作为特殊职业人群之一，从面对歧视、谩骂再到接受、认可这 ...",
          "date": "2018年12月20日",
          "position": 47
        },
        {
          "title": "“春藤蔓展·华年秀裳”银川西夏区怀远红酒街华服艺术节开幕 - 宁夏频道",
          "link": "http://nx.people.com.cn/n2/2023/0430/c192493-40399349.html",
          "snippet": "人民网银川4月30日电（周航）古风市集、国潮汉服街头秀、古风变装体验……“五一”假期，你若前往银川市西夏区怀远红酒街，常常会偶遇一群身穿汉服的“古人”， ...",
          "date": "2023年4月30日",
          "position": 48
        },
        {
          "title": "39 个Drag queen 点子| 变装皇后, 艺术, 木炭画 - Pinterest",
          "link": "https://www.pinterest.com/haoyiwang8262/drag-queen/",
          "snippet": "2020年8月1日- 在Pinterest 上探索HAOYIWANG 的图板 “Drag queen”。。查看更多关于变装皇后, 艺术, 木炭画主题的点子。",
          "position": 49
        },
        {
          "title": "上海展览中心华丽变装灯光视觉盛宴璀璨亮相 - 中青在线",
          "link": "http://m.cyol.com/gb/articles/2024-09/19/content_JQpYOECZyw.html",
          "snippet": "上海展览中心华丽变装灯光视觉盛宴璀璨亮相. 视觉中国 | 2024-09-19 ... 乌鲁木齐：南瓜艺术展十万南瓜共绘金秋画卷 · 合肥肥东县发生4.7级地震居民前往户外避险 ...",
          "position": 50
        },
        {
          "title": "Good Juju： Jujubee 谈论真实性、与受众的连接以及做自己的重要性",
          "link": "https://advertising.amazon.com/zh-cn/blog/how-rupauls-drag-race-star-jujubee-built-her-brand",
          "snippet": "鲁保罗变装皇后秀给了我一个卓越的平台和无数机会。粉丝们太不可思议了 ... 我认识到自己必须通过提升自己的艺术水平并与受众一起成长来挑战自己。",
          "date": "2022年7月14日",
          "position": 51
        },
        {
          "title": "清迈歌舞表演泰国女妖变装皇后秀门口涂鸦艺术编辑类库存照片. 图片 ...",
          "link": "https://cn.dreamstime.com/%E6%B8%85%E8%BF%88%E6%AD%8C%E8%88%9E%E8%A1%A8%E6%BC%94%E6%B3%B0%E5%9B%BD%E5%A5%B3%E5%A6%96%E5%8F%98%E8%A3%85%E7%9A%87%E5%90%8E%E7%A7%80%E9%97%A8%E5%8F%A3%E6%B6%82%E9%B8%A6%E8%89%BA%E6%9C%AF-%E6%B3%B0%E5%9B%BD%E6%B8%85%E8%BF%88-%E2%80%94-%E5%B9%B4-%E6%9C%88-%E6%97%A5%EF%BC%9A%E4%B8%96%E7%95%8C%E8%91%97%E5%90%8D%E5%8F%98%E8%A3%85%E5%A5%B3%E7%8E%8B%E7%A7%80ladyboy-image182517863",
          "snippet": "照片关于泰国清迈— 2020年1月10日：世界著名变装女王秀Ladyboy Cabaret入口墙壁艺术卡通涂鸦. 图片包括有附庸风雅, 绘画, 聚会所- 182517863.",
          "position": 52
        },
        {
          "title": "國際變裝藝術節妮妃雅奪冠後首公開演出【最新快訊】 - YouTube",
          "link": "https://www.youtube.com/watch?v=VBtEFcA_7PY",
          "snippet": "變裝皇后#魯保羅變裝皇后秀#妮妃雅2024.05.25【最新快訊】知名美國實境節目「魯保 ...\n时长： 0:54\n发布时间： 2024年5月25日",
          "date": "2024年5月25日",
          "position": 53
        },
        {
          "title": "台北國際變裝藝術節With Miss Vanjie & Naomi Smalls - KKTIX",
          "link": "https://cumpartytw.kktix.cc/events/youbetterwerq",
          "snippet": "魯保羅變裝秀巨星Vanessa Vanjie Mateo ＆ Angele Anang 降臨寶島//台灣史上規模最大變裝盛事//網羅本地最受歡迎共39位皇后及表演者全員集合同台爭豔.",
          "position": 54
        },
        {
          "title": "免费变装舞会模板 - Fotor懒设计",
          "link": "https://www.fotor.com.cn/templates/tag-bianzhuangwuhui-369h",
          "snippet": "Fotor懒设计提供免费变装舞会模板、变装舞会设计素材、变装舞会图片，在线编辑变装舞会模板，文字图片背景皆可修改，简单3步在线完成平面设计，并能下载高清变装舞会图片。",
          "position": 55
        },
        {
          "title": "比女人还美的变装皇后是妈妈的骄傲 - 风采Feminine",
          "link": "https://feminine.com.my/news/%E6%AF%94%E5%A5%B3%E4%BA%BA%E8%BF%98%E7%BE%8E%E7%9A%84%E5%8F%98%E8%A3%85%E7%9A%87%E5%90%8E-%E6%98%AF%E5%A6%88%E5%A6%88%E7%9A%84%E9%AA%84%E5%82%B2/",
          "snippet": "... 艺术总监，从表演方式、编舞、服装、造型、道具等等，一整个秀都要靠自己独立完成。”已有6年变装经验的Yolanda这么说。 来自台湾的Yolanda身材高挑 ...",
          "date": "2021年12月17日",
          "position": 56
        },
        {
          "title": "[艺览天下]变装魔术师 - CCTV节目官网",
          "link": "https://tv.cctv.com/v/v1/VIDEigpgx5fX0aRFj9PSAHyP211209.html",
          "snippet": "更新时间：2021-12-09 03:37 · 来源：央视网. 视频简介：变装魔术师。 · 视频简介：变装 ...\n发布时间： 2021年12月9日",
          "date": "2021年12月9日",
          "position": 57
        },
        {
          "title": "婺剧变装：传统与现代的视觉盛宴 - 新闻- 搜狐",
          "link": "https://news.sohu.com/a/821262286_121798711",
          "snippet": "从古典的妆容到现代的造型，婺剧变装不仅保留了传统的韵味，还融入了现代审美的元素，使得这一古老的艺术形式焕发出新的生命力。许多观众认为婺剧变装是 ...",
          "date": "7天前",
          "position": 58
        },
        {
          "title": "百老汇变装早午餐| 华盛顿特区 - Washington DC",
          "link": "https://washington.org/zh-CN/event/broadway-drag-brunch",
          "snippet": "百老汇变装早午餐. 分享这个. Facebook Pinterest Twitter LinkedIn. 面包屑. 首页 · 活动 ... 肯尼迪中心表演艺术. 2700 F圣西北 华盛顿, DC 20566 美国. (202) 416-8090 ...",
          "position": 59
        },
        {
          "title": "艺术用品收纳：创意设计 - 宜家",
          "link": "https://www.ikea.cn/cn/zh/ideas/storage-story/fu4-gu3-huang2-yi1-yi4-shu4-jia1-pubad3b14fc",
          "snippet": "她热衷于烫木成画（烙画艺术），这是一种有助于身心放松的艺术形式，她通过 ... 一个化了妆、戴着发网的人正在收拾变装皇后. 变装皇后 · 一位戴墨镜的女士站在草地边 ...",
          "position": 60
        },
        {
          "title": "快速变装！Quick Change 要让你不相信你自己的眼睛☺️ - Facebook",
          "link": "https://es-la.facebook.com/yeapmagic/videos/1507012955992542/",
          "snippet": "Yeap Magic 魔术学院与娱乐制作 celebrando 指导老师栽培出国际魔术比赛 冠军魔术 ...\n时长： 0:33\n发布时间： 2016年6月19日",
          "date": "2016年6月19日",
          "position": 61
        },
        {
          "title": "瞬间变脸+变装你见过吗？千万别眨眼！",
          "link": "https://xinwen.bjd.com.cn/content/s672430dde4b0f72813bd788f.html",
          "snippet": "近日，婺剧《三打白骨精》在浙江绍兴上演，演员在变脸的同时还能瞬间变装，让无数网友惊叹“太惊艳了，第一次看到'变脸+变装'的”。 “白骨精变身”的背后有着 ...",
          "date": "3天前",
          "position": 62
        },
        {
          "title": "惊艳变脸与变装！揭秘婺剧舞台背后的传承与创新 - 搜狐",
          "link": "https://roll.sohu.com/a/822979963_121956424",
          "snippet": "未来的婺剧，必将是一场充满创意和活力的饕餮盛宴，让观众既能感受到传统文化的底蕴，又能体验到现代艺术的创新。 瞬间变脸和变装的婺剧，已经不仅仅是一 ...",
          "date": "3天前",
          "position": 63
        },
        {
          "title": "八块厝民俗艺术村工艺变装秀艺阁踩街拼创意| 闽南| 文化节| 嘉年华",
          "link": "https://www.epochtimes.com/gb/23/6/7/n14011386.htm",
          "snippet": "八块厝民俗艺术村工艺变装秀艺阁踩街拼创意. 2023桃园闽南文化节系列活动起跑，桃园最大闽南传统嘉年华，艺阁VS踩街领衔登场！（桃园市文化局提供 ...",
          "date": "2023年6月7日",
          "position": 64
        },
        {
          "title": "经典反串摄影工作室",
          "link": "http://www.jd-cd.com/",
          "snippet": "变装视频 · 项目报价 · 联系我们. 经典反串艺术摄影. Crosstalk Art Photography. 查看更 ... 迎合时下喜欢自然、崇尚个性、追求真我的新人们的需求，从独特的角度去诠释艺术 ...",
          "position": 65
        },
        {
          "title": "美女变装日签",
          "link": "https://m.sc.chinaz.com/psd/220510223221240.html",
          "snippet": "美女变装日签. 来源：图夫. 时间：2021-10-06. 类别： 企业画册PSD素材. 大小： 4MB. 标签： 艺术 一中. 简介：. 展开更多 收起更多. 美女变装日签. 夏季3D立体艺术字海报.",
          "position": 66
        },
        {
          "title": "变装与跨性别有什么区别？ - 界面新闻",
          "link": "https://m.jiemian.com/article/2345525.html",
          "snippet": "跨性别”指的是一种个人性别认同和本真的、持久的自我感知。相比之下，“变装”是一种暂时的、有意的性别表演。",
          "date": "2018年7月30日",
          "position": 67
        },
        {
          "title": "变装玩偶图片素材下载-我图网",
          "link": "https://m.ooopic.com/sousuo/27307741/",
          "snippet": "万圣节变身变装聚会舞会 · 卡通 ... 变装派对万圣节艺术字免费下载 · 卡通可爱 ...",
          "position": 68
        },
        {
          "title": "网红都去博物馆拍变装了？谁的古今穿越惊艳到你了？ - 什么值得买",
          "link": "https://post.smzdm.com/p/a7nxw6oo/",
          "snippet": "谁的古今穿越惊艳到你了？ 茶会甜漫记 22-08-01 关注. 最近抖音 ... 以具体入微的写实的雕刻手法再现了滇国社会生活的大事件，不仅具有强烈的艺术感染力，堪称“青铜铸造的 ...",
          "position": 69
        },
        {
          "title": "變裝皇后文化興起藝術與美麗的自我展現 - 小世界周報",
          "link": "http://shuj.shu.edu.tw/blog/2020/04/27/%E8%AE%8A%E8%A3%9D%E7%9A%87%E5%90%8E%E6%96%87%E5%8C%96%E8%88%88%E8%B5%B7-%E8%97%9D%E8%A1%93%E8%88%87%E7%BE%8E%E9%BA%97%E7%9A%84%E8%87%AA%E6%88%91%E5%B1%95%E7%8F%BE/",
          "snippet": "雖然變裝皇后在台灣屬於小眾文化，但是相較於當初剛出現的時候，台灣人對文化的接納度已經提高許多，Supernova參賽者姚穎禔提到：「當初接觸時還會覺得奇怪，但 ...",
          "date": "2020年4月27日",
          "position": 70
        },
        {
          "title": "Art-Ba-Ba 中国当代艺术社区",
          "link": "http://www.art-ba-ba.com/main/view.art?menu=Previous&forumId=8&threadId=198028",
          "snippet": "... 变装皇后的形式对语言和身份认同的现有概念进行批判。 单慧乾的表演作品《今日头条新闻》. 在《星体电威力，变身！》（Astral Bodies Electric, Make ...",
          "date": "2021年1月27日",
          "position": 71
        },
        {
          "title": "反串艺术照变装写真--职业装_人像 - Poco.cn",
          "link": "https://www.poco.cn/works/detail_id20038098",
          "snippet": "小芊平时喜欢的女生就是御姐，所以希望自己变装以后成为那样的女生，果然气质形象都符合御姐呢。预约QQ2032860037.",
          "date": "2018年3月3日",
          "position": 72
        },
        {
          "title": "[环球综艺秀]魔术师苑佳会表演变装魔术 - CCTV节目官网",
          "link": "https://tv.cctv.com/2024/03/10/VIDEoXx8P2GAZ8NoOxoXqGDe240310.shtml",
          "snippet": "我的艺术清单 · 走在回家的路上 · 你好生活 · 舞蹈世界 · 文化十分 · 越战越勇 · 黄金100秒 · 星光大道 · 开门大吉 · 非常6+1 · 我要上春晚 · 向幸福出发.",
          "date": "2024年3月10日",
          "position": 73
        },
        {
          "title": "吉莉安·韦英：戴着面具跳舞 - 艺术与设计",
          "link": "https://www.donnamail.com/article/view/id/71554",
          "snippet": "... 变装与伪装的假面唤起一种对性别、身份与角色的哲学沉思。 文：王一如. 图：纽约古根海姆博物馆. 文章来源：艺术与设计. 版权声明：【除原创作品外，本平台所使用的文章 ...",
          "position": 74
        },
        {
          "title": "北京小燕子变装摄影的个人空间 - BiliBili",
          "link": "https://space.bilibili.com/476536255/",
          "snippet": "... 变装摄影的个人空间，提供北京小燕子变装摄影分享的视频、音频、文章、动态、收藏等内容，关注北京小燕子变装 ... 今天女装子出发拍艺术照啦. 转发; 评论; 赞. + 关注. 北京小 ...",
          "position": 75
        },
        {
          "title": "花瓣网-Rupaul's Drag Race / 鲁保罗变装皇后秀》正式在Logo电视台 ...",
          "link": "http://huaban.com/pins/3744230936/",
          "snippet": "花瓣，陪你做生活的设计师. 登录/ 注册. 淳STUDIO; >; 人文艺术; >; drag · 鲁保罗变装皇后秀超话12年前的今天《. 采集喜欢评论. 查看来源weibo.com.",
          "date": "2021年2月3日",
          "position": 76
        },
        {
          "title": "变装共和国-进度9，10 - 《黑道圣徒：重启版》图文攻略 - 游戏星辰",
          "link": "https://www.2023game.com/gonglue/qitaglu/176333_86.html",
          "snippet": "变装共和国-进度9，10. 作者游戏年轮用户上传 2022-09-14 15:25:24. 本篇小编为大家介绍的是游戏中犯罪事业：变装共和国的流程部分，下面是详细解析部分。 ... 第106页：全摆件艺术品收集：斯梅尔维特 ...",
          "position": 77
        },
        {
          "title": "金刚芭比：走进变装演员的后台 - 纽约时报",
          "link": "https://cn.nytimes.com/culture/20140629/t07hedwig/",
          "snippet": "变装男性的表演正在向美国主流靠近。摄影师马格纳斯·阿里瓦德在几个国家用近五年的时间拍摄画着浓妆、穿着精致服装进行表演的男性，纪录了这种艺术形式 ...",
          "date": "2014年6月29日",
          "position": 78
        },
        {
          "title": "豆瓣9.1，这部年度最过瘾美剧我追定了！ - 南方+",
          "link": "https://static.nfapp.southcn.com/content/201807/05/c1287449.html",
          "snippet": "而这部剧的口碑也再次证实了墨菲的实力，豆瓣评分高达9.1，烂番茄新鲜度也保持在96%。 《姿态》将镜头对准了LGBTQ群体中的变装皇后，故事背景设定在上个世纪 ...",
          "date": "2018年7月5日",
          "position": 79
        },
        {
          "title": "台湾第一人妮妃雅摘美国变装秀后冠破亚洲魔咒 - 1688澳洲新闻网",
          "link": "https://www.1688.com.au/culture/entertainment/2024/04/21/1585581",
          "snippet": "... 变装艺术舞台争奇斗豔，争夺「下一位变装巨星」的头衔。 妮妃雅19日成为美国实境电视节目「鲁保罗变装皇后秀」首位台湾变装皇后。（图取自twitter.com ...",
          "date": "2024年4月21日",
          "position": 80
        },
        {
          "title": "免费变装PNG设计图片大全 - 图精灵",
          "link": "https://616pic.com/tupian/bianzhuang9197.html",
          "snippet": "... 变装图片素材，变装PNG及PSD格式图片， ... 艺术字 · 图标元素 · 边框纹理 · 不规则图形 · PPT元素 · 产品实物 · 卡通手绘 · 数字艺术 · 其它 ...",
          "position": 81
        },
        {
          "title": "公立图书馆「变装皇后故事时间」引发抗议 - UNE 新闻速递",
          "link": "https://www.unecne.com/archives/61700",
          "snippet": "简单来说，「变装皇后故事时间」就是让变装皇后为小孩念故事，透过 ... 艺术之花璀璨盛放. 2024年10月29日16:54. 洛杉矶郡起诉可口可乐和百事可乐.",
          "date": "2018年9月25日",
          "position": 82
        },
        {
          "title": "「做我自己．藝術變裝」導覽派對｜Accupass 活動通",
          "link": "https://www.accupass.com/event/2407230248319032509950",
          "snippet": "當臺灣變裝皇后妮妃雅（Nymphia）贏得國際冠軍時，不僅鼓舞了每個人展現自我的勇氣，同時也給許多年輕人帶來了信心，讓他們能毫無畏懼地做真正的自己。",
          "position": 83
        },
        {
          "title": "旧金山的Rock M. Sakura是美国下一个变装皇后超级明星吗?",
          "link": "https://www.t1mobile.com/movies-tv/is-san-franciscos-rock-m-sakura-americas-next-drag-queen-superstar",
          "snippet": "Rock M. Sakura是七年来第一位参加“鲁保罗变装比赛”的旧金山变装皇后。 ... 这是一种艺术形式，体现了我所热爱的一切。” 一个月后，变装人物Rock M ...",
          "date": "2020年2月26日",
          "position": 84
        },
        {
          "title": "中国变装皇后秀：男演员的另一张精致脸庞",
          "link": "https://m.huanqiu.com/gallery/9CaKrnQhbNE",
          "snippet": "不少男性表演者不仅痴迷歌舞表演，而且还喜欢反串表演。",
          "position": 85
        },
        {
          "title": "5月31至6月3日！泰国及亚洲地区首届大型变装活动将于曼谷开办！",
          "link": "https://thaiwen.com/2024/05/5%E6%9C%8831%E8%87%B36%E6%9C%883%E6%97%A5%EF%BC%81%E6%B3%B0%E5%9B%BD%E5%8F%8A%E4%BA%9A%E6%B4%B2%E5%9C%B0%E5%8C%BA%E9%A6%96%E5%B1%8A%E5%A4%A7%E5%9E%8B%E5%8F%98%E8%A3%85%E6%B4%BB%E5%8A%A8%E5%B0%86/",
          "snippet": "... 变装社区的重要时刻。 曼谷变装节旨在表达对泰国变装艺术家职业生涯的支持，并强化泰国在艺术、文化和旅游方面作为LGBTQIA+之地的地位（相关链接 ...",
          "date": "2024年5月10日",
          "position": 86
        },
        {
          "title": "婺剧三打白骨精是怎么变装的 - 西瓜视频",
          "link": "https://m.ixigua.com/zhuanti/7432014495586945058",
          "snippet": "婺剧三打白骨精是怎么变装的. 变脸又变衣服，婺剧《三打白骨精》连续变装太惊艳 ... 浙江婺剧艺术研究院三打白骨精第一二场杭州萧山剧院演出#婺剧. 5次播放 ...",
          "date": "4天前",
          "position": 87
        },
        {
          "title": "藝術街Halloween 變裝Follow me！  活動圓滿成功",
          "link": "https://www.gogoartstreet.com/2021halloweenend/",
          "snippet": "首先感謝大家熱情的參與，讓活動圓滿達成！小編代表主委、商圈店家夥伴和工作人員向你們獻上熱烈掌聲。南北各路、還有香港跟許多外籍朋友們的參與！",
          "position": 88
        },
        {
          "title": "专栏| 财经时时听: 中国资金外逃创新高艺术品、比特币成新招",
          "link": "https://www.rfa.org/mandarin/zhuanlan/jingmaorediansaomiao/econ-china-capital-flee-via-arts-bitcoin-11012024102103.html",
          "snippet": "专栏| 财经时时听: 中国资金外逃创新高艺术品、比特币成新招. 撰稿 ... 变装”声援. 热门文章. 财经时时听.",
          "date": "2天前",
          "position": 89
        },
        {
          "title": "95后小伙“反串变装”涨粉300W，JK制服引网友炸锅：现在的博主",
          "link": "https://h5.ifeng.com/c/vivoArticle/v002wZpl9xGXs9cyv-_yienwFPRu0o8P-_edL7T-_CbgC6--Uak__?isNews=1&showComments=0",
          "snippet": "那今天，就和象君一起，感受快乐！ 内容图片. 艺术难道就不值得尊重吗. 菜园一只猪，本名莫贵凌，广西小伙 ...",
          "date": "2022年11月28日",
          "position": 90
        },
        {
          "title": "经典摄影价目总表- 影楼动态",
          "link": "http://www.jdcdsy.com/bencandy.php?fid=4&id=666",
          "snippet": "3、穿经典的整套衣服鞋子外出，每次收费800元。 二、外景变装摄影及变装外出活动费用. 1、艺术外景摄影：. 化妆一次、服装三套自选、发型3个造型、30张 ...",
          "date": "2021年5月9日",
          "position": 91
        },
        {
          "title": "今夏17个不可错过的LGBTQ主题展览 - artnet 新闻",
          "link": "https://www.artnetnews.cn/people/lgbtq-zhanlan-5707",
          "snippet": "为了在这个夏天为LGBTQIA群体或变装艺术家们庆祝节日，敬请浏览这份遍布 ... 艾未未又一新作，推特发帖也能变成艺术？ Proceed. 联系我们; 广告 ...",
          "date": "2015年6月29日",
          "position": 92
        },
        {
          "title": "重新回味「台北國際變裝藝術節」的精彩時刻，跟著灣島皇后一起 ...",
          "link": "https://www.youtube.com/watch?v=hbyZLEKr7y8",
          "snippet": "大家還記得「台北國際變裝藝術節」的那些精彩片段嗎？這集讓跩姬、Bagel、漢娜一同帶著大家回 ...\n时长： 22:21\n发布时间： 2024年6月3日",
          "date": "2024年6月3日",
          "position": 93
        },
        {
          "title": "變裝的藝術- 精選書展 - 女書店",
          "link": "https://www.fembooks.com.tw/tc/projects_in.aspx?id=5918&chk=fff30d39-fd60-4a5d-b518-18ceb4abb321&mid=44&cid=1014",
          "snippet": "變裝，一門戲耍性別的藝術，掙脫了怎樣才像男人、才像女人、才像人的枷鎖。在《魯保羅變裝秀》將變裝文化推向全球的焦點之前，變裝已存在數千年的歷史：變裝存在於西方的古希臘 ...",
          "currency": "$",
          "price": 900,
          "position": 94
        },
        {
          "title": "变装部落 - 搜狗百科",
          "link": "https://baike.sogou.com/v165406983.htm",
          "snippet": "变装部落是沪上（上海）一家具有非常特色的摄影品牌，隶属于明仪变装旗下，涵盖cosplay变装、行为艺术、反串摄影艺术，伪娘cosplay等. 反馈有用 ...",
          "position": 95
        },
        {
          "title": "展评丨李琳琳：阿拉斯加的鳕鱼 - 中央美术学院",
          "link": "https://www.cafa.com.cn/mobile/cn/opinions/reviews/details/8332615",
          "snippet": "这个艺术装置是实现当代社会技术发展既奇妙又令人担忧的方面的渠道。 wps_doc_21.jpeg 《AI 绿色通道》局部，综合材料，尺寸可变，2024“阿拉斯加的鳕鱼”展览 ...",
          "date": "5天前",
          "position": 96
        },
        {
          "title": "关于变装皇后，你想知道的一切让他们来回答 - 时尚- 搜狐",
          "link": "https://fashion.sohu.com/20170320/n483966449.shtml",
          "snippet": "虽然百分之七十的纽约人都知道变装表演是什么，但SLURP秀开始的头几年，来看表演的多是同志，变性人，或艺术类的自由职业者。慢慢的，来的人多了起来，几乎各行 ...",
          "date": "2017年3月20日",
          "position": 97
        },
        {
          "title": "历史上的潮人：变装的莎士比亚和伊丽莎白 - 雅昌艺术网",
          "link": "https://amma.artron.net/observation_shownews.php?newid=445289",
          "snippet": "作家和历史学家博士苏珊娜·利普斯科姆和一个数字艺术家团队花了3个月来更新一系列的经典人像。这些作品表达了对一些百年之前的著名人物在今天会变成 ...",
          "date": "2013年5月4日",
          "position": 98
        },
        {
          "title": "郭松民：逛“艺术区”有感 - 红歌会",
          "link": "https://m.szhgh.com/Article/opinion/xuezhe/2024-11-03/363168.html",
          "snippet": "把工厂的遗址变为艺术创意园区，是可以的。 但作为后人的我们，应该对 ... 装睡的恶人们？ 特朗普：我们几乎轰炸了整个中东，却一无所获 · 老田 ...",
          "date": "22小时前",
          "position": 99
        },
        {
          "title": "[我要上春晚]魔术《变装秀》 表演：李霞 - CCTV节目官网",
          "link": "http://tv.cctv.com/2013/12/13/VIDE1386943762407583.shtml",
          "snippet": "更新时间：2013-12-13 22:06. 来源：央视网 · 来源：央视网 · 视频简介：魔术《变装秀 ...\n发布时间： 2013年12月13日",
          "date": "2013年12月13日",
          "position": 100
        }
      ],
      "credits": 2
    },
    {
      "searchParameters": {
        "q": "变装艺术",
        "gl": "cn",
        "hl": "zh-cn",
        "type": "search",
        "num": 100,
        "page": 3,
        "engine": "google"
      },
      "organic": [
        {
          "title": "1分钟资讯｜@同学们调整了！国家奖助学金政策提标扩面 - 金华新闻网",
          "link": "https://www.jhnews.com.cn/xw/1712349",
          "snippet": "... 艺术研究院、金华市戏剧家协会承办的“法兴婺剧婺韵赋美”金华市婺剧 ... 这两天，婺剧《三打白骨精》中白骨精变脸变装的视频持续在微信视频号、抖 ...",
          "date": "5天前",
          "position": 1
        },
        {
          "title": "变装文化(Drag)是如何兴起的?为什么美国人都爱看变装秀 ... - YouTube",
          "link": "https://www.youtube.com/watch?v=62QURtJDeVo",
          "snippet": "你看过《鲁保罗变装皇后秀》吗？这个曾荣获艾美奖，历经10多年久盛不衰的节目向人们展现变装 ...\n时长： 6:09\n发布时间： 2021年3月4日",
          "date": "2021年3月4日",
          "position": 2
        },
        {
          "title": "最美写真变装写真艺术照",
          "link": "https://www.xz885.com/p/1036243.html",
          "snippet": "最美写真变装写真艺术照”手机软件APP，致力于将您的美丽瞬间定格，通过强大的变装和艺术照功能，让您轻松塑造出独一无二的个人形象。",
          "date": "2024年9月23日",
          "position": 3
        },
        {
          "title": "三星电视携手京东推出艺术电视焕新活动，探索现代家居的艺术之美",
          "link": "https://www.donews.com/news/detail/4/4592918.html",
          "snippet": "... 艺术电视相关产品，可享政府补贴至高省2000元等多项优惠，部分三星电视可享送装一体服务，让所有家庭都能享受艺术与科技邂逅的惊喜。 The Frame打造 ...",
          "date": "2天前",
          "position": 4
        },
        {
          "title": "中国最适合看展的城市，一票难求-虎嗅网",
          "link": "https://m.huxiu.com/article/3632850.html",
          "snippet": "女性艺术家的机会变多了吗？艺术应当由谁来定义？在当下这个“景观时代 ... 新周刊：格雷森·佩里在这本书里还说：“艺术已经成为一个装满着令人难以置信的想法的大 ...",
          "date": "5天前",
          "position": 5
        },
        {
          "title": "邀请观众共同探索800年来的未解之谜闽剧《幻戏图》将于11月1日上演",
          "link": "https://m.163.com/news/article/JFORQ7NK0530QRMB.html?clickfrom=subscribe&spss=adap_pc",
          "snippet": "... ：人民网人民网福州10月30日电（记者张子剑）11月1日19：30，古装闽剧《幻戏图》将在福州市海峡文化艺术 ... “变装界天花板”，非遗婺剧不止有变脸还有变 · 川剧鬼 ...",
          "date": "5天前",
          "position": 6
        },
        {
          "title": "习近平与文艺工作者的故事｜梨园春秋薪火传 - 科技日报",
          "link": "https://www.stdaily.com/web/2024-11/03/content_252325.html",
          "snippet": "京剧表演艺术家尚长荣出生在戏曲世家，长期投身京剧艺术事业。他曾三次 ... 向“新”谋变借“智”攀高——山东部分工业企业走访见闻 · 封面新闻 · 封面新闻 ...",
          "date": "24小时前",
          "position": 7
        },
        {
          "title": "新华网：如约绽放！第41届武汉金秋菊展绚丽开幕持续一月",
          "link": "https://www.wuhan.gov.cn/sy/kwh/202411/t20241103_2479290.shtml",
          "snippet": "沙湖公园展区展出百余幅出以花为主题的儿童＋AI共创画作，推出由艺术 ... 变装、菊花科普等创意活动。 见习编辑：张子菲. 扫一扫在手机上查看当前 ...",
          "date": "19小时前",
          "position": 8
        },
        {
          "title": "高甲戏《冯谖与孟尝君》精彩亮相第九届福建艺术节 - 地方频道",
          "link": "https://difang.gmw.cn/2024-10/30/content_37645575.htm",
          "snippet": "汽车后市场变了，你感觉到了吗？ 汽车后市场在规范化的基础上，借助智能 ... AEP100发动机配装全球最大无人运输机. 由中国航发完全自主研制、具备 ...",
          "date": "5天前",
          "position": 9
        },
        {
          "title": "万圣节上海风声鹤唳逮捕、清查行为随处可见-中国瞭望 - 万维读者网",
          "link": "https://m.creaders.net/news/page/1289731",
          "snippet": "... 艺术界，大部分朋友都经营艺术馆、咖啡店、书店或 ... 图像来源，Getty Images 万圣节前的最后一个周末，上海锦江乐园官方帐号表示“不接待变装游客”。",
          "date": "4天前",
          "position": 10
        },
        {
          "title": "万圣节之夜嘲讽中共当局的变装者现身洛杉矶 - 禁闻网",
          "link": "https://www.bannedbook.org/bnews/headline/20241102/2110241.html",
          "snippet": "在当晚的洛杉矶圣塔莫妮卡大道街头，往来着身穿各色万圣节街头变装服饰的大批民众，其中有数十位来自中国的民运人士的身影。这些民运人士装扮成习近平、 ...",
          "date": "2天前",
          "position": 11
        },
        {
          "title": "汪黎明：用照片搭起一座淳安蝶变“档案馆” - 千岛湖新闻网",
          "link": "https://www.qdhnews.com.cn/news/content/2024-10/31/content_9740497.html",
          "snippet": "汪黎明，中国摄影家协会会员、杭州市艺术摄影学会主席团成员、淳安县摄协艺术 ... 当年，4张拼接而成的照片能装下排岭镇的全部，今天却装不下了。如今的 ...",
          "date": "4天前",
          "position": 12
        },
        {
          "title": "变装皇后 - 反潮流俱乐部",
          "link": "https://fanchaoliuclub.fireside.fm/dragqueen",
          "snippet": "About this Episode. 「变装皇后」这个词来自英文“Drag Queen”，特指那些通过穿女性服装来扮演女性的男性。虽然这是一个小众的圈子， 但是它的文化却有着悠久的历史. 本 ...",
          "position": 13
        },
        {
          "title": "最娇艳妩媚大学校长竟是变装癖艺术家| 新生活报",
          "link": "https://www.ilifepost.com/20201130/%E6%9C%80%E5%A8%87%E8%89%B3%E5%A6%A9%E5%AA%9A%E5%A4%A7%E5%AD%A6%E6%A0%A1%E9%95%BF%E7%AB%9F%E6%98%AF%E5%8F%98%E8%A3%85%E7%99%96%E8%89%BA%E6%9C%AF%E5%AE%B6",
          "snippet": "Grayson Perry是伦敦艺术大学新校长，人们最广为人知的是他的陶瓷花瓶和易装癖。当Perry身着女装时，有时候优雅时髦、天真烂漫、天马行空。",
          "date": "2020年11月29日",
          "position": 14
        },
        {
          "title": "男童顶塔骨训练，摇身一变成为大元帅，潇洒威风凛凛福建游神",
          "link": "https://www.youtube.com/watch?v=EQI5gmgv9Ug",
          "snippet": "民俗艺术游神活动，雄伟霸气大将军变装，男童顶塔骨训练，摇身一变成为大元帅，潇洒威风 ...\n时长： 0:09\n发布时间： 2024年10月9日",
          "date": "2024年10月9日",
          "position": 15
        },
        {
          "title": "什么厨电品牌，能走进时装周？ - 中国新闻周刊网",
          "link": "http://www.inewsweek.cn/yysbg/2024-11-01/23537.shtml",
          "snippet": "... 装》主编、时尚摄影师、制片人余凌远在S/S 2025深圳时装周现场. 同时，本 ... 大面积净洁的白，上面跳动着灵动的绿，华帝“天生干净”艺术展的入口设计就非常抓人 ...",
          "date": "3天前",
          "position": 16
        },
        {
          "title": "首都乡村展现振兴新气象_中国经济网",
          "link": "http://tuopin.ce.cn/news/202410/31/t20241031_39187813.shtml",
          "snippet": "... 变。近日，记者跟随“高质量发展调研行 ... 平谷区携手清华大学美术学院等京津冀8所艺术院校共同打造“南山艺术季”活动，青年学子在村里进行艺术创作。",
          "date": "4天前",
          "position": 17
        },
        {
          "title": "上海严控万圣节在英中国青年大使馆外“变装”声援(图)",
          "link": "https://www.secretchina.com/news/gb/2024/11/03/1072285.html",
          "snippet": "在中国官方严控之下，今年中国年轻人难以再趁万圣节进行政治抗议。而在伦敦中国大使馆外，有中国异见者上演“一人变装秀”，希望声援国内的同龄人。",
          "date": "16小时前",
          "position": 18
        },
        {
          "title": "勤益科大「永續藝術變裝伸展台」亮相國美館學生化身藝術作品展現 ...",
          "link": "https://lifenews.com.tw/222190/",
          "snippet": "國立勤益科技大學「自然永續與藝術社會實踐」課程的學生們在洪晧倫老師帶領下，於國立臺灣美術館舉辦「入畫—永續藝術變裝伸展台」活動，透過藝術與環保結合 ...",
          "date": "1天前",
          "position": 19
        },
        {
          "title": "万圣节上海风声鹤唳逮捕、清查行为随处可见 - 万维读者网（电脑版）",
          "link": "https://news.creaders.net/china/2024/10/30/2791033.html",
          "snippet": "... 艺术界，大部分朋友都经营艺术馆、咖啡店、书店或 ... 图像来源，Getty Images 万圣节前的最后一个周末，上海锦江乐园官方帐号表示“不接待变装游客”。",
          "date": "4天前",
          "position": 20
        },
        {
          "title": "上海地标被严控学生被要求不参加“非官方活动” - 倍可亲",
          "link": "https://www.backchina.com/news/2024/10/29/941206.html",
          "snippet": "图像加注文字，2023年万圣节，各种颇具讽刺意味的变装秀在上海未完全遭到禁止。 ... 先前居住在上海、目前已移居北京的艺术家夏先生对BBC表示，自己身处艺术 ...",
          "date": "6天前",
          "position": 21
        },
        {
          "title": "风灾清太慢，白昼之夜地板泥泞害跌倒，台北市文化局道歉了",
          "link": "https://m.stnn.cc/c/2024-11-03/3931997.shtml",
          "snippet": "文化局说，今年白昼之夜集结61组岛内外艺术团队参与，带来超过百场 ... 变装气氛，加上送机票的号召，每隔1小时总计5次的游行队伍动辄数10公尺 ...",
          "date": "19小时前",
          "position": 22
        },
        {
          "title": "新职业涌现折射中国社会发展新变化 - 科技日报",
          "link": "https://www.stdaily.com/web/gdxw/2024-10/30/content_250598.html",
          "snippet": "甘肃省博物馆艺术生活馆的 ... 今年“上榜”的19个新职业中，半数以上与新质生产力密切相关，其中包括38岁的张帆正在从事的智能网联汽车装调运维员。",
          "date": "5天前",
          "position": 23
        },
        {
          "title": "“阅读中华国粹”之【传统戏曲】【传统音乐】任选！全彩印制 - 淘书团",
          "link": "https://t.bookschina.com/tuan/24946",
          "snippet": "【传统戏曲】4册，荟萃豫剧、吕剧、黄梅戏、苏州评弹四个剧种，让读者深切领略中国戏曲艺术的独特魅力。 ... 变音五、变脸六、变草帽圈七、耍牙八、爬竿九、夹鸡蛋簸米 ...",
          "position": 24
        },
        {
          "title": "“冬歇”变“冬忙”！ 沈阳铁西区全力推动项目建设“三量齐升” - 辽宁新闻网",
          "link": "https://www.ln.chinanews.com.cn/news/2024/1028/347289.html",
          "snippet": "... 装智慧园升级等一批“智改数转”项目；推动传统产业高端化、智能化、绿色化 ... 2024沈阳艺术季·青年戏剧 ...",
          "date": "7天前",
          "position": 25
        },
        {
          "title": "國際變裝藝術節妮妃雅奪冠後首公開演出 - YouTube",
          "link": "https://www.youtube.com/watch?v=CbbM0wzzUV4",
          "snippet": "魯保羅變裝皇后秀#妮妃雅#台北國際變裝藝術節知名美國實境節目「魯保羅變裝皇后秀」最新 ...\n时长： 1:57\n发布时间： 2024年5月25日",
          "date": "2024年5月25日",
          "position": 26
        },
        {
          "title": "2024「白晝之夜」登場！台北大安森林公園變身藝術天堂，活動主題",
          "link": "https://www.vogue.com.tw/article/%E7%99%BD%E6%99%9D%E4%B9%8B%E5%A4%9C-nuit-blanche-2024",
          "snippet": "快跟著Vogue，一起來看看這次的2024臺北白晝之夜有什麼精彩亮點吧！ 更有趣的是，廖小子這次還設計了三款充滿巧思的變裝面具，並有空白版本 ...",
          "date": "3天前",
          "position": 27
        },
        {
          "title": "菜筐变微景花园首都花园城市建设的N种创意 - 中国青年网",
          "link": "https://news.youth.cn/sh/202411/t20241102_15621236.htm",
          "snippet": "一个菜筐除了装菜还可以装什么？ 在北京市东城区景山街道，一个菜筐将在 ... 艺术雕塑作品《超时空的对话》《玫瑰色果浆》《踢毽子》点缀其间 ...",
          "date": "2天前",
          "position": 28
        },
        {
          "title": "在“中国式现代化”命题中，上海何以成为全球“人民城市”之样板？",
          "link": "https://www.jfdaily.com/news/detail?id=808837",
          "snippet": "走出展示馆，在江边走上一段就能看到，昔日的“工业锈带”已蝶变为“生活秀带”“发展绣带”——工厂仓库改建成了博物馆、艺术 ... 装电梯。蒙西小区急老人们之 ...",
          "date": "3天前",
          "position": 29
        },
        {
          "title": "金黃色亮片裝登場！ 妮妃雅現身變裝藝術節｜#鏡新聞 - YouTube",
          "link": "https://www.youtube.com/watch?v=XqFN4uMRKvk",
          "snippet": "一年一度的台北國際變裝藝術節今天（5/25）登場，台灣之光妮妃雅4月在美國變裝皇后節目奪得冠 ...\n时长： 1:54\n发布时间： 2024年5月25日",
          "date": "2024年5月25日",
          "position": 30
        },
        {
          "title": "在澳洲漂泊的芭蕾王子颠覆古典芭蕾竟变装为”芭蕾小丑“！郭富城竟要 ...",
          "link": "https://www.youtube.com/watch?v=4hRzQcTs_mk",
          "snippet": "... 艺术、弘扬中国舞蹈文化。 ○HOT热门综艺中国好声音2018 ：http://bit.ly ...\n时长： 4:46\n发布时间： 2018年8月10日",
          "date": "2018年8月10日",
          "position": 31
        },
        {
          "title": "生活画廊YH2 ART 顺德艺术家，艺人- 《中西合一》为何称为中西合 ...",
          "link": "https://m.facebook.com/2068293653432953/",
          "snippet": "《中西合一》为何称为中西合一,中代表风水学那什么是风水学呢,运命这两字就是风水的根本,改变的意思,西代表新潮给人了解说《不能过时的意思》终的来说改变命运的方法是 ...",
          "position": 32
        },
        {
          "title": "20140118 我要上春晚《变装秀》 表演：李霞- YouTube",
          "link": "https://www.youtube.com/watch?v=aBwS2HhnHws",
          "snippet": "20140118 我要上春晚《变装秀》 表演：李霞 ... 2:39. Go to channel · 周深、克莱德曼 ...\n时长： 2:56\n发布时间： 2014年2月20日",
          "date": "2014年2月20日",
          "position": 33
        },
        {
          "title": "变装舞会文化的历史与意义 - Google Play",
          "link": "https://play.google.com/store/apps/editorial?id=mc_apps_editorial_pride_2023_ballroom_culture_fcp&hl=zh_CN",
          "snippet": "在20 世纪20 年代的纽约，LGBTQ+ 群体饱受歧视。为了对抗这种偏见，变装舞会文化应运而生。黑人和拉丁裔酷儿青年开始搭建互助网络并创造自己的家庭结构，以便通过演出获得 ...",
          "position": 34
        },
        {
          "title": "「變裝皇后」是表演藝術！ 他性感尬舞比女生還辣 - YouTube",
          "link": "https://www.youtube.com/watch?v=u2zqIllqKsI",
          "snippet": "變裝皇后#表演藝術#性感感謝授權：@nene0711 原始影片：https://youtu.be ...\n时长： 7:20\n发布时间： 2022年1月1日",
          "date": "2022年1月1日",
          "position": 35
        },
        {
          "title": "國際變裝藝術節妮妃雅奪冠後首公開演出【最新快訊】 - YouTube",
          "link": "https://www.youtube.com/watch?v=g_Gk4ef4PgM",
          "snippet": "知名美國實境節目「魯保羅變裝皇后秀」最新一季，由來自台灣的妮妃雅，奪下冠軍，25日他參加活動 ...\n时长： 0:54\n发布时间： 2024年5月25日",
          "date": "2024年5月25日",
          "position": 36
        },
        {
          "title": "『西式變裝秀』 閃電變裝快速變裝男女變裝變裝表演魔術表演兆群 ...",
          "link": "https://www.youtube.com/watch?v=3bhDoi0QScU",
          "snippet": "兆群表演團隊- 魔術表演、泡泡表演、歡樂小丑- 兆群藝術娛樂有限公司•10K ... 2024全新“快速 ...\n时长： 3:11\n发布时间： 2019年6月3日",
          "date": "2019年6月3日",
          "position": 37
        },
        {
          "title": "《鲁保罗变装皇后秀》 | Netflix 官方网站",
          "link": "https://www.netflix.com/sg-zh/title/70187741",
          "snippet": "鲁保罗·查尔斯米歇尔·维塞奇罗斯·马修斯卡森·克雷斯利桑提诺·赖斯梅尔·金斯伯格比利·B. 访问Tudum.com，了解Netflix 电影和电视节目的幕后花絮，查看即将上线的内容，观看 ...",
          "position": 38
        },
        {
          "title": "变装- 杨霞云- 三打白骨精（婺剧） - YouTube",
          "link": "https://www.youtube.com/watch?v=kUHYgXSiUeQ",
          "snippet": "Comments · FULL丨4K婺剧《三打白骨精》， #杨霞云#楼胜文戏武做场场爆满火出圈，白 ...\n时长： 0:24\n发布时间： 2024年10月21日",
          "date": "2024年10月21日",
          "position": 39
        },
        {
          "title": "打破亚洲魔咒！妮妃雅《鲁保罗》摘冠首位台湾变装皇后 - 新加坡",
          "link": "https://nextapple.com.sg/entertainment/20240420/319AC72EF55C4F16099A5D466F01618B",
          "snippet": "2009年开播的《鲁保罗变装皇后秀》获多座艾美奖肯定，是全球最知名的变装艺术舞台之一，10多年来只有7位亚洲变装皇后闯进4强。",
          "date": "2024年4月20日",
          "position": 40
        },
        {
          "title": "『快速變裝秀』變裝秀閃電變裝魔術秀兆群表演團隊活動 ... - YouTube",
          "link": "https://www.youtube.com/watch?v=06LlSKYFYd4",
          "snippet": "全新❗️ 2021全新官方網站 ❗️ 『 兆群藝術娛樂DAREN MAGIC 』 用心、專業、創意、歡樂 ...\n时长： 3:41\n发布时间： 2021年10月24日",
          "date": "2021年10月24日",
          "position": 41
        },
        {
          "title": "艺术就是装逼#艺术#陈丹青#艺术家- YouTube",
          "link": "https://www.youtube.com/watch?v=fV7HT3E8DIY",
          "snippet": "Share your videos with friends, family, and the world.\n时长： 0:20\n发布时间： 2023年3月6日",
          "date": "2023年3月6日",
          "position": 42
        },
        {
          "title": "『快速變裝』閃電變裝秀變裝魔術秀婚禮節目兆群表演團隊活動邀約 ...",
          "link": "https://www.youtube.com/watch?v=H8SOKCXWrBg",
          "snippet": "全新❗️ 2021全新官方網站 ❗️ 『 兆群藝術娛樂DAREN MAGIC 』 用心、專業、創意、歡樂 ...\n时长： 4:26\n发布时间： 2022年5月18日",
          "date": "2022年5月18日",
          "position": 43
        },
        {
          "title": "民俗传统艺术游神活动，两个可爱的小男孩大摇大摆变装 - YouTube",
          "link": "https://www.youtube.com/watch?v=sI9d1x3GuW0",
          "snippet": "民俗传统艺术游神活动，两个可爱的小男孩大摇大摆变装，调皮小太子巡游，活泼小马夫开路 ...\n时长： 0:11\n发布时间： 2024年10月12日",
          "date": "2024年10月12日",
          "position": 44
        },
        {
          "title": "小燕子变装摄影馆- 变装,伪娘,女装,CD,反串男扮女装女装大佬",
          "link": "https://www.xyzsyg.com/",
          "snippet": "Hi，各位亲们： (\\ ￣ ▽￣)o╭╯ 人海之中相遇，真是一种妙不可言的缘分呢。请问，亲是懵懂的变装新人，还是久经历练的女装大佬呢？嘻嘻，其实都不重要的啦，因为无论亲属于哪一种， ...",
          "position": 45
        },
        {
          "title": "《锦绣安宁》剧组做客好六街开启“惊喜变装夜” - 读特",
          "link": "https://m.dutenews.com/n/article/8486425",
          "snippet": "本周好六街开启“惊喜变装夜”，《锦绣安宁》主演张晚意、任敏与苏醒、刘宇宁、付航、张颜齐、石凯、李雪琴、丁程鑫、杨迪以两人一组的形式开启每轮游戏，而在每轮游戏中 ...",
          "position": 46
        },
        {
          "title": "这伪装立牌真是“战争艺术”【及嘉测评#210】POP COSTUME 1/12 ...",
          "link": "https://www.youtube.com/watch?v=GiqBJslDjgs",
          "snippet": "这伪装立牌真是“战争艺术”【及嘉测评#210】POP COSTUME 1/12 大头兵第八弹战争艺术 ...\n时长： 4:55\n发布时间： 4天前",
          "date": "4天前",
          "position": 47
        }
      ],
      "credits": 2
    }
  ]
}