{
  "query": "性别肯定治疗",
  "language": "zh-cn",
  "geo_location": "cn",
  "totalPages": 3,
  "endpoint": "/search",
  "date": "2024-11-04T00:36:21.527981",
  "results": [
    {
      "searchParameters": {
        "q": "性别肯定治疗",
        "gl": "cn",
        "hl": "zh-cn",
        "type": "search",
        "num": 100,
        "page": 1,
        "engine": "google"
      },
      "organic": [
        {
          "title": "性别肯定激素治疗- 维基百科，自由的百科全书",
          "link": "https://zh.wikipedia.org/zh-cn/%E6%80%A7%E5%88%AB%E8%82%AF%E5%AE%9A%E6%BF%80%E7%B4%A0%E6%B2%BB%E7%96%97",
          "snippet": "是一种提供给跨性别者或非性别二元者的激素替代疗法（HRT），借由摄入性激素或相关激素制剂，让跨性别者或非二元性别者的第二性征能更贴近他们的性别认同。 一般而言，这 ...",
          "position": 1
        },
        {
          "title": "女性化激素治疗- 妙佑医疗国际 - Mayo Clinic",
          "link": "https://www.mayoclinic.org/zh-hans/tests-procedures/feminizing-hormone-therapy/about/pac-20385096",
          "snippet": "女性化激素治疗需要服用药物，以阻断睾酮激素的作用。此外，这类治疗还需要服用雌激素。雌激素可减少身体产生的睾酮量，还可诱发女性第二性征。",
          "date": "2024年7月12日",
          "position": 2
        },
        {
          "title": "性别肯定（跨性别）嗓音治疗和手术- 妙佑医疗国际 - Mayo Clinic",
          "link": "https://www.mayoclinic.org/zh-hans/tests-procedures/transgender-voice-therapy-and-surgery/about/pac-20470545",
          "snippet": "性别肯定嗓音治疗和手术可帮助跨性别者和多元性别者调整嗓音，使其沟通方式符合自己的性别认同。这类治疗也称为跨性别者嗓音治疗和手术，或者称为嗓音 ...",
          "date": "2024年5月14日",
          "position": 3
        },
        {
          "title": "女性化激素疗法- 维基百科，自由的百科全书",
          "link": "https://zh.wikipedia.org/zh-cn/%E5%A5%B3%E6%80%A7%E5%8C%96%E6%BF%80%E7%B4%A0%E7%96%97%E6%B3%95",
          "snippet": "女性化激素疗法（英语：feminizing hormone therapy）是一种性别肯定激素治疗（GAHT）及性别重置疗法，旨在将跨性别者的第二性征从男或中性转变为女性气质。用于治疗跨性别 ...",
          "position": 4
        },
        {
          "title": "跨性别激素治疗_百度百科",
          "link": "https://baike.baidu.com/item/%E8%B7%A8%E6%80%A7%E5%88%AB%E6%BF%80%E7%B4%A0%E6%B2%BB%E7%96%97/54212022",
          "snippet": "跨性别激素治疗（Transgender Hormone Therapy）是肯定跨性别者性别认同的一种卫生保健服务，透过外源性内分泌制剂的投药，使跨性别者身体的第二性征与其性别认同相符， ...",
          "position": 5
        },
        {
          "title": "Nature：雄激素治疗后的跨性别男性，免疫系统被重塑 - 生物谷",
          "link": "https://news.bioon.com/article/b6b884204611.html",
          "snippet": "该研究表明，跨性别男性（出生性别女性，但自我认同为男性）在性别肯定激素治疗（睾酮治疗）期间，免疫反应会变得更像顺性别男性（出生性别男性，且自我认同为男性） ...",
          "date": "2024年9月6日",
          "position": 6
        },
        {
          "title": "[PDF] 2021全国跨性别健康调研报告",
          "link": "https://cnlgbtdata.com/files/uploads/2023/01/2021%E5%85%A8%E5%9B%BD%E8%B7%A8%E6%80%A7%E5%88%AB%E5%81%A5%E5%BA%B7%E8%B0%83%E7%A0%94%E6%8A%A5%E5%91%8A.pdf",
          "snippet": "性别肯定医疗（Gender Affirmation Healthcare）. 指通过医学手段使跨性别者的性别特征与其性别认同. 相符的过程，包括激素替代治疗和性别肯定手术等。 跨性别（Transgender）.",
          "position": 7
        },
        {
          "title": "内分泌疾病的管理：变性人的最佳女性化激素治疗。 - X-MOL",
          "link": "https://www.x-mol.com/paper/1417179886993297408/t?recommendPaper=1235636840413511680",
          "snippet": "性别不安可能与抑郁和生活质量低下有关，在大多数情况下，这种情况在性别肯定激素治疗(GAHT) 期间会有所改善。针对跨性别女性或非二元性别人群的女性 ...",
          "date": "2021年6月28日",
          "position": 8
        },
        {
          "title": "联合国专家称，“矫正治疗”可构成酷刑，应予禁止 - ohchr",
          "link": "https://www.ohchr.org/zh/stories/2020/07/conversion-therapy-can-amount-torture-and-should-be-banned-says-un-expert",
          "snippet": "“矫正治疗”是一种干预治疗，宣称能够改变人的性取向或性别认同，因而声称其目的是将人从男、女同性恋或双性恋转变为异性恋，从跨性别或多元性别转变为顺性别— ...",
          "date": "2020年7月13日",
          "position": 9
        },
        {
          "title": "Nature重磅：睾酮治疗使“女变男”跨性别男性的免疫反应趋向男性",
          "link": "https://news.qq.com/rain/a/20240908A04EP500",
          "snippet": "研究性别肯定激素治疗（GAHT）对免疫反应的作用有助于揭示性激素对免疫系统的影响，并提供机会来改善对这一历来被排斥、得不到充分服务的患者群体的照护。",
          "date": "2024年9月8日",
          "position": 10
        },
        {
          "title": "跨性别女性的评估和管理- UpToDate",
          "link": "https://www.uptodate.com/contents/zh-Hans/transgender-women-evaluation-and-management/print",
          "snippet": "发生率–现有数据表明0.6%的成人为跨性别者[3-5]。跨性别的发生率取决于定义。例如，一些研究仅纳入接受了激素治疗、性别确认手术或证实跨性别(有对应 ...",
          "date": "2023年10月12日",
          "position": 11
        },
        {
          "title": "荷尔蒙替代疗法",
          "link": "https://www.kamolhospital.com/zh/service/1117/hormone-replacement-therapy",
          "snippet": "... 疗法对于跨性别和性别不一致的人士来说是一项重要的治疗，尤其是对于那些对自身性别 ... 性别确认手术前的准备 · 女性阴道重建. 男变女手术. 脸部女性化手术 · MTF 乳房增大 ...",
          "position": 12
        },
        {
          "title": "Nature：雄激素治疗后的跨性别男性，免疫系统被重塑 - 澎湃新闻",
          "link": "https://m.thepaper.cn/newsDetail_forward_28638946",
          "snippet": "在女跨男性别肯定睾酮治疗过程中，人们对激素水平发生明显变化产生的免疫结果也所知甚少。研究性别肯定激素治疗（Gender-affirming hormone therapy，GAHT）对 ...",
          "date": "2024年9月5日",
          "position": 13
        },
        {
          "title": "性别肯定激素治疗与跨性别和非二元青年的抑郁、自杀念头和企图 ...",
          "link": "https://www.x-mol.com/paper/1470852022926876672/t?recommendPaper=1244797757950836736",
          "snippet": "没有大规模研究检查接受性别肯定激素治疗(GAHT) 的跨性别和非二元青年的心理健康。本研究的目的是在大量跨性别和非二元青年样本中检查获得GAHT 与抑郁 ...",
          "date": "2021年12月14日",
          "position": 14
        },
        {
          "title": "性别确认手术| Bangkok Hospital",
          "link": "https://www.bangkokhospital.com/zh/content/sex-affirmation-surgery",
          "snippet": "这种手术是在子宫和输卵管切除术完成后，永久性地停止阴道的功能。 身体将不再分泌女性荷尔蒙，没有排卵，没有月经，将来也不会有受孕的机会，这一切都符合患者成为变性 ...",
          "position": 15
        },
        {
          "title": "性别不一致与性别焦虑- MSD诊疗手册专业版",
          "link": "https://www.msdmanuals.cn/professional/psychiatric-disorders/gender-incongruence-and-gender-dysphoria/gender-incongruence-and-gender-dysphoria",
          "snippet": "对于大多数患有性别不安的人来说，寻求医疗帮助的主要目的不是获得心理健康治疗，而是获得激素治疗和/或性别确认手术（以前称为性别重置或生殖器手术）形式的性别确认治疗手术， ...",
          "position": 16
        },
        {
          "title": "UCSF指南 - 跨性别在线·文档库",
          "link": "https://docs.transonline.org.cn/ucsf/",
          "snippet": "性别肯定护理与WHI的研究结果存在许多差异：人群往往更年轻；不使用马雌激素；治疗重点不是预防慢性疾病而是性别肯定干预措施，而这些措施对精神健康和生活质量有诸多益处。",
          "position": 17
        },
        {
          "title": "易性症(男转女)醋酸环丙孕酮与螺内酯抗雄激素的效果比较",
          "link": "https://rs.yiigle.com/CN114657202205/1434019.htm",
          "snippet": "部分易性症群体存在性别焦虑，渴望通过医学方法(如药物治疗与手术治疗)进行性别表达的改变，以实现身心统一。性别确认激素治疗(gender ...",
          "date": "2022年10月15日",
          "position": 18
        },
        {
          "title": "跨性别男性的性别确认激素治疗及其安全监测 - 中国生物医学文献数据库",
          "link": "https://www.sinomed.ac.cn/article.do?ui=2024111920",
          "snippet": "性别确认激素治疗(gender affirming hormone therapy,GAHT)是跨性别者进行性别转化不可避免且最为主要的方式,治疗安全性需要更多关注。对于跨性别男性,雄激素的使用 ...",
          "position": 19
        },
        {
          "title": "潘柏林：跨性别治疗很冷门，但TA们需要医学支持 - 澎湃新闻",
          "link": "https://m.thepaper.cn/newsDetail_forward_8786958",
          "snippet": "激素疗法：使用药物来增加体内性激素或阻断体内自身性激素，以达到第二性征的改变。如跨性别男性使用雄性激素类药物后长胡须、声音低沉；跨性别女性使用雌 ...",
          "date": "2020年8月19日",
          "position": 20
        },
        {
          "title": "咖蒙医院的跨性别心理健康照护",
          "link": "https://www.kamolhospital.com/zh/service/1115/mental-healthcare",
          "snippet": "我们的心理健康评估方法 · 全面评估：详细的评估以了解需求和目标。 · 个性化治疗计划：量身定制的治疗、药物和干预措施。 · 专业知识：具有性别焦虑和LGBTQ+心理健康问题专业 ...",
          "position": 21
        },
        {
          "title": "[PDF] “我需要家长同意才能做自己”",
          "link": "https://www.amnesty.org/en/wp-content/uploads/2021/05/ASA1702692019CHINESE.pdf",
          "snippet": "... 治疗选择时应视所有选择同样重要。21. 部分而非全部的跨性别者认为激素疗法和性别确认手术是缓解性别不一致的必需医疗程序。22. 在接受激素疗法或手术前要进行精神病诊断 ...",
          "position": 22
        },
        {
          "title": "Nature | “女变男”跨性别者，在睾酮治疗期间免疫反应会趋向男性！",
          "link": "https://bydrug.pharmcube.com/news/detail/27b7e0dd17a56f619c367dc763d360c2",
          "snippet": "研究性别肯定激素治疗（Gender-affirming hormone therapy，GAHT）对免疫反应的作用有助于确定性激素对免疫的作用，并提供机会来改善对这一历来被排斥、得不到充分服务的患者 ...",
          "position": 23
        },
        {
          "title": "[PDF] 北京大学第三医院- 跨性别序列医疗",
          "link": "https://cnlgbtdata.com/files/uploads/2023/12/2022%E7%89%88%E8%B7%A8%E6%80%A7%E5%88%AB%E5%8C%BB%E7%96%97%E7%85%A7%E6%8A%A4%E6%89%8B%E5%86%8C_4JGB5o5.pdf",
          "snippet": "性别肯定激素治疗. 性别肯定激素治疗(Gender-affirming Hormone. Therapy,GAHT)、激素替代治疗(Hormone Replacement. Therapy, HRT),是通过药物帮助跨性别者和性别非常. 规 ...",
          "position": 24
        },
        {
          "title": "[PDF] 跨性别者性别认同的法律承认",
          "link": "https://www.undp.org/sites/g/files/zskgke326/files/migration/asia_pacific_rbap/81e35c0bbe5b80d746519d11bb00d20cb33c8990b529c6664137bf2127ce73cd.pdf",
          "snippet": "60 但既然肯定为同性恋者进行治疗是虚假宣传，那. 么对这一涉及生命健康的违法医疗行为进行营利性网络推广的虚假宣传行为就应当适用《中华人民共和. 国消费者权益保护法》 ...",
          "position": 25
        },
        {
          "title": "性别不一致和性别焦虑症 - 默沙东诊疗手册",
          "link": "https://www.msdmanuals.cn/home/mental-health-disorders/gender-incongruence-and-gender-dysphoria/gender-incongruence-and-gender-dysphoria",
          "snippet": "缓解痛苦的治疗选择包括社会性别转换（以指定性别生活，即使没有医疗或手术治疗）、治疗抑郁或焦虑的心理治疗、性别认定激素治疗和/或性别确认手术。 ... 跨性别肯定 ...",
          "position": 26
        },
        {
          "title": "中国跨性别者寻求性别确认医疗程序时遇到的障碍",
          "link": "https://www.amnesty.org/ar/documents/asa17/0269/2019/zh/",
          "snippet": "跨性别者基本上是被中国的医疗卫生系统所忽视的一群。到底中国有多少跨性别者，又或是多少人接受了激素疗法及手术等性别确认医疗程序，官方没有统计数据。",
          "position": 27
        },
        {
          "title": "跨性别女性性别确认激素治疗策略 - 学术前沿在线- 高等教育出版社",
          "link": "https://academic.hep.com.cn/ogg/CN/10.3868/j.issn.2095-1558.2022.04.007",
          "snippet": "摘要:慢性炎症与肿瘤的发生发展息息相关。研究发现中性粒细胞淋巴细胞比值（NLR）、血小板淋巴细胞比值（PLR）可能作为炎症标记物，预测各种疾病的进展或预后。NLR、PLR已被证明 ...",
          "position": 28
        },
        {
          "title": "[PDF] 健康提示",
          "link": "https://www.nyc.gov/assets/doh/downloads/pdf/ah/pride-and-care-tgncnb-sc.pdf",
          "snippet": "本. 手册含有可为TGNCNB 人员健康提供支持. 的信息，内容包括性别确认、初级护理、性 ... 纽约市性健康诊所可提供STI 的预防、检测和治疗，HIV 服. 务（包括检测、PrEP ...",
          "position": 29
        },
        {
          "title": "[PDF] 解答你的问题- 关于跨性别者",
          "link": "https://www.apa.org/topics/lgbtq/chinese-simplified-transgender.pdf",
          "snippet": "有些跨性别者，尤其是变性者，会非常. 不满意自己的生理性别、身体性特征或符合. 该性别的性别角色。这些人通常会寻求性别. 确认治疗。 如果发现孩子出现跨性别或性别不. 符 ...",
          "position": 30
        },
        {
          "title": "跨性别男性的评估与管理- UpToDate",
          "link": "https://www.uptodate.com/contents/zh-Hans/transgender-men-evaluation-and-management",
          "snippet": "想要接受性别确认治疗的患者可选择激素治疗和性别确认手术，以及脱毛或言语治疗等其他方法[1-7]。 本文将使用广义上的跨性别者，包括性别认同与出生时 ...",
          "date": "2023年6月30日",
          "position": 31
        },
        {
          "title": "“救救孩子们，为何美国还在假装认为'性别确认护理'有效？”-观察者网",
          "link": "https://www.guancha.cn/internation/2024_07_28_743009.shtml",
          "snippet": "文章作者保罗最后苦心劝告说，只有将性别治疗从政治意识形态中解放出来，并建立基于证据的指导方针，才能使父母相信医生能为他们的孩子提供最好的照顾。对于 ...",
          "date": "2024年7月28日",
          "position": 32
        },
        {
          "title": "HRT 概论 - FtM.wiki",
          "link": "https://ftm.wiki/zh-cn/hrt/overview/",
          "snippet": "激素替代治疗(HRT) 指的是通过摄入性激素或相关药物， 让跨性别者的第二性征能更贴近他们的性别认同 ， 体验所认同性别的生理状态，帮助接纳自我。 男性化激素治疗(MHT) 是一 ...",
          "position": 33
        },
        {
          "title": "GnRH 类似物 - MtF.wiki",
          "link": "https://mtf.wiki/zh-cn/docs/medicine/antiandrogen/gnrha/",
          "snippet": "若成年后仍希望进行性别转变，则可接以性别肯定激素治疗；若决定不进行转变，停药后原有青春期会重新启动。国外研究显示，该治疗可以改善跨性别青少年的性别焦虑相关心理健康。",
          "position": 34
        },
        {
          "title": "[PDF] 为儿童和青少年保留选择权 - Translated government of Alberta news",
          "link": "https://www.alberta.ca/system/files/news-preserving-choice-for-children-and-youth-20240201-langsc.pdf",
          "snippet": "... 疗法来进行性别重置或性别肯. 定，已开始治疗的儿童除外。 • 16 岁和 ... 春期阻滞剂和激素治疗，以达到性别重置和性别肯定的目的。 针对阿尔伯塔 ...",
          "date": "2024年2月1日",
          "position": 35
        },
        {
          "title": "【专题报道】中国“同志”等性和性别少数群体境遇有待改善 - UN News",
          "link": "https://news.un.org/zh/story/2019/06/1036281",
          "snippet": "刘明辉：“跨性别的人如果想做性别肯定手术，也就是我们说的变性手术 ... 在中国，一名曾遭受过催眠和电击等所谓“矫正治疗”的性少数人士于2014年 ...",
          "date": "2019年6月24日",
          "position": 36
        },
        {
          "title": "[PDF] 全球跨性别健康与幸福指数议题",
          "link": "https://transrespect.org/wp-content/uploads/2018/12/TvT-PS-Vol20-2018_CN.pdf",
          "snippet": "此外，该地区无法获得性别肯定手. 术。 对于希望接受荷尔蒙代替治疗的跨性别者来说，通过私人医生或者进行自. 我药物治疗或获取是常见的， ...",
          "position": 37
        },
        {
          "title": "日本法院推翻跨性别者强制绝育规定 - Human Rights Watch",
          "link": "https://www.hrw.org/zh-hans/news/2023/10/16/japan-court-rules-against-mandatory-transgender-sterilization",
          "snippet": "不过，其中两位大法官肯定改革确有必要，他们写道：“［跨性别人士］在 ... 中国对LGBT人士的扭转治疗. Main Image for China Report. 更多报导.",
          "date": "2023年10月16日",
          "position": 38
        },
        {
          "title": "醫療程序 - Transgender Equality Hong Kong 香港跨性別平權協會",
          "link": "http://www.tehk.org.hk/healthcare_tc.html",
          "snippet": "一般而言，性別不一致或性別不安人士會在治療初期接受精神及心理評估，亦會在醫療團隊的安排下接受基本身體檢查及荷爾蒙檢驗。團隊成員會根據他/她們的臨床情況以及個人意願 ...",
          "position": 39
        },
        {
          "title": "性别肯定:我需要手术吗? - 外围足球",
          "link": "http://2vcoalo.mlbsluggers.com/health/wellness-and-prevention/gender-affirmation-do-i-need-surgery",
          "snippet": "Hormone therapy 能帮助你获得更多男性化或女性化的特征吗. 通常由初级保健提供者或内分泌学家开处方, 激素治疗可以是术前计划的一部分，也可以是单独的服务.",
          "position": 40
        },
        {
          "title": "跨性別女性化賀爾蒙療法| 最新消息 - 中國醫藥大學附設醫院",
          "link": "https://www.cmuh.cmu.edu.tw/NewsInfo/NewsArticle?no=6907",
          "snippet": "跨性別賀爾蒙治療的關鍵原則是盡可能地達到與個人的所認同之性別環境，以減緩性別不安，這其中包括一些抑制的內源激素或替代療法的賀爾蒙。賀爾蒙療法會 ...",
          "date": "2020年10月26日",
          "position": 41
        },
        {
          "title": "性别确认手术- 男性至女性 - Samitivej",
          "link": "https://www.samitivejhospitals.com/zh/article/detail/Gender-Affirmation-Surgery-Male-to-Female-bangkok-thailand",
          "snippet": "性别确认手术（男性至女性）的目的是改变男性的生殖器，使其在外观上类似于女性的生殖器，功能和感觉与阴道相似。这是通过手术改变睾丸来创建阴道腔，从而可以进行性交。 有多种 ...",
          "position": 42
        },
        {
          "title": "女跨男性别肯定激素治疗中的免疫适应 - 楚雄州科学技术协会",
          "link": "https://cxzkx.org.cn/wap_2018/file_read.aspx?id=9307",
          "snippet": "近日，一项发表于《自然》（Nature）的研究报道称，跨性别男性（出生性别为女性）在性别肯定激素治疗期间，免疫反应会变得更像顺性别男性（出生性别为男性）。",
          "date": "2024年9月25日",
          "position": 43
        },
        {
          "title": "[PDF] 美国心理学会性少数人群心理实践指南",
          "link": "https://www.apa.org/pi/lgbt/resources/practice-sexual-minority-chinese.pdf",
          "snippet": "工作小组《对性倾向苦恼和扭转. 治疗的正确的肯定式回应》的报. 告，提倡以下肯定性少数者的替. 代性选择（APA，2009a）： 提供. 接纳和支持；对性少数压力和其. 他影响来访 ...",
          "position": 44
        },
        {
          "title": "中国第一个“跨性别门诊” - 36氪",
          "link": "https://m.36kr.com/p/2838705615882887",
          "snippet": "不像其它疾病的诊断和治疗完全由医生主导，在“性别确认治疗”中，我们和来诊者是互动的。 有些人只是不喜欢自己的某一个部位，有些人就是从头到脚都不认同， ...",
          "date": "2024年6月28日",
          "position": 45
        },
        {
          "title": "[PDF] 跨儿的性别困惑与身份认同 - ACHPPI 国际华人心理与援助专业协会",
          "link": "https://achppi.org/wp-content/uploads/2020/07/%E8%B7%A8%E5%84%BF%E7%9A%84%E6%80%A7%E5%88%AB%E5%9B%B0%E6%83%91%E4%B8%8E%E8%BA%AB%E4%BB%BD%E8%AE%A4%E5%90%8C.pdf",
          "snippet": "2018-2020年先后在台湾、美国方向，接受关系取向心理治疗、女. 性主义治疗、性别与心理、多元文化咨询训练； ... 使用性别肯定语言很重要。 • 创造一个性别肯定的咨询 ...",
          "position": 46
        },
        {
          "title": "北医三院 - MtF.wiki",
          "link": "https://mtf.wiki/zh-cn/docs/hrt/puth/",
          "snippet": "已就诊精神心理科，诊断易性症、性别认同障碍、性别焦虑或性别烦躁;有性别肯定激素治疗的诉求； · 满18周岁且≤ 40岁，具备完全民事行为能力； · 从未使用过相关药物;或既往连续 ...",
          "position": 47
        },
        {
          "title": "美媒：变性正变得越来越低龄化和匆忙，一些青少年后悔改变性别了",
          "link": "https://news.sina.cn/2022-06-19/detail-imizirau9379133.d.html",
          "snippet": "科尔同意安德森的观点，她也认为需要进行更多的心理评估，以确定心理健康问题是否可能影响变性的欲望。“心理治疗需要得到更多的关注，”科尔说。“我们本可以让 ...",
          "date": "2022年6月19日",
          "position": 48
        },
        {
          "title": "卫生部办公厅关于印发《性早熟诊疗指南（试行）》的通知",
          "link": "http://www.nhc.gov.cn/yzygj/s3585u/201012/30b6e1feac354a18bf6987971b7afc76.shtml",
          "snippet": "4.治疗监测和停药决定：治疗过程中每3-6个月测量身高以及性征发育状况（阴毛进展不代表性腺受抑状况）；首剂3-6个月末复查GnRH激发试验，LH峰值在青春前期水平 ...",
          "date": "2010年12月17日",
          "position": 49
        },
        {
          "title": "接受激素治疗的成年跨性别者：50年内死亡率趋势调查 - 环球医学",
          "link": "https://www.g-medon.com/Item/64581.aspx",
          "snippet": "将1972～2018年间接受激素治疗的跨性别者数据与荷兰统计局相关联。排除使用睾酮和雌二醇交替治疗，在17岁以下开始治疗，或者在性别确认激素治疗之前曾经使用 ...",
          "date": "2021年10月22日",
          "position": 50
        },
        {
          "title": "性别重置手术_百度百科",
          "link": "https://baike.baidu.com/item/%E6%80%A7%E5%88%AB%E9%87%8D%E7%BD%AE%E6%89%8B%E6%9C%AF/1301503",
          "snippet": "... 肯定，这三种性别重置手术均包含了一系列互不相同的手术项目。受术者术后的性别认定方法因国家而异，有第一、第二性征认定法、心理认定法和第三性别 ... “跨性别扭转治疗” ...",
          "position": 51
        },
        {
          "title": "跨的旅程：跨性別的賀爾蒙治療 - 台灣基地協會",
          "link": "https://www.gdi.org.tw/archives/17126",
          "snippet": "在面對這樣的「性別不安」時，賀爾蒙治療（Hormone Replacement Therapy, HRT）是其中一個許多人會選擇的方式，透過使用賀爾蒙來抑制或逆轉原生性別的生理特徵，以更符合自身所 ...",
          "position": 52
        },
        {
          "title": "[PDF] UNDP-CH-PEG-Being-LGBT-in-China_CH.pdf",
          "link": "https://www.undp.org/sites/g/files/zskgke326/files/migration/cn/UNDP-CH-PEG-Being-LGBT-in-China_CH.pdf",
          "snippet": "那些感染HIV 的. 性少数人士更是遭遇双重的污名化，他们在获取疾病防治和治疗服务以及无偏见的心理支持和咨询服务. 时障碍重重。 Page 6. 6 Ⅰ中国性少数群体生存状况– 基于 ...",
          "position": 53
        },
        {
          "title": "跨性别激素治疗须知（2022版）-北京整形美容医院",
          "link": "https://www.sar.com.cn/huiyin/yxp/13029.html",
          "snippet": "跨性别激素治疗须知（2022版） · 1、 精神科“易性症”诊断相关病历资料，交复印件。 · 2、 启动前全面体检纸质结果(提前打印出来) · 3、 父母知情确认：现场或电话.",
          "date": "2023年6月8日",
          "position": 54
        },
        {
          "title": "性别肯定激素治疗和变性个体中性激素依赖性 - 脑膜瘤",
          "link": "https://www.naomoliu.org/n/xinwen/xingbie.html",
          "snippet": "已知许多良性和恶性肿瘤是性激素依赖性的;然而，目前尚不清楚这些肿瘤的风险是否在接受性别肯定激素治疗的变性人群中是不同的。这是非常重要的研究，因为这种激素疗法是在 ...",
          "position": 55
        },
        {
          "title": "[PDF] 第三章認識跨性別者（T）及其處境",
          "link": "https://www.boca.gov.tw/dl-2331-7e983e47d7e043f3b9c6d19c66e9d68a.html",
          "snippet": "即使在明確出櫃之後，如果親友無法肯定自己的性別認同，仍可能會錯稱自己. 的性別 ... ……三、藥癮治療、美容外科手術、非外傷治療性齒列矯正、預防性手術、. 人工 ...",
          "position": 56
        },
        {
          "title": "跨儿心理工作手册 - 跨性別資源中心",
          "link": "https://www.tgr.org.hk/index.php/zh/31-china/355-twt-counselor-handbook",
          "snippet": "这种改变是为了更好地使身体与性别认同相符。这些医疗干预主要包括激素治疗（性别肯定激素治疗，激素替代治疗）（Hormone therapy,gender-affirming hormone ...",
          "date": "2021年9月11日",
          "position": 57
        },
        {
          "title": "[PDF] 透过联邦临时医疗保险项目(Interim - Trans Care BC",
          "link": "https://www.transcarebc.ca/sites/default/files/2024-03/Gender-affirming_care_on_the_IFHP_CH-Simplified.pdf",
          "snippet": "性别肯定手术的咨询和评估. 性别肯定手术. 受保障的服务和申请要求会不时改变，您可以考虑联络下列组织查询目前的资料。 申请联邦临时医保：. 1. 申请难民／受庇护人士身份：.",
          "position": 58
        },
        {
          "title": "手術資訊／Surgery Information - Gender Empowerment 性別空間",
          "link": "https://genderempowerment.org/index.php/surgery-infomation/",
          "snippet": "性別肯定手術(Gender Affirming Surgery, GAS) (舊稱: 性別重置手術, SRS) ． · 面部女性化手術/面部柔化手術(Facial Feminization Surgery, FFS) · 喉核切除 · 聲帶手術 · 胸部 ...",
          "position": 59
        },
        {
          "title": "[PDF] 性別不安 - 健康九九",
          "link": "https://health99.hpa.gov.tw/media/public/pdf/21920.pdf",
          "snippet": "隨著當代精神醫學界將性別不安「去疾. 病化」，精神科醫師的角色由判定有無疾病的「仲裁. 者」，轉變為肯定個體自我認同，並協助克服轉換性 ... 及性別置換手術治療後，性別不安 ...",
          "position": 60
        },
        {
          "title": "Nature | 女跨男性别确认睾酮治疗过程中的免疫适应 - 医药魔方ByDrug",
          "link": "https://bydrug.pharmcube.com/news/detail/b72bad79d0627d244bcdb0cd5e3ab68d",
          "snippet": "ByDrug医药新闻摘要⌋ 2024-09-07 08:18，BioArt：传染性、炎症性和自身免疫性疾病在男性和女性中的表现不同。 比如初次感染SARS-CoV-2的男性的死亡风险相对略高， ...",
          "position": 61
        },
        {
          "title": "结合雌激素片说明书 - 标准来源",
          "link": "https://www.nmpa.gov.cn/wwwroot/hy5/035.htm",
          "snippet": "因此，冠状动脉疾病危险性的降低不能肯定地归于雌激素替代治疗。这可能是由研究妇女的生活方式和医学方面的特征所致，因为受试者是健康妇女。一般来讲，与 ...",
          "position": 62
        },
        {
          "title": "变性手术",
          "link": "https://www.yanhee.net/cn/sex-reassignment-surgery-thailand/",
          "snippet": "治疗 · 阻断青春期发育– 性别焦虑的少年可以寻求性激素（睾酮或雌激素）的药物处方，来抑制青春期的外形变化。 · 性激素– 青少年或成人可以通过服用性激素如雌激素或睾酮来促使 ...",
          "position": 63
        },
        {
          "title": "巴黎奥运会已经彻底禁止跨性别运动员按照其性别认同参赛 ... - Reddit",
          "link": "https://www.reddit.com/r/douban_read/comments/1ehhifp/%E5%B7%B4%E9%BB%8E%E5%A5%A5%E8%BF%90%E4%BC%9A%E5%B7%B2%E7%BB%8F%E5%BD%BB%E5%BA%95%E7%A6%81%E6%AD%A2%E8%B7%A8%E6%80%A7%E5%88%AB%E8%BF%90%E5%8A%A8%E5%91%98%E6%8C%89%E7%85%A7%E5%85%B6%E6%80%A7%E5%88%AB%E8%AE%A4%E5%90%8C%E5%8F%82%E8%B5%9B%E6%97%A0%E8%AE%BA%E5%85%B6%E6%98%AF%E5%90%A6%E6%8E%A5%E5%8F%97%E6%BF%80%E7%B4%A0%E6%B2%BB%E7%96%97%E6%98%AF%E5%90%A6%E6%8E%A5%E5%8F%97%E6%80%A7%E5%88%AB%E8%82%AF%E5%AE%9A%E6%89%8B%E6%9C%AF%E8%80%8C%E8%BF%99%E4%B8%80/",
          "snippet": "巴黎奥运会已经彻底禁止跨性别运动员按照其性别认同参赛，无论其是否接受激素治疗、是否接受性别肯定手术，而这一规定当然不会只影响到跨性别运动员， ...",
          "date": "2024年8月1日",
          "position": 64
        },
        {
          "title": "Purple Med | 跨性别男性如何变回自己",
          "link": "https://wdkpurple.lgbt/post/2019-04-05-ftm/",
          "snippet": "这种做法是可逆的，可以延长确认性别焦虑的时间，而且把青春期抑制在早期会使随后的激素治疗取得更好的效果。这样做还可以预防跨性别儿童的心理问题。但GnRH ...",
          "date": "2019年4月5日",
          "position": 65
        },
        {
          "title": "是不是需要心理评估才能进行激素治疗？-京东健康 - JD.com",
          "link": "https://www.jd.com/pccontent/12055210",
          "snippet": "跨性别，现在的诊断主要是需要在精神心理科进行，医生会对是不是跨性别进行确认。其次，跨性别是否合并性别焦虑，属于哪一种性别焦虑，还有是否同时合并有其他精神心理方面 ...",
          "position": 66
        },
        {
          "title": "如何看懂性激素六项检查结果？-武汉大学医院",
          "link": "https://hospital.whu.edu.cn/info/1281/1756.htm",
          "snippet": "伴随女性终生的性腺轴即下丘脑-垂体-卵巢轴，控制着女性发育、正常月经和性生殖功能，这些功能是通过神经调节和性激素反馈调节完成的。因此，临床上通过测定性激素水平来了解 ...",
          "position": 67
        },
        {
          "title": "如何看待更年期激素补充治疗 - 北京协和医院",
          "link": "https://www.pumch.cn/detail/13611.html",
          "snippet": "... 性，入选人群年龄偏大，不能证实绝经过渡期的情况。当然，“激素补充治疗与乳腺癌的关系没有肯定”不等于可以随便使用激素，应用时应严格掌握适应证和禁忌证，注意用药前 ...",
          "position": 68
        },
        {
          "title": "跨性别者医美之路",
          "link": "https://m.medsci.cn/article/show_article.do?id=ca77e84043e2",
          "snippet": "跨性别者的医美提出了一项独特的美学任务，因为变性妇女可能寻求女性化，但美学目标可能不是实现女性气质或男性气质本身，而是获得最符合患者自我肯定的女性 ...",
          "date": "2023年8月1日",
          "position": 69
        },
        {
          "title": "艾滋病毒和艾滋病",
          "link": "https://www.who.int/zh/news-room/fact-sheets/detail/hiv-aids",
          "snippet": "值得注意的是，正在接受抗逆转录病毒治疗且无法检测到病毒载量的艾滋病毒携带者不会将艾滋病毒传给其性伴侣。因此，及早向艾滋病毒感染者提供抗逆转录病毒 ...",
          "date": "2023年7月13日",
          "position": 70
        },
        {
          "title": "马斯克首次公开谈论跨性别的儿子，“我的泽维尔被觉醒害了” - QQ News",
          "link": "https://news.qq.com/rain/a/20240723A06NPT00",
          "snippet": "”马斯克害表示说，当他同意儿子接受治疗时，没有人向他解释青春期阻滞剂“实际上只是绝育药物”。他称“性别肯定治疗”一词是“糟糕的委婉说法”。 图片.",
          "date": "2024年7月23日",
          "position": 71
        },
        {
          "title": "安非他酮与舍曲林治疗首发女性抑郁症患者疗效及对患者雌激素水平 ...",
          "link": "https://rs.yiigle.com/CN431274202210/1433429.htm",
          "snippet": "目前抗抑郁药物是抑郁症主要治疗手段，其抗抑郁药物种类较多，疗效不一。随着研究深入，抑郁症本身引发的性功能障碍备受临床关注，经过抗抑郁治疗后某些性功能问题可能得到 ...",
          "position": 72
        },
        {
          "title": "雌激素孕激素及妈富隆三种方法治疗青春期功血180例临床分析",
          "link": "http://www.xdyyws.com/xdyyws/article/html/163543",
          "snippet": "... 治疗青春期功血治疗效果肯定，不良反应少，患者依从性好， ... 结论：妈富隆用于治疗青春期功血治疗效果肯定，不良反应少，患者依从性好，值得临床推广。",
          "position": 73
        },
        {
          "title": "中国性别肯定激素治疗研究(CGAHT)",
          "link": "https://ichgcp.net/zh/clinical-trials-registry/NCT05318755",
          "snippet": "关于跨性别医疗，尤其是性别肯定激素治疗（GAHT）的数据在中国极度不足。 很少有证据表明激素治疗对中国跨性别人群的生理和心理影响。",
          "date": "2023年11月16日",
          "position": 74
        },
        {
          "title": "性别工程：弥补上帝造人时偶然的疏漏 - 搜狐",
          "link": "https://www.sohu.com/a/357287006_296660",
          "snippet": "刘医生：对，原本内分泌科的疾病谱里并没有包含跨性别这一块。但在欧美国家，跨性别激素治疗是有相应指南的，是由内分泌协会和跨性别健康组织共同发起、制定和 ...",
          "date": "2019年11月29日",
          "position": 75
        },
        {
          "title": "性别重置手术概论 - FtM.wiki",
          "link": "https://ftm.wiki/zh-cn/srs/overview/",
          "snippet": "通常，在跨性别者社群中，性别重置手术被略称为“手术”或“SRS”，视语境而定可能指代生殖器的手术或任何可能的手术。 跨性别男性(FtM) 的性别重置手术项目主要包括：. 性别肯定 ...",
          "position": 76
        },
        {
          "title": "跨性別醫療資源 - 台灣同志諮詢熱線協會|",
          "link": "https://hotline.org.tw/pagegeneral/3244",
          "snippet": "... 性別社群及其親友提供即時完整的資源！ 勘誤來函請寄： ... 鄧敦弘（語言治療師）. 新竹. 新竹國泰醫院. 洪薏婷（語言治療師，復健科），可掛號 ...",
          "position": 77
        },
        {
          "title": "关于发布药物临床试验质量管理规范的公告 - 中国政府网",
          "link": "https://www.gov.cn/gongbao/content/2020/content_5525106.htm",
          "snippet": "第七条 所有临床试验的纸质或电子资料应当被妥善地记录、处理和保存，能够准确地报告、解释和确认。 ... （五）实施非治疗性临床试验（即对受试者没有预期的直接临床获益的试验） ...",
          "position": 78
        },
        {
          "title": "如何早期发现感染艾滋病毒",
          "link": "https://ncaids.chinacdc.cn/sjb/zsyd_10323/201804/t20180419_164653.htm",
          "snippet": "... 治疗措施来争取早期治疗和延长生命。 感染艾滋病毒有急性期吗？ 有。有些人通过 ... 首先要肯定自己是否可能感染艾滋病毒。 凡是同性恋，与人合用过针头注射毒品 ...",
          "position": 79
        },
        {
          "title": "跨性別醫療程序／Transition Process - Gender Empowerment 性別空間",
          "link": "https://genderempowerment.org/index.php/transition-process/",
          "snippet": "內分泌科臨床心理科職業治療言語治療等等… ↓ 內分泌科荷爾蒙補充療法 (同時 ... 性別肯定手術 (性別重置手術) ↓ 由醫院發出性別重置證明書 ↓ 更改身份證性別.",
          "position": 80
        },
        {
          "title": "“医生，求求你把我阑尾切了！”可你明明没得阑尾炎啊...",
          "link": "http://wsjkw.hangzhou.gov.cn/art/2024/10/31/art_1229113704_58939285.html",
          "snippet": "... 治疗难治性抑郁症。 无抽搐电痉挛治疗（MECT）：对于严重抑郁症或自杀风险高的患者，MECT是一种起效迅速、相对安全、疗效肯定的治疗方法。 04 自我 ...",
          "date": "4天前",
          "position": 81
        },
        {
          "title": "性别肯定激素治疗 - Wikiwand",
          "link": "https://www.wikiwand.com/zh/articles/%E6%80%A7%E5%88%AB%E8%82%AF%E5%AE%9A%E6%BF%80%E7%B4%A0%E6%B2%BB%E7%96%97",
          "snippet": "性别肯定激素治疗，旧称跨性別荷爾蒙治療（，THT），在部分跨性别女性中被以俚语称为“吃糖”。是一种提供给跨性別者或非性別二元者的激素替代疗法（HRT），藉由摄入性激素或相關 ...",
          "position": 82
        },
        {
          "title": "医生知识【跨性别的“激素科技”泰国变性手术前的变更点】",
          "link": "https://rubikhealth.com/zh/articles/interesting-doctors-fact-on-taking-hormones-for-transgender-turning-point-before-sex-reassignment-surgery-in-thailand",
          "snippet": "但是在改变性别之前来之不易，因为接受变性手术的人必须去看心理医生为了得到确认“身体和精神上出现的性别不匹配”。 ... 并导致治疗无效或更多不良药物反应; 如果剧烈或 ...",
          "position": 83
        },
        {
          "title": "[PDF] 前列腺癌诊疗指南",
          "link": "http://www.nhc.gov.cn/yzygj/s7659/202204/a0e67177df1f439898683e1333957c74/files/64eb7728ee494e299a77846fff09840e.pdf",
          "snippet": "... 性治疗从而减少治疗. 可能引起的副作用。由于这类患者有着更长的预期寿命，因. 此 ... 其疗效肯定、创伤小，尤其适合于不能耐受根治性前列腺切. 除术的高龄前列腺癌 ...",
          "position": 84
        },
        {
          "title": "梅毒",
          "link": "https://www.who.int/zh/news-room/fact-sheets/detail/syphilis",
          "snippet": "梅毒是一种可以预防和可以治愈的细菌性性传播感染。如果不治疗，可能会导致严重的健康问题。 许多梅毒患者没有症状，或者没有注意到症状。 梅毒在口交、 ...",
          "date": "2024年5月21日",
          "position": 85
        },
        {
          "title": "【假】加州允许医生在家长不知情的情况下给孩子做跨性别手术？",
          "link": "https://www.piyaoba.org/gender-affirming-california/",
          "snippet": "ABC的核查确认，加州法律并不允许医生在没有家长允许的情况下进行性别肯定（Gender-Affirming）手术，即变性手术。 ... 性别转换的治疗。 107号法案还为 ...",
          "date": "2022年10月15日",
          "position": 86
        },
        {
          "title": "青少年性別認同障礙之認識與處理 - 亞東醫院",
          "link": "https://www.femh.org.tw/magazine/viewmag.aspx?ID=4692",
          "snippet": "... 性別認同及肯定其實更為重要。 而同性戀則沒有「性別認同」上的困擾，他們認同 ... 治療主要在於協助他（她）以自己所認同的性別或性取向適應生活，調適其心理與 ...",
          "position": 87
        },
        {
          "title": "干细胞疗法治新冠：中国起步更早，走得更快",
          "link": "http://gdstc.gd.gov.cn/kjfyzl/fykp/content/post_2985441.html",
          "snippet": "... 治疗安全性良好。 早在2月1日，郑州大学附属河南省人民医院的“间充质干细胞(MSC) ... “调控是一个复杂的网络，目前我们只是沿着一条路线去看它的调控，肯定会有一些我们还未观察 ...",
          "position": 88
        },
        {
          "title": "“性倾向纠正治疗”在瑞士害人不浅 - Swissinfo",
          "link": "https://www.swissinfo.ch/chi/business/%E6%80%A7%E5%80%BE%E5%90%91%E7%BA%A0%E6%AD%A3%E6%B2%BB%E7%96%97-%E5%9C%A8%E7%91%9E%E5%A3%AB%E5%AE%B3%E4%BA%BA%E4%B8%8D%E6%B5%85/47619568",
          "snippet": "与许多国家不同，瑞士并未对“性倾向矫正疗法“(conversion therapy，又称回转治疗)予以禁止。顾名思义，这些疗法声称可以\"治愈同性恋\"。这种治疗经常在 ...",
          "date": "2022年6月19日",
          "position": 89
        },
        {
          "title": "中国心理咨询与治疗行业大会暨中…",
          "link": "http://www.chinacpb.net/public/index.php/phone/index/info/leixing/22/id/231.html",
          "snippet": "加速体验性动力学治疗介绍. W38.性少数群体的心理治疗. W39.基于认知疗法的多元性别肯定式治疗. W40.正念与领导力工作坊. 讲者——嘉宾：. 蔺桂瑞、刘军、陶新华、祝卓宏、高 ...",
          "position": 90
        },
        {
          "title": "你了解癫痫生酮饮食治疗吗？ - 四川大学华西医院",
          "link": "https://www.wchscu.cn/public/department/yzyz/detail/71873.html",
          "snippet": "看到生酮饮食肯定有人要问，这个是啥子哦，不是用来减肥的吗， ... 治性癫痫公认的非药物治疗方法。特别是婴儿、儿童效果明显，合理使用生酮饮食后使 ...",
          "position": 91
        },
        {
          "title": "[PDF] 化学药物制剂人体生物利用度和生物等效性研究技术指导原则",
          "link": "https://www.nmpa.gov.cn/wwwroot/gsz05106/08.pdf",
          "snippet": "如果两制剂中所用辅料本身并不会导致有效性和安全性问题，生物. 等效性研究是证实两制剂治疗等效性最合适的办法。 ... 性，确认受试制剂的缓. （控）释药代动力学特征 ...",
          "position": 92
        },
        {
          "title": "肝癌患者：早诊早治踏上长期生存大道",
          "link": "https://www.anti-cancer.com.cn/html/news/articles/17745.html",
          "snippet": "当AFP升高到一定程度时肯定是癌，AFP阴性时不能说一定不是癌。 早诊早治踏上长期生存大道 早期肝癌的主要治疗方法是根治性手术切除和局部（射频）消融治疗 ...",
          "date": "2018年5月11日",
          "position": 93
        },
        {
          "title": "免疫联合治疗让肝癌患者焕发“生机” - 科技日报",
          "link": "https://www.stdaily.com/index/kejixinwen/2021-07/13/content_1176182.shtml",
          "snippet": "邢宝才认为，未来针对肝癌治疗，不应该先手术，也不应该先局部治疗，系统性治疗应该摆在第一位，“这肯定是一个时代”。他说，影像学检查做完以后，根据肿瘤的大小 ...",
          "date": "2021年7月13日",
          "position": 94
        },
        {
          "title": "常见外阴阴道炎的治疗进展 - 中国生育健康杂志",
          "link": "http://cjrh.bjmu.edu.cn/fileup/HTML/2017-4-392.shtml",
          "snippet": "... 性阴道炎以及近些年新提出细胞溶解性阴道病,滴虫阴道炎的治疗方法很成熟，疗效肯定，本文不再涉及。 一、细菌性阴道病(bacterial vaginosis,BV). BV是育龄期女性最常见 ...",
          "position": 95
        },
        {
          "title": "美國緬因州眾議會表決通過「性別肯定照護」法案，造福青年跨性別者",
          "link": "https://www.thenewslens.com/article/187795",
          "snippet": "美國國內對性別肯定照護的反對聲浪不斷，許多州制訂禁令限制相關醫療行為，LGBT青少年族群的權益恐遭剝奪。美國主流醫療協會紛紛表態支持性別肯定照護，認為 ...",
          "date": "2023年6月28日",
          "position": 96
        },
        {
          "title": "2023妊娠期高血糖医学营养治疗及系统化管理培训班顺利召开",
          "link": "https://news.ccmu.edu.cn/fykx_11926/dd08ab06edc7427691f8bbfbd7c2d8a1.htm",
          "snippet": "... 治疗的重要性。最后，结合切身经验，对孕期糖尿病营养治疗中需要 ... 赵维纲教授肯定了这两个病例的治疗效果，结合丰富的临床经验，为大家分享 ...",
          "date": "2024年2月1日",
          "position": 97
        },
        {
          "title": "准备性别确认手术:询问专家 - 外围足球",
          "link": "http://www.hokkaidopc.com/health/wellness-and-prevention/preparing-for-gender-affirmation-surgery-ask-the-experts",
          "snippet": "To help provide guidance for those considering gender affirmation surgery, two experts from the Johns Hopkins Center for 变性人的健康answer questions about ...",
          "position": 98
        },
        {
          "title": "抑郁症治疗难题，何解？ - 上观新闻",
          "link": "https://www.jfdaily.com/news/detail?id=812728",
          "snippet": "目前，我国抑郁症患者数量已达到9500万，2021年卫生健康统计年鉴数据显示，精神科门急诊人次数，比2019年增加了约849万。 北京安定医院曾参与的一项国际性研究 ...",
          "date": "5天前",
          "position": 99
        }
      ],
      "images": [
        {
          "title": "性别重置疗法- 维基百科，自由的百科全书",
          "imageUrl": "https://upload.wikimedia.org/wikipedia/commons/thumb/d/d3/MTF_hormone_replacement_therapy_before_after.png/640px-MTF_hormone_replacement_therapy_before_after.png",
          "link": "https://zh.wikipedia.org/zh-cn/%E6%80%A7%E5%88%A5%E9%87%8D%E7%BD%AE%E7%99%82%E6%B3%95"
        },
        {
          "title": "Nature：雄激素治疗后的跨性别男性，免疫系统被重塑- 生物研究专区- 生物谷",
          "imageUrl": "https://msimg.bioon.com/bioon-com/20240905/c9931d93eabe4d62908088209bda52de-YdPsrOLDZ0iU.jpg",
          "link": "https://news.bioon.com/article/b6b884204611.html"
        },
        {
          "title": "Nature：雄激素治疗后的跨性别男性，免疫系统被重塑- 生物研究专区- 生物谷",
          "imageUrl": "https://msimg.bioon.com/bioon-com/20240905/b3aad900ba0e4f41a1942b440034aa28-W7RaKrR8bHFM.jpg",
          "link": "https://news.bioon.com/article/b6b884204611.html"
        },
        {
          "title": "Nature：雄激素治疗后的跨性别男性，免疫系统被重塑",
          "imageUrl": "https://imagepphcloud.thepaper.cn/pph/image/320/898/290.jpg",
          "link": "https://m.thepaper.cn/newsDetail_forward_28638946"
        },
        {
          "title": "跨性别和性别多样化人群的雄激素性脱发：治疗方法综述- X-MOL",
          "imageUrl": "https://xpic.x-mol.com/20230919%2F10.1016_j.jaad.2021.08.067.jpg",
          "link": "https://www.x-mol.com/paper/1453881095373094912/t"
        },
        {
          "title": "咖蒙医院的跨性别心理健康照护| Cosmetic Plastic Surgery | Aesthetic ...",
          "imageUrl": "https://www.kamolhospital.com/uploads/blog/1502/thumb-66153ff01fa7b-image_highlight.jpg",
          "link": "https://www.kamolhospital.com/zh/service/1115/mental-healthcare"
        },
        {
          "title": "MTF 替代激素的有效性和风险| Cosmetic Plastic Surgery | Aesthetic ...",
          "imageUrl": "https://www.kamolhospital.com/uploads/cke-img-upload/1712665137-661532318d284.jpg",
          "link": "https://www.kamolhospital.com/zh/blog/1498/mtf-replacement-hormone-effective-and-risk"
        },
        {
          "title": "醫療程序- Transgender Equality Hong Kong 香港跨性別平權協會",
          "imageUrl": "http://www.tehk.org.hk/img/Timeline_ch.gif",
          "link": "http://www.tehk.org.hk/healthcare_tc.html"
        },
        {
          "title": "女性化激素疗法- 维基百科，自由的百科全书",
          "imageUrl": "https://upload.wikimedia.org/wikipedia/commons/thumb/3/31/Testosterone_levels_as_a_function_of_estradiol_levels_during_oral_estradiol_therapy_in_transgender_women.png/350px-Testosterone_levels_as_a_function_of_estradiol_levels_during_oral_estradiol_therapy_in_transgender_women.png",
          "link": "https://zh.wikipedia.org/zh-cn/%E5%A5%B3%E6%80%A7%E5%8C%96%E6%BF%80%E7%B4%A0%E7%96%97%E6%B3%95"
        }
      ],
      "relatedSearches": [
        {
          "query": "男服用雌激素"
        },
        {
          "query": "mtf用药指导"
        },
        {
          "query": "雄激素药物"
        },
        {
          "query": "雌激素药物副作用"
        },
        {
          "query": "雄激素高的症状"
        },
        {
          "query": "mtf hrt变化"
        },
        {
          "query": "雌雄 激素双 高"
        },
        {
          "query": "雄激素不足"
        }
      ],
      "credits": 2
    },
    {
      "searchParameters": {
        "q": "性别肯定治疗",
        "gl": "cn",
        "hl": "zh-cn",
        "type": "search",
        "num": 100,
        "page": 2,
        "engine": "google"
      },
      "organic": [
        {
          "title": "最高法院将听取田纳西禁止为未成年人进行跨性别手术的辩论",
          "link": "https://www.epochtimes.com/gb/24/10/24/n14356713.htm",
          "snippet": "... 性别医疗治疗的立法。 联邦政府于2023年11月向最高法院提交了请愿书 ... 上诉法院维持田纳西未成年人性别肯定法律.",
          "date": "2024年10月24日",
          "position": 1
        },
        {
          "title": "习近平总书记重要指示为民政事业发展指明方向注入动力 - 省财政厅",
          "link": "https://czt.hlj.gov.cn/czt/c110775/202410/c00_31780001.shtml",
          "snippet": "习近平总书记的重要指示充分肯定近年来民政事业 ... “加强对民政工作的领导，加强普惠性、基础性、兜底性民生建设”。 ... 治疗—出院回家—复发住院治疗'的'旋转 ...",
          "date": "7天前",
          "position": 2
        },
        {
          "title": "血液系统恶性肿瘤治疗研究热点- PMC",
          "link": "https://pmc.ncbi.nlm.nih.gov/articles/PMC7348503/",
          "snippet": "... 肯定，也适合在移植后进行维持治疗研究。 继BTK激酶 ... CAR-T发展的两个核心问题为杀伤持久性和靶向性。 ... 3．免疫检查点治疗：靶向T细胞负性共刺激信号从而 ...",
          "position": 3
        },
        {
          "title": "跨性别者：喜欢穿女装的男孩需要治疗吗？ - 新浪网站导航",
          "link": "https://blog.sina.com.cn/s/blog_5b2b70620102wvvm.html",
          "snippet": "... 性别，那个性别叫“出生性别（natal gender）”。 ... 以上，就是目前APA对性别焦虑症的治疗建议。 谁 ... 并非每个患者都会求医，因此这个患病率肯定低于实际 ...",
          "date": "2016年4月28日",
          "position": 4
        },
        {
          "title": "噻托溴铵显著缓解早期慢性阻塞性肺疾病肺功能下降 - NEJM医学前沿",
          "link": "https://nejmqianyan.cn/article/YXQYoa1700228?sg=AbW1N",
          "snippet": "... 治疗质量进行监察，同时检查临床试验治疗依从性。 ... 性别、住院、GOLD分级、体质指数（体重 ... 肯定了之前的报告7,9,20。最后，在我们的试验中 ...",
          "date": "2017年9月6日",
          "position": 5
        },
        {
          "title": "体检查出慢性萎缩性胃炎，究竟要不要紧？",
          "link": "http://cq.news.cn/2024/jkmyta/mobile.htm",
          "snippet": "由于萎缩性胃炎症状无特异性，且很多患者无症状或未行内镜检查，所以患病率很难确切统计，但可以肯定 ... 萎缩性胃炎患者的症状没有特异性 ... 治疗。 经内镜下治疗的早期胃癌 ...",
          "position": 6
        },
        {
          "title": "【中国科学报】付小兵院士：杰青项目开启我科研事业的“黄金时代”",
          "link": "https://www.nsfc.gov.cn/publish/portal0/tab434/info93771.htm",
          "snippet": "但付小兵的心情却不同于此：“那是杰青项目设立的第一年，其实我不太清楚它的重要性，心态反而很放松。 ... 作为中国人自己研发的用于烧伤治疗的生物治疗新 ...",
          "date": "4天前",
          "position": 7
        },
        {
          "title": "基于信使核糖核酸(mRNA) 治疗——过去、现在和未来",
          "link": "https://www.xiahepublishing.com/m/2475-7543/MRP-2023-004S",
          "snippet": "基于mRNA的疗法的多样性，新药研发者使用合成mRNA作为疾病治疗工具，在研发癌症治疗的免疫疗法、干细胞治疗以及控制传染病上取得进展，特别是在这次新冠 ...",
          "date": "2023年6月30日",
          "position": 8
        },
        {
          "title": "手术与非手术治疗重症急性胰腺炎120例 - Baishideng Publishing Group",
          "link": "https://www.wjgnet.com/1009-3079/full/v11/i4/494.htm",
          "snippet": "... 肯定又不能除外脏器破裂穿孔者应手术探查; (5)假性胰腺囊肿于3-6 mo后行囊肿空肠内引流术. 3.4 需要借助手术解决的问题. 胆源性胰腺炎并胆道梗阻或化脓性胆管炎, 应尽早 ...",
          "position": 9
        },
        {
          "title": "关注抽动为爱前行 - 北京市卫生健康委员会",
          "link": "https://wjw.beijing.gov.cn/xwzx_20031/jcdt/202410/t20241031_3931947.html",
          "snippet": "王素梅主任医师带领团队深入研究小儿抽动障碍多年，创新性地提出了“脾虚肝旺”的病机，治疗以“扶土抑木”为法，自拟健脾止动汤，不仅临床治疗效果肯定，而且 ...",
          "date": "4天前",
          "position": 10
        },
        {
          "title": "激素疗法是否有助于跨性别女性进行性别重建以实现转换？ - Cochrane",
          "link": "https://www.cochrane.org/zh-hans/CD013138/TOBACCO_ji-su-liao-fa-shi-fou-you-zhu-yu-kua-xing-bie-nu-xing-jin-xing-xing-bie-chong-jian-yi-shi-xian-zhuan",
          "snippet": "RCT是一种能够降低几类偏倚可能性的研究方法。本综述纳入研究的标准是比较用于促进跨性别女性转换的不同激素治疗（单独使用雌激素、单独使用睾酮阻滞 ...",
          "position": 11
        },
        {
          "title": "尿路感染治疗切忌自己随便停药",
          "link": "https://mpa.zj.gov.cn/art/2010/1/29/art_1228972445_41321319.html",
          "snippet": "尿路感染是一种常见的多发性疾病，男女 ... 他肯定了中成药在治疗尿路感染的独特优势，并强调进一步发挥中药优势，以满足患者对药物疗效、耐受性和安全性的 ...",
          "date": "2010年1月29日",
          "position": 12
        },
        {
          "title": "全球首款AI骨科机器人获批上市 - 国际科技创新中心",
          "link": "https://www.ncsti.gov.cn/kjdt/kjrd/rgzn_kjrd/202410/t20241030_183958.html",
          "snippet": "... 治疗方案和机器人精准辅助，让以前凭经验完成的 ... 确认机器人算法的正确性和术前规划的可行性。 ... 肯定还能为祖国的医疗健康事业再奋斗30年”。",
          "date": "5天前",
          "position": 13
        },
        {
          "title": "生长后治疗\"是永久性的吗？",
          "link": "https://www.igi.org/zh/are-post-growth-treatments-permanent/",
          "snippet": "简短的回答是肯定的：解释如下。 有趣的事实：世界上大多数钻石都是棕色的. 棕色是最常见的钻石颜色，无论是天然的还是实验 ...",
          "date": "2023年1月11日",
          "position": 14
        },
        {
          "title": "[PDF] 硫酸镁治疗慢性阻塞性肺疾病急性加重的疗效观察 - 实用临床医药杂志",
          "link": "https://jcmp.yzu.edu.cn/cn/article/pdf/preview/10.3969/j.issn.1672-2353.2010.17.039.pdf",
          "snippet": "性加重的治疗价值，提示该药有可能成为一种无. 毒的支气管舒张剂。但由于样本较小，结论尚不. 能得到充分肯定，还需要大样本的研究加以证实。 参考文献. ［1］. 中华医学 ...",
          "position": 15
        },
        {
          "title": "大剂量低分子肝素治疗进展性重症脑梗死的临床研究",
          "link": "http://xuebao.bjmu.edu.cn/CN/abstract/abstract8740.shtml",
          "snippet": "结论:低分子肝素治疗进展性重症脑梗死有肯定的疗效,可降低死亡率,改善预后,且方法简便,安全. 关键词: 脑梗塞/药物疗法, 肝素, 低分子/治疗应用, 肝素, 低 ...",
          "date": "2002年6月28日",
          "position": 16
        },
        {
          "title": "膝关节骨关节炎的症状、原因、诊断与治疗| Pantai医院",
          "link": "https://www.pantai.com.my/zh-cn/medical-specialties/orthopaedic/knee-osteoarthritis",
          "snippet": "性别- 50岁以上的女性比男性更容易得这种病。 体重 ... 职业治疗和物理治疗. 手术技术包括 ... 马来西亚班台医院也荣获马来西亚健康品质协会（MSQH）的认证，以肯定 ...",
          "position": 17
        },
        {
          "title": "流行性感冒（流感） - NSW Health",
          "link": "https://www.health.nsw.gov.au/Infectious/Influenza/Pages/flu-fs-chinese-simplified.aspx",
          "snippet": "确认流感诊断的唯一方法是进行PCR（鼻部和咽部 ... 流感重症风险较高的患者，可以使用抗病毒疗法。 ... 尽管任何人都可能得流感，不过有些人患重症的风险较高 ...",
          "date": "2023年5月25日",
          "position": 18
        },
        {
          "title": "[PDF] 世界物理治疗联盟报告物理治疗师在灾害管理中的作用",
          "link": "https://world.physio/sites/default/files/2020-06/Disaster-Management-Report-201603-Chinese.pdf",
          "snippet": "根据年龄、性别和残疾进行分类对于监管公平和获取服务的很重要。 ... 人道主义环境下肯定不是物理治疗师在法律不完善的地区开 ... 物理治疗专业的现实性和兴趣增加了，培训机构 ...",
          "position": 19
        },
        {
          "title": "中医药治疗心衰科研成果登上国际权威医学期刊《自然医学》 - 以岭药业",
          "link": "https://www.yiling.cn/%E4%B8%AD%E5%8C%BB%E8%8D%AF%E6%B2%BB%E7%96%97%E5%BF%83%E8%A1%B0%E7%A7%91%E7%A0%94%E6%88%90%E6%9E%9C%E7%99%BB%E4%B8%8A%E5%9B%BD%E9%99%85%E6%9D%83%E5%A8%81%E5%8C%BB%E5%AD%A6%E6%9C%9F%E5%88%8A%E3%80%8A/",
          "snippet": "新加坡国家心脏中心高级顾问Carolyn Sp Lam 教授称：“该项目取得了芪苈强心治疗射血分数降低的心衰的重要长期结果数据，再次确认了该药物的长期用药安全性 ...",
          "date": "2024年8月7日",
          "position": 20
        },
        {
          "title": "白癜风科普 - 上海第四人民医院",
          "link": "https://www.sh4th.com/Content/News/1131",
          "snippet": "中医中药适用于各型各期白癜风，疗效肯定，无激素副作用，安全性更高。 3.光疗及光化学疗法：. 局部光化学疗法适用于白斑面积＜20%。口服光化学疗法用于 ...",
          "date": "2020年4月2日",
          "position": 21
        },
        {
          "title": "惠斯安普6项科技成果获评“国际领先”“国际先进” - 秦皇岛经济技术开发区",
          "link": "https://www.qetdz.gov.cn/Content/info/cid/54/id/149489",
          "snippet": "... 治疗系统”“多参数人体阻抗评测分析系统”“认知功能障碍筛查系统”等6项科技创新成果，从创新性、先进性 ... 肯定 ， 并对下一步成果推广应用提出了宝贵 ...",
          "date": "7天前",
          "position": 22
        },
        {
          "title": "六尺巷何以赋能基层治理？ - 重庆市农业农村委员会",
          "link": "https://nyncw.cq.gov.cn/zwxx_161/rdtt/202410/t20241031_13757016.html",
          "snippet": "“比如说公司与员工发生矛盾，我们肯定先做公司 ... 2023年8月，桐城市民都金姑遭遇交通事故后立即住院治疗 ... 性猝死可能。事情发生后，李某妻子 ...",
          "date": "4天前",
          "position": 23
        },
        {
          "title": "加强技术帮扶指导助力白路镇畜牧产业优产增收 - 武定县人民政府",
          "link": "http://www.ynwd.gov.cn/info/1042/57591.htm",
          "snippet": "看到他家的羊生病卧地不起，杨培昌一眼就看出羊只问题所在，当即就现场开方、指导用药，让养殖户及时治疗，减少经济损失。农户一句句朴实的肯定话语，就是 ...",
          "date": "4天前",
          "position": 24
        },
        {
          "title": "习近平总书记重要指示为民政事业发展指明方向 - 时政- 人民网",
          "link": "http://politics.people.com.cn/n1/2024/1027/c1001-40348061.html",
          "snippet": "习近平总书记的重要指示充分肯定近年来民政事业 ... “加强对民政工作的领导，加强普惠性、基础性、兜底性民生建设”。 ... 治疗—出院回家—复发住院治疗'的'旋转 ...",
          "date": "8天前",
          "position": 25
        },
        {
          "title": "性别可以被强行更改吗？“世界上最成功变性人”之死 - 36氪",
          "link": "https://m.36kr.com/p/1847100502838658",
          "snippet": "... 治疗性发育畸形和生殖器官损伤的婴儿，他感到 ... 在戴蒙德和科拉品托看来，大卫从小就有表现出典型男性行为的倾向，这说明性别中肯定有某些和基因有关的 ...",
          "date": "2022年7月28日",
          "position": 26
        },
        {
          "title": "特药事业部-医学信息沟通代表-安庆 - Sanofi Careers",
          "link": "https://jobs.sanofi.com/en/job/hangzhou/-/2649/18495129536",
          "snippet": "从研发到销售，我们的优秀团队进行通力合作，创新治疗 ... 享受周到、精心设计的奖励方案，肯定您的贡献，扩大您的影响。 ... 性别的育儿假。 追寻发展。探索 ...",
          "date": "5天前",
          "position": 27
        },
        {
          "title": "慢性炎症性关节疾病的诊断、分子分辨和治疗开发的方法",
          "link": "https://patents.google.com/patent/CN1537173A/zh",
          "snippet": "自身抗体可用于其它类风湿自身免疫病，如系统性红斑狼疮(SLE)为主要成员的胶原性疾病的诊断性分类。这些自身抗体的主要致病性已经过长期和反复讨论。可肯定在此病周期性 ...",
          "position": 28
        },
        {
          "title": "CHMP认同安进公司产品REPATHA®（依洛尤单抗）可预防心肌梗死 ...",
          "link": "https://www.amgen.cn/cn/media/chmp.html",
          "snippet": "目前，有权批准欧盟药品的欧洲委员会(EC) 将审核CHMP的肯定性意见。 ... Repatha适用于作为饮食的辅助疗法，治疗原发性高胆固醇血症（杂合子家族性和非家族性）或混合性血脂 ...",
          "position": 29
        },
        {
          "title": "美国如何操纵青少年变性？物色人选、思想灌输、偷偷带去手术 - 搜狐",
          "link": "https://www.sohu.com/a/728959433_121681544",
          "snippet": "这得益于一种名叫“性别肯定治疗”的服务，哪怕你是未成年，医护人员也会鼓励你做出改变。 虽然按照规定，一切性别肯定治疗都要成年后才能实行，但现实 ...",
          "date": "2023年10月17日",
          "position": 30
        },
        {
          "title": "【跨儿家长答疑1】孩子怎么突然说自己是跨性别？ - YouTube",
          "link": "https://www.youtube.com/watch?v=4n3uhb6xNsA",
          "snippet": "4:30 · Go to channel · 变性人？易性癖？易性病？易性症？变性手术？性别重置手术？性别肯定治疗？傻傻分不清楚. 潘柏林医生•235 views · 7:44 · Go ...",
          "date": "2023年5月25日",
          "position": 31
        },
        {
          "title": "花粉过敏都怪免疫力差？真相来了！ - 新闻频道",
          "link": "https://news.cctv.com/2023/03/25/ARTI03mnfPCRecloD1Ycj664230325.shtml",
          "snippet": "密码与确认密码不一致. 请再次输入密码. 注册. 请 ... 密码与确认密码不一致. 请再次输入密码 ... 抗组胺药属于治疗过敏性鼻炎的常用药物。患者在 ...",
          "date": "2023年3月25日",
          "position": 32
        },
        {
          "title": "性疗法技巧及其为何有用 - Carepatron",
          "link": "https://www.carepatron.com/cn/guides/sex-therapy-techniques",
          "snippet": "这个身体形象工作表 包括提示识别负面身体信念，挑战这些信念，以及制定更积极的身体肯定态度的行动计划，这可能会影响性和人际关系满意度。 2。性别界限工作表. 这个性别 ...",
          "position": 33
        },
        {
          "title": "[PDF] 间充质干细胞治疗中枢神经系统疾病的研究进展",
          "link": "https://pps.cpu.edu.cn/cn/article/pdf/preview/86ff1a82-ca74-42ad-8482-dadebe0bc9f0.pdf",
          "snippet": "安全性和有效性。 ... 表4 间充质干细胞治疗缺血性脑卒中以及创伤性脑损伤汇总 ... 综上所述，MSC 在治疗中枢神经系统疾病中的. 潜力是肯定的，但在使用时必须 ...",
          "date": "2019年3月20日",
          "position": 34
        },
        {
          "title": "我国科学家发现BCMA-CD19 双特异性CAR-T 细胞有望用于治疗慢性 ...",
          "link": "https://news.bioon.com/article/8a2583154061.html",
          "snippet": "... 治疗复发/难治性自身免疫性疾病方面的潜力。这一策略有望为CIDP带来可 ... 肯定了CAR-T细胞疗法治疗CIDP的安全性。虽然这只是一个病例报告，但更 ...",
          "date": "2024年6月28日",
          "position": 35
        },
        {
          "title": "關於茄荖山莊 - 衛生福利部草屯療養院",
          "link": "https://www.ttpc.mohw.gov.tw/?aid=52&pid=130",
          "snippet": "各界肯定 · 感謝函專區 · 看診進度查詢 · 醫療團隊 · 一般 ... [國際治療性社區標準運作]. [擴編專收女性藥癮者] ... 最末頁. 關閉網站導覽. 關於本院; 醫院介紹 · 院長的話 ...",
          "position": 36
        },
        {
          "title": "加快开发利用公共数据资源 - 光明网",
          "link": "https://economy.gmw.cn/2024-10/29/content_37643036.htm",
          "snippet": "“公共数据开发是否具有可持续性，取决于授权运营制度能否兼顾经济性和公益性。 ... 收益分配方面，应按照“肯定数据资源的基础贡献 ... 因此，如何提高ICB治疗 ...",
          "date": "6天前",
          "position": 37
        },
        {
          "title": "十年，肠菌移植从混沌走向规范 - 论文- 科学网",
          "link": "https://news.sciencenet.cn/htmlnews/2024/10/532856.shtm",
          "snippet": "第二，规范FMT的适应证、禁忌证和病人的治疗疗程、剂量。我们首次提出FMT疗法的响应规律：急性肠道炎症优于肠道慢性炎症，肠道功能性疾病优于肠道器 ...",
          "date": "6天前",
          "position": 38
        },
        {
          "title": "张强专题调研细胞与基因治疗企业时提出致力将先发优势转化为持久 ...",
          "link": "https://kfqgw.beijing.gov.cn/zwgkkfq/yzxwkfq/202410/t20241025_3927954.html",
          "snippet": "北京锦篮基因科技有限公司、北京赛赋医药研究院有限公司在CGT领域已取得突破性进展。锦篮基因作为基于AAV载体递送技术的基因治疗药物研发企业，其研发的 ...",
          "date": "2024年10月25日",
          "position": 39
        },
        {
          "title": "在全国各地创新“尖子生”中，广东缘何连续8年“霸榜”？_南方网",
          "link": "https://gdio.southcn.com/node_5201f00af5/3d36ceaa69.shtml",
          "snippet": "这份肯定，既“意料之中”，又“来之不易”。 做强 ... 2020年，广东提出要培育发展20个战略性产业集群，如今雏形已现。 ... 自主研发治疗抑郁症的中药创新药参郁 ...",
          "date": "23小时前",
          "position": 40
        },
        {
          "title": "Nature Communications首次发表泛癌免疫治疗浸润性髓系细胞单 ...",
          "link": "http://www.medicine.ynu.edu.cn/info/1043/2070.htm",
          "snippet": "... 治疗浸润性髓系细胞单细胞图谱 ... 肿瘤免疫疗法已在实体肿瘤的治疗中取得了突破性进展。 ... 但即使 PD-1 / PD-L1免疫检查点抑制剂疗效得到了很大程度的肯定 ...",
          "date": "2024年7月31日",
          "position": 41
        },
        {
          "title": "聚桂醇泡沫硬化剂治疗浅表静脉畸形的疗效及安全性分析",
          "link": "https://www.qk.sjtu.edu.cn/jter/CN/abstract/abstract23275.shtml",
          "snippet": "结论应用聚桂醇泡沫硬化剂治疗浅表静脉畸形,疗效肯定,无严重并发症,安全性高。 关键词: 聚桂醇, 泡沫硬化治疗, 浅表静脉畸形. Abstract: Objective To ...",
          "date": "2020年7月23日",
          "position": 42
        },
        {
          "title": "JEADV:局部非那雄胺喷雾剂治疗男性雄激素性脱发研究-MedSci.cn",
          "link": "https://www.medsci.cn/article/show_article.do?id=593d221425a6",
          "snippet": "口服非那雄胺治疗AGA的临床疗效肯定。尽管口服非那雄胺一般耐受性良好，在一些患者中，5a-还原酶抑制与性不良反应(勃起功能障碍 ...",
          "date": "2021年12月2日",
          "position": 43
        },
        {
          "title": "《中国流感认知与治疗现状调查报告》发布 - 广州日报大洋网",
          "link": "https://news.dayoo.com/finance/202411/01/171077_54740500.htm",
          "snippet": "... 性。 国家传染病医学中心主任、复旦大学附属 ... 性治疗，以降低重症肺炎和严重并发症的风险。 ... 肯定。 2024-10-31 20:13. 余依婷获得游泳世界杯 ...",
          "date": "3天前",
          "position": 44
        },
        {
          "title": "中医药对治疗新冠肺炎有效 - 人民日报",
          "link": "http://paper.people.com.cn/rmrb/html/2022-04/07/nw.D110000renmrb_20220407_4-17.htm",
          "snippet": "... 肯定了中医药救治新冠肺炎的有效性和安全性，鼓励世卫组织会员国在其卫生保健系统和监管框架内考虑使用中医药治疗新冠肺炎的可能性。 世卫组织中医药 ...",
          "date": "2022年4月7日",
          "position": 45
        },
        {
          "title": "华尔街到陆家嘴精选丨金价历久弥坚？微软和Meta业绩力证AI变现 ...",
          "link": "https://m.yicai.com/news/102335876.html",
          "snippet": "... 性引发投资者避险需求；其次 ... 业绩电话会后，微软也宣布在AI上将建立1000亿的基金，这也是对AI的肯定。 ... 治疗中的反复试验和试错。甲骨文负责健康与生命科学 ...",
          "position": 46
        },
        {
          "title": "「這是人類的勝利！」紐西蘭立法禁止LGBT迴轉治療 - T-Studio",
          "link": "https://www.t-studio.info/zh-TW/blogs/gender-news/92850?srsltid=AfmBOoooeaCvC_lXj6nlBGIPuKO5vTPO-Xy4PMdAYp0FzSXPT7U9DQgI",
          "snippet": "：「我們承諾，我們會愛護、支持、肯定做自己的你們…… ... 性別認同或性別表現的心理療程， ... 台灣的衛福部則在2018年以函釋的方式，禁止了性傾向扭轉治療， ...",
          "date": "2022年2月23日",
          "position": 47
        },
        {
          "title": "一款植入式神经刺激仪B轮融了6600万美元，面向10.4亿偏头痛患者",
          "link": "https://www.vbdata.cn/1518991329",
          "snippet": "... 性脑功能障碍性 ... 值得一提的是，在RELIEV-CM试验完成后，有6名患者都选择了永久植入ShiraTronics系统，这也是对该产品疗效的最大肯定。 ... 性治疗. 2024- ...",
          "date": "1天前",
          "position": 48
        },
        {
          "title": "走进2024“科学探索奖”医学科学领域唯一获奖的女科学家 - 广东",
          "link": "https://gd.chinadaily.com.cn/a/202410/31/WS6722eef4a310b59111da0dfe.html",
          "snippet": "颁奖典礼上，王峰的颁奖词是：肯定她在消化道肿瘤免疫治疗 ... 中山大学肿瘤防治中心徐瑞华、王峰团队创新性 ... 商业性个人房贷利率将实行新定价机制 · 前三 ...",
          "date": "4天前",
          "position": 49
        },
        {
          "title": "学习贯彻习近平总书记回信精神出征“挑战杯”创业计划竞赛国赛",
          "link": "https://news.ccmu.edu.cn/syyw_12977/63d67652b95545ba929761a3b1adefb7.htm",
          "snippet": "呼文亮对学校创新创业教育工作取得的阶段性成绩表示肯定，并提出了三点希望：一是要进一步学习领会习近平总书记关于科技创新一列重要讲话和论述。",
          "date": "7天前",
          "position": 50
        },
        {
          "title": "CN117677612A - 治疗缺血性脑损伤相关疾病的化合物- Google Patents",
          "link": "https://patents.google.com/patent/CN117677612A/zh",
          "snippet": "... 治疗作用不肯定。从芹菜籽挥发油中提取的3-正丁基苯酞(NBP)于2005年在中国获批用于用于治疗轻、中度急性缺血性脑卒中，但目前作用机制尚不清楚，且在 ...",
          "date": "2024年3月8日",
          "position": 51
        },
        {
          "title": "在全国各地创新“尖子生”中，广东缘何连续8年“霸榜”？",
          "link": "http://www.huizhou.cn/news/gdxw/202411/t20241103_1574399.htm",
          "snippet": "这份肯定，既“意料之中”，又“来之不易”。 做强 ... 2020年，广东提出要培育发展20个战略性产业集群，如今雏形已现。 ... 自主研发治疗抑郁症的中药创新药参郁 ...",
          "date": "23小时前",
          "position": 52
        },
        {
          "title": "北京中医药大学东方医院儿科开展“抽动障碍关爱日”主题义诊活动",
          "link": "https://www.dongfangyy.com.cn/Html/News/Articles/11191.html",
          "snippet": "王素梅主任医师带领团队深入研究小儿抽动障碍多年，创新性地提出其病机为“脾虚肝旺”，治疗以“扶土抑木”为法，自拟健脾止动汤广泛用于临床，其治疗效果肯定 ...",
          "date": "4天前",
          "position": 53
        },
        {
          "title": "佛山11岁男孩被诱骗裸聊打赏1万元，41岁女主播被判",
          "link": "https://m.mp.oeeee.com/a/BAAFRD0000202410291017653.html",
          "snippet": "“我们肯定不是个例，我担心主播这个行为还影响 ... 性权利，严重影响儿童性心理正常 ... 瑞典2岁女孩患罕见病来穗治疗，国外类似疗法约3070万元.",
          "date": "5天前",
          "position": 54
        },
        {
          "title": "快速上手指南：晕厥诊断与治疗 - 丁香智汇",
          "link": "https://e.dxy.cn/wisdom/front/zhihuihao/3117",
          "snippet": "3．心源性晕厥：心源性晕厥包括心律失常性 ... 3．器质性心血管疾病性晕厥： 治疗目标不仅是 ... 性不能肯定。此外， 尽管有血管迷走神经性晕厥 ...",
          "date": "2019年2月12日",
          "position": 55
        },
        {
          "title": "Altman携高管“回答一切”：Ilya看到了超凡未来，现有硬件就可以实现 ...",
          "link": "https://wallstreetcn.com/articles/3732740",
          "snippet": "07vex: 你如何看待人们使用ChatGPT进行心理治疗？ Sam Altman: 它显然不是治疗师，但很明显，很多人通过与它谈论他们的问题而获得价值。我们看到很多 ...",
          "date": "2天前",
          "position": 56
        },
        {
          "title": "21健讯Daily｜药明康德第三季度收入重回百亿元规模 - 21财经",
          "link": "https://www.21jingji.com/article/20241029/herald/af1c86f9b0d825d07eb5f777cf2a9710.html",
          "snippet": "10月28日，安斯泰来宣布撤回向欧洲药品管理局（EMA）递交的avacincaptad pegol（ACP）用于治疗年龄相关性黄斑变性（AMD）继发地图样萎缩（GA）的上市申请 ...",
          "date": "6天前",
          "position": 57
        },
        {
          "title": "一位医生眼中的红斑狼疮 - 网易",
          "link": "https://www.163.com/dy/article/JFE450LK0512D3VJ.html",
          "snippet": "新京报：系统性红斑狼疮怎么治疗？ 周炜：有药物治疗也有非药物治疗。药物治疗包括糖皮质激素、免疫制剂、生物制剂、细胞疗法等，非 ...",
          "date": "2024年10月26日",
          "position": 58
        },
        {
          "title": "LGBTQ+ 个体如何从在线治疗中受益：打破障碍，培育心理健康",
          "link": "https://www.bonobology.com/zh-CN/LGBTQ-%E4%B8%AA%E4%BD%93%E5%A6%82%E4%BD%95%E4%BB%8E%E5%9C%A8%E7%BA%BF%E6%B2%BB%E7%96%97%E4%B8%AD%E5%8F%97%E7%9B%8A%EF%BC%8C%E6%89%93%E7%A0%B4%E9%9A%9C%E7%A2%8D%E5%B9%B6%E5%9F%B9%E5%85%BB%E5%BF%83%E7%90%86%E5%81%A5%E5%BA%B7/",
          "snippet": "LGBTQ+ 疗法通过为酷儿社区提供方便、实惠且保密的医疗保健来满足这一需求。身份肯定治疗师的工作内容如下：他们有与不符合刻板性别期望、角色和身份的人合作的经验。他们 ...",
          "position": 59
        },
        {
          "title": "习近平总书记重要指示为民政事业发展指明方向、注入动力 - 时政频道",
          "link": "https://politics.gmw.cn/2024-10/28/content_37639658.htm",
          "snippet": "习近平总书记的重要指示充分肯定近年来民政事业 ... “加强对民政工作的领导，加强普惠性、基础性、兜底性民生建设”。 ... 治疗—出院回家—复发住院治疗'的'旋转 ...",
          "date": "7天前",
          "position": 60
        },
        {
          "title": "经济低迷刺激“五失人员” 中国报复社会型暴力事件激增恐慌蔓延",
          "link": "https://www.voachinese.com/a/china-faces-surge-in-violent-attacks-on-innocents-amid-economic-downturn-20241025/7839412.html",
          "snippet": "... 性也大幅增加。 ... 10月23日夜，山东青岛，一辆混凝土搅拌车撞向多部车辆，当地警方称司机涉嫌醉驾，事故造成3人受伤留院治疗。 ... 肯定重视安全防范，但也 ...",
          "date": "2024年10月26日",
          "position": 61
        },
        {
          "title": "LGBT 肯定治疗与实践 - Bilibili",
          "link": "https://www.bilibili.com/read/cv7814045/",
          "snippet": "性少数人群在心理咨询、心理治疗中通常面临和异性恋人群同样的问题。但是，Chernin 和Johnson (2003) 指出，虽然面临相似的心理问题，同性恋人群在 ...",
          "date": "2020年10月2日",
          "position": 62
        },
        {
          "title": "HRC | Map: Attacks on Gender Affirming Care by State",
          "link": "https://www.hrc.org/resources/attacks-on-gender-affirming-care-by-state-map",
          "snippet": "In a coordinated push led by national anti-LGBTQ+ hate groups, legislators across the country have overridden the recommendations of the American medical…",
          "position": 63
        },
        {
          "title": "免疫性疾病正在“围剿”主播？医生提醒：与环境饮食有关 - 上观新闻",
          "link": "https://www.jfdaily.com/news/detail?id=814123",
          "snippet": "应该如何避免和治疗？如果高强度工作导致身体受损，公司应该承担部分责任吗？上游新闻（报料邮箱：baoliaosy@163.com）记者 ...",
          "date": "2天前",
          "position": 64
        },
        {
          "title": "性別歧視- 平等機會委員會",
          "link": "https://www.eoc.org.hk/zh-hk/legal-services/significant-court-cases/hong-kong/sex-discrimination",
          "snippet": "原告人於2007年11月一宗交通意外中受傷，需不時請病假看醫生和接受物理治療。 ... 兩部分的答覆必須同時為肯定的，才能證實有直接歧視。 ... 第三，男女校設有男女生學 ...",
          "position": 65
        },
        {
          "title": "连续八年“霸榜” 广东为什么能？ - 南方网",
          "link": "https://news.southcn.com/node_54a44f01a2/b8c41232ba.shtml",
          "snippet": "这份肯定，既“意料之中”，又“来之不易”。 做强 ... 2020年，广东提出要培育发展20个战略性产业集群，如今雏形已现。 ... 自主研发治疗抑郁症的中药创新药参郁 ...",
          "date": "23小时前",
          "position": 66
        },
        {
          "title": "聚焦精神心理数智创新与康复行动全球业界大咖在温对话 - 温州新闻网",
          "link": "https://news.66wz.com/system/2024/11/03/105659757.shtml",
          "snippet": "论坛现场，加拿大健康科学院院士李新民分享了AI对精神医学诊断治疗 ... 性。”上海市精神卫生中心院长赵敏也肯定了智慧 ... 性大麻素和CB1型的大麻 ...",
          "date": "24小时前",
          "position": 67
        },
        {
          "title": "ICIs治疗晚期非小细胞肺癌免疫相关不良事件的系统综述及Meta分析",
          "link": "https://pmc.ncbi.nlm.nih.gov/articles/PMC7519956/",
          "snippet": "目前临床上对ir-AEs的管理一般基于基于药物的安全性报告、专家共识以及既往对自身免疫性疾病的认识。虽然目前ir-AEs发病的确切病理生理机制尚不明确，但可以肯定的是是由 ...",
          "position": 68
        },
        {
          "title": "创新升级、全球化加速，恒瑞医药“双曲线”驱动业绩增长 - 第一财经",
          "link": "https://m.yicai.com/news/102329359.html",
          "snippet": "今年以来，恒瑞医药共有7项创新药上市许可申请获得国家药监局受理，并取得6项突破性疗法认定，其中第三季度分别为3项和1项。 “恒瑞医药创新升级，全球化加速。”申万宏源 ...",
          "position": 69
        },
        {
          "title": "淺談放射線治療 - 高雄榮民總醫院-單位網",
          "link": "https://org.vghks.gov.tw/ct/News_Content.aspx?n=2044902FC839D045&sms=D59138EA3ED4269C&s=8C0FDD45235831A5",
          "snippet": "放射線治療大致可分為遠隔治療及近接治療。 ... 根治性放射治療因為要考慮到病人治療後的晚期效應 ... 所以放射線治療在目前腫瘤治療上所扮演的角色是肯定的，而且日趨重要.",
          "position": 70
        },
        {
          "title": "香港社会服务联会 - 社聯",
          "link": "https://www.hkcss.org.hk/?lang=zh-hans",
          "snippet": "... 肯定，自2022年開始至今年7月初，總共獲得29個獎項...，成績令人非常鼓舞，團隊方方面面的努力也令人十分感動！ 我感謝在推展房屋局過渡性房屋項目時，不論是我們的 ...",
          "position": 71
        },
        {
          "title": "默克中国宋发贤：多维度构建肿瘤治疗与患者康复支持体系- 经济观察网",
          "link": "http://www.eeo.com.cn/2024/1102/695849.shtml",
          "snippet": "... 性MET抑制剂，其问世标志着肿瘤罕见靶点治疗 ... “精准治疗或个体化治疗是一个系统工程，需要 ... 肯定还需要时间。” 他进一步表示，“未来，默 ...",
          "date": "2天前",
          "position": 72
        },
        {
          "title": "启明周报| 启明创投投资企业融资及动态速递Vol. 41, 2024",
          "link": "https://www.qimingvc.com/cn/news/%E5%90%AF%E6%98%8E%E5%91%A8%E6%8A%A5-%E5%90%AF%E6%98%8E%E5%88%9B%E6%8A%95%E6%8A%95%E8%B5%84%E4%BC%81%E4%B8%9A%E8%9E%8D%E8%B5%84%E5%8F%8A%E5%8A%A8%E6%80%81%E9%80%9F%E9%80%92-vol-41-2024",
          "snippet": "... 肯定，公司亦将藉此进一步推进全球化战略以及 ... 性及安全性的相似性。 03/ 神州细胞重组 ... 本次CDE对于HMI-115纳入突破性治疗药物品种的 ...",
          "date": "6天前",
          "position": 73
        },
        {
          "title": "山东将11项治疗性辅助生殖技术项目纳入医保 - 健康- 大众网",
          "link": "https://health.dzwww.com/jkxw/jrxw/202410/t20241030_15029242.htm",
          "snippet": "截至目前，山东治疗性辅助生殖共结算6.87万人次，基本医保基金支付8691.55万元，大大减轻了不孕不育患者等人群的生育医疗负担。",
          "date": "5天前",
          "position": 74
        },
        {
          "title": "患者送来锦旗感谢两位医生“揪出”早期输卵管癌 - 健康报",
          "link": "https://www.jkb.com.cn/hyfz/yy_hyzx/2024/1101/498773.html",
          "snippet": "刘蓉反复寻找证据确认，高度怀疑李女士的右输卵管有恶性肿瘤。 当李女士看到超声检查结果的那一刻，恐惧瞬间涌上心头，泪水夺眶而出。她怀着沉重的心情， ...",
          "date": "2天前",
          "position": 75
        },
        {
          "title": "復發難治型濾泡性淋巴瘤治療進展，國際指引列新一代口服標靶BTK ...",
          "link": "https://www.careonline.com.tw/2024/10/follicular-lymphoma-241007.html",
          "snippet": "... 治療經過兩線或以上全身治療後的復發或難治型濾泡性淋巴瘤（R/R FL），肯定其臨床優勢。 張明志醫師表示，復發難治型濾泡性淋巴瘤（R/R FL）在使用 ...",
          "date": "2024年10月7日",
          "position": 76
        },
        {
          "title": "三季报营收、净利双增长，恒瑞医药创新成果加速涌现 - 东方财富",
          "link": "https://wap.eastmoney.com/a/202410293220987779.html",
          "snippet": "... 性治疗品种，未来审批有望加速。 国际化战略稳步推进. 恒瑞医药稳步推进 ... 肯定。在9月7日至10日举办的2024年世界肺癌大会（WCLC）、9月13日至17日举办的 ...",
          "date": "7天前",
          "position": 77
        },
        {
          "title": "二次根管治疗对牙齿有伤害吗？一起来看二次根 ... - 贝色口腔- 牙齿矫正",
          "link": "https://m.beise.com/note/75345.html",
          "snippet": "... 治疗便成为了患者不得不面对的选项。这不禁让人心生疑虑：二次根管治疗 ... 因此，二次根管治疗的必要性在于，它能够尝试 ... 答案并非肯定，是否需要做根管， ...",
          "date": "1天前",
          "position": 78
        },
        {
          "title": "21健讯Daily｜药明康德第三季度收入重回百亿元规模；安斯泰来撤回 ...",
          "link": "https://wap.stockstar.com/detail/IG2024102900008163",
          "snippet": "10月28日，安斯泰来宣布撤回向欧洲药品管理局（EMA）递交的avacincaptad pegol（ACP）用于治疗年龄相关性黄斑变性（AMD）继发地图样萎缩（GA）的上市申请 ...",
          "date": "6天前",
          "position": 79
        },
        {
          "title": "Nature：雄激素治疗后的跨性别男性，免疫系统被重塑 - 医药招商新闻",
          "link": "https://news.100yiyao.net/detail/193597893.html",
          "snippet": "来源：生物世界2024-09-06 11:16. 在这项研究中，通过为23名跨性别男性（出生性别女性，但自我认同为男性）在性别肯定睾酮治疗之前和期间进行分析，揭示出性激素对免疫 ...",
          "position": 80
        },
        {
          "title": "國立臺灣大學醫學院附設醫院- 最新消息",
          "link": "https://www.ntuh.gov.tw/ntuh/News.action?q_type=-1&q_itemCode=13324",
          "snippet": "腎上腺高血壓病友的福音一站式專業診斷治療臺大醫院原發性高醛固酮症中心揭牌 ... 高醛固酮症團隊的努力得到了肯定 ... 肯定。未來，團隊將持續秉持初衷，不斷 ...",
          "date": "2023年5月10日",
          "position": 81
        },
        {
          "title": "南方医科大学皮肤病医院牵头成立广东省白癜风专病联盟 - 金羊健康",
          "link": "https://health.ycwb.com/2024-11/02/content_53029439.htm",
          "snippet": "白癜风是一种常见的后天性色素脱失性皮肤黏膜疾病，表现为白斑或白发。 ... 为提高白癜风疾病的诊断治疗水平，推动疾病诊疗 ... 中国医师协会皮肤科医师分会会 ...",
          "date": "1天前",
          "position": 82
        },
        {
          "title": "男子自以为魅力十足？老婆嫌弃多年！医生从他的身上割下10斤重……",
          "link": "https://www.ctdsb.net/c1659_202411/2295483.html",
          "snippet": "... 性对称性脂肪瘤病，为少见病。 ... 手术治疗主要包括手术切除治疗和脂肪抽吸术。 ... 医生介绍，几乎所有马德龙病患者都有长期的酗酒史，因此长期饮酒是该病的 ...",
          "date": "17小时前",
          "position": 83
        },
        {
          "title": "【跨性別承認制度一覽】強制完成下身手術最嚴苛歐洲多國邁向僅需 ...",
          "link": "https://gdottv.com/main/archives/30986",
          "snippet": "根據入境處提供的資訊，在司法覆核勝訴前，跨性別人士要更改身分證性別需要提交「已完成性別肯定手術」的醫學證明，包括：跨性別男性需切除子宮及卵巢，及 ...",
          "date": "2023年3月18日",
          "position": 84
        },
        {
          "title": "蓝芩颗粒治疗儿童急性上呼吸道感染真实世界研究总结会圆满召开",
          "link": "https://life.china.com/2024-11/01/content_375311.html",
          "snippet": "在总结发言环节，申教授对本次研究的成果和安全性表示肯定，本研究首次将Wong-Baker面部表情量表(WBS) 应用于中药研究的呼吸领域，并提出了进一步优化研究 ...",
          "date": "3天前",
          "position": 85
        },
        {
          "title": "推動「居住型處遇」戒癮治療雲檢與茄荖山莊簽署合作意向書",
          "link": "https://tw.news.yahoo.com/%E6%8E%A8%E5%8B%95-%E5%B1%85%E4%BD%8F%E5%9E%8B%E8%99%95%E9%81%87-%E6%88%92%E7%99%AE%E6%B2%BB%E7%99%82-%E9%9B%B2%E6%AA%A2%E8%88%87%E8%8C%84%E8%8D%96%E5%B1%B1%E8%8E%8A%E7%B0%BD%E7%BD%B2%E5%90%88%E4%BD%9C%E6%84%8F%E5%90%91%E6%9B%B8-075423877.html",
          "snippet": "... 治療案件之執行成效，雲林地檢署日前與全國唯一由衛生福利部與法務部合作設立的戒毒單位「藥癮治療性 ... 肯定，目前雲林縣轄內缺乏「長期居住型戒癮治療 ...",
          "date": "2天前",
          "position": 86
        },
        {
          "title": "问题解答！二次根管治疗牙冠还能用吗？原来牙冠能否继续使用取决 ...",
          "link": "https://m.beise.com/note/75346.html",
          "snippet": "... 治疗未能完全解决问题，或者牙齿状况进一步恶化时，就可能需要进行二次根管治疗 ... 目前，全瓷牙冠因其良好的美观性和耐用性而备受推崇。 ... 答案并非肯定， ...",
          "date": "1天前",
          "position": 87
        },
        {
          "title": "香港罕有跨性別武術家許瑋楓專訪：「我男變女，喜歡女生 - BBC",
          "link": "https://www.bbc.com/zhongwen/trad/chinese-news-54553312",
          "snippet": "... 性别刻板印象的香港跨性别武术家\", 節目全長5 ... 「我肯定這不單是一家公司的政策問題，希望由這 ... 她解釋說，原生性別、性別認同、性別表達、性 ...",
          "date": "2020年11月13日",
          "position": 88
        },
        {
          "title": "关于激素治疗：你需要了解的内容| Bangkok Hospital",
          "link": "https://www.bangkokhospital.com/zh/content/know-the-truth-before-taking-hormones",
          "snippet": "性别与激素的差异密切相关，这种差异可以通过多种方式表达。如果你想成为跨性别者，服用激素是一个很常见的开始。因此，在使用激素之前，充分了解相关知识非常重要。",
          "position": 89
        },
        {
          "title": "【专题报道】“治疗”还是“酷刑”？联合国人权专家剖析针对性少数群体 ...",
          "link": "https://news.un.org/zh/story/2020/07/1062101",
          "snippet": "男女同性恋、双性恋者、跨性别或多性别者是世界上遭受歧视、排斥甚至迫害最多的群体之一。在世界各地的每一个角落都存在着各种试图改变他们的性取向或 ...",
          "date": "2020年7月14日",
          "position": 90
        },
        {
          "title": "[PDF] 防止性取向和性别认同的暴力和歧视问题独立专家的任务 - ohchr",
          "link": "https://www.ohchr.org/Documents/Issues/SexualOrientation/Call_for_Inputs_CH_markup.pdf",
          "snippet": "一些获得许可的医学从业者，包括心理学家，进行认知行为疗. Page 2. 法，提供药物、电击疗法、厌恶手段等物理干预措施。 这些“治疗”. 的接受者包括从儿童 ...",
          "date": "2019年12月21日",
          "position": 91
        },
        {
          "title": "[PDF] 重点：性别认定护理",
          "link": "https://www.careoregon.org/docs/default-source/members/education-handouts/gender-affirming-care/gender-affirming-care-benefit-handout-simplified-chinese.pdf?sfvrsn=5d3ccc47_3",
          "snippet": "根据俄勒. 冈州法律，性别认定治疗指的是医疗护理提供者为治疗性别认同与出生时指定的性别不一致的人开出的. 任何手术、服务、药物、设备或产品。 请注意：在评估性别认定 ...",
          "position": 92
        }
      ],
      "credits": 2
    }
  ]
}